Workbook

Sheet 千牛数据
A1: 统计日期 | B1: 商品ID | C1: 商品名称 | D1: 主商品ID | E1: 商品类型 | F1: 货号 | G1: 商品状态 | H1: 商品标签 | I1: 商品访客数 | J1: 商品浏览量 | K1: 平均停留时长 | L1: 商品详情页跳出率 | M1: 商品收藏人数 | N1: 商品加购件数 | O1: 商品加购人数 | P1: 下单买家数 | Q1: 下单件数 | R1: 下单金额 | S1: 下单转化率 | T1: 支付买家数 | U1: 支付件数 | V1: 支付金额 | W1: 商品支付转化率 | X1: 支付新买家数 | Y1: 支付老买家数 | Z1: 老买家支付金额 | AA1: 聚划算支付金额 | AB1: 访客平均价值 | AC1: 成功退款金额 | AD1: 竞争力评分 | AE1: 年累计支付金额 | AF1: 月累计支付金额 | AG1: 月累计支付件数 | AH1: 搜索引导支付转化率 | AI1: 搜索引导访客数 | AJ1: 搜索引导支付买家数 | AK1: 结构化详情引导转化率 | AL1: 结构化详情引导成交占比
A2: 2026-01-01 | B2: 969105067992 | C2: LENNEA气质大毛领羽绒服外套女秋冬季连帽毛呢上衣小个子夹棉保暖 | D2: '969105067992 | E2: 主商品 | F2: 2025895 | G2: 当前在线 | H2: - | I2: 6560 | J2: 25528 | K2: 5.09 | L2: 0.6017 | M2: 220 | N2: 427 | O2: 400 | P2: 90 | Q2: 105 | R2: 30088 | S2: 0.0137 | T2: 80 | U2: 86 | V2: 24642 | W2: 0.0122 | X2: 75 | Y2: 5 | Z2: 2206 | AA2: 0 | AB2: 3.76 | AC2: 15685.2 | AD2: - | AE2: 24642 | AF2: 24642 | AG2: 86 | AH2: 0.026 | AI2: 845 | AJ2: 22 | AK2: - | AL2: -
A3: 2026-01-01 | B3: 973083694338 | C3: LENNEA连帽毛领棉服宽松简约棉衣冬季短款羽绒服面包服外套上衣女 | D3: '973083694338 | E3: 主商品 | F3: 2025890 | G3: 当前在线 | H3: - | I3: 2447 | J3: 6563 | K3: 5.89 | L3: 0.5954 | M3: 64 | N3: 124 | O3: 115 | P3: 25 | Q3: 28 | R3: 8689 | S3: 0.0102 | T3: 23 | U3: 25 | V3: 7879 | W3: 0.0094 | X3: 23 | Y3: 0 | Z3: 0 | AA3: 0 | AB3: 3.22 | AC3: 5302 | AD3: - | AE3: 7879 | AF3: 7879 | AG3: 25 | AH3: 0.0385 | AI3: 182 | AJ3: 7 | AK3: - | AL3: -
A4: 2026-01-01 | B4: 825735521554 | C4: LENNEA原创基础高立领面包服冬季通勤简约百搭宽松棉服保暖外套 | D4: '825735521554 | E4: 主商品 | F4: 2024878 | G4: 当前在线 | H4: - | I4: 2367 | J4: 6316 | K4: 7.21 | L4: 0.6527 | M4: 50 | N4: 91 | O4: 86 | P4: 20 | Q4: 24 | R4: 5256 | S4: 0.0084 | T4: 19 | U4: 20 | V4: 4380 | W4: 0.008 | X4: 19 | Y4: 0 | Z4: 0 | AA4: 0 | AB4: 1.85 | AC4: 2190 | AD4: - | AE4: 4380 | AF4: 4380 | AG4: 20 | AH4: 0.0282 | AI4: 177 | AJ4: 5 | AK4: - | AL4: -
A5: 2026-01-01 | B5: 970286397535 | C5: LENNEA小香风白色外套女秋冬2025新款深秋初冬高级短款羊毛感上衣 | D5: '970286397535 | E5: 主商品 | F5: - | G5: 当前在线 | H5: - | I5: 3257 | J5: 9039 | K5: 4.04 | L5: 0.6171 | M5: 76 | N5: 116 | O5: 109 | P5: 19 | Q5: 20 | R5: 5240 | S5: 0.0058 | T5: 15 | U5: 16 | V5: 4248 | W5: 0.0046 | X5: 13 | Y5: 2 | Z5: 636 | AA5: 0 | AB5: 1.3 | AC5: 4636 | AD5: - | AE5: 4248 | AF5: 4248 | AG5: 16 | AH5: 0.0397 | AI5: 126 | AJ5: 5 | AK5: - | AL5: -
A6: 2026-01-01 | B6: 972548387983 | C6: LENNEA藏青色毛领连帽棉服女冬季新款宽松保暖小个子百搭棉衣外套 | D6: '972548387983 | E6: 主商品 | F6: 2025918 | G6: 当前在线 | H6: - | I6: 1869 | J6: 3858 | K6: 4.61 | L6: 0.6207 | M6: 26 | N6: 64 | O6: 61 | P6: 15 | Q6: 17 | R6: 4590 | S6: 0.008 | T6: 14 | U6: 15 | V6: 4050 | W6: 0.0075 | X6: 13 | Y6: 1 | Z6: 270 | AA6: 0 | AB6: 2.17 | AC6: 2970 | AD6: - | AE6: 4050 | AF6: 4050 | AG6: 15 | AH6: 0.0377 | AI6: 53 | AJ6: 2 | AK6: - | AL6: -
A7: 2026-01-01 | B7: 987923069100 | C7: LENNEA高级感千金风金扣双面呢大衣女冬新款毛呢外套中长款小个子 | D7: '987923069100 | E7: 主商品 | F7: 2025302 | G7: 当前在线 | H7: - | I7: 1425 | J7: 4681 | K7: 4.35 | L7: 0.3509 | M7: 28 | N7: 117 | O7: 115 | P7: 12 | Q7: 12 | R7: 3588 | S7: 0.0084 | T7: 11 | U7: 11 | V7: 3289 | W7: 0.0077 | X7: 10 | Y7: 1 | Z7: 299 | AA7: 0 | AB7: 2.31 | AC7: 3588 | AD7: - | AE7: 3289 | AF7: 3289 | AG7: 11 | AH7: 0.0066 | AI7: 151 | AJ7: 1 | AK7: - | AL7: -
A8: 2026-01-01 | B8: 974433252366 | C8: LENNEA黑色短款木耳边棉服女韩系百搭面包服棉衣宽松休闲外套 | D8: '974433252366 | E8: 主商品 | F8: 2025902 | G8: 当前在线 | H8: - | I8: 3121 | J8: 6815 | K8: 4.37 | L8: 0.7107 | M8: 36 | N8: 77 | O8: 75 | P8: 12 | Q8: 13 | R8: 3094 | S8: 0.0038 | T8: 12 | U8: 12 | V8: 2856 | W8: 0.0038 | X8: 11 | Y8: 1 | Z8: 238 | AA8: 0 | AB8: 0.92 | AC8: 1190 | AD8: - | AE8: 2856 | AF8: 2856 | AG8: 12 | AH8: 0.0138 | AI8: 145 | AJ8: 2 | AK8: - | AL8: -
A9: 2026-01-01 | B9: 987169874467 | C9: LENNEA毛领双排扣短款毛呢羊毛大衣连帽外套女收腰秋冬加厚上衣 | D9: '987169874467 | E9: 主商品 | F9: 2025998 | G9: 当前在线 | H9: - | I9: 757 | J9: 2107 | K9: 6.48 | L9: 0.4518 | M9: 14 | N9: 63 | O9: 61 | P9: 8 | Q9: 10 | R9: 3090 | S9: 0.0106 | T9: 8 | U9: 9 | V9: 2781 | W9: 0.0106 | X9: 6 | Y9: 2 | Z9: 927 | AA9: 0 | AB9: 3.67 | AC9: 4017 | AD9: - | AE9: 2781 | AF9: 2781 | AG9: 9 | AH9: 0.0411 | AI9: 73 | AJ9: 3 | AK9: - | AL9: -
A10: 2026-01-01 | B10: 974413116307 | C10: LENNEA立领短款高腰棉服女冬季新款厚外套面包服棉袄纯色简约上衣 | D10: '974413116307 | E10: 主商品 | F10: 2025892 | G10: 当前在线 | H10: - | I10: 1056 | J10: 2243 | K10: 4.71 | L10: 0.5843 | M10: 17 | N10: 30 | O10: 30 | P10: 10 | Q10: 11 | R10: 2409 | S10: 0.0095 | T10: 11 | U10: 11 | V10: 2409 | W10: 0.0104 | X10: 10 | Y10: 1 | Z10: 219 | AA10: 0 | AB10: 2.28 | AC10: 2190 | AD10: - | AE10: 2409 | AF10: 2409 | AG10: 11 | AH10: 0.023 | AI10: 87 | AJ10: 2 | AK10: - | AL10: -
A11: 2026-01-01 | B11: 992234348721 | C11: LENNEA冬季新款绞花针织拼接长袖波点棉服女上衣保暖短外套棉衣 | D11: '992234348721 | E11: 主商品 | F11: 2025991 | G11: 当前在线 | H11: - | I11: 1890 | J11: 4361 | K11: 4.25 | L11: 0.6169 | M11: 47 | N11: 102 | O11: 100 | P11: 9 | Q11: 9 | R11: 2691 | S11: 0.0048 | T11: 8 | U11: 8 | V11: 2392 | W11: 0.0042 | X11: 8 | Y11: 0 | Z11: 0 | AA11: 0 | AB11: 1.27 | AC11: 1495 | AD11: - | AE11: 2392 | AF11: 2392 | AG11: 8 | AH11: 0.0256 | AI11: 117 | AJ11: 3 | AK11: - | AL11: -
A12: 2026-01-01 | B12: 986610503692 | C12: LENNEA毛毛外套女冬季短款翻领正肩皮毛一体环保毛皮草上衣女冬 | D12: '986610503692 | E12: 主商品 | F12: 2025997 | G12: 当前在线 | H12: - | I12: 927 | J12: 2338 | K12: 4.63 | L12: 0.5599 | M12: 16 | N12: 56 | O12: 53 | P12: 6 | Q12: 7 | R12: 1806 | S12: 0.0065 | T12: 6 | U12: 7 | V12: 1806 | W12: 0.0065 | X12: 4 | Y12: 2 | Z12: 774 | AA12: 0 | AB12: 1.95 | AC12: 774 | AD12: - | AE12: 1806 | AF12: 1806 | AG12: 7 | AH12: 0.0093 | AI12: 108 | AJ12: 1 | AK12: - | AL12: -
A13: 2026-01-01 | B13: 763414867633 | C13: LENNEA法式气质小香风短款外套女2025秋冬加绒显瘦高级感羽绒上衣 | D13: '763414867633 | E13: 主商品 | F13: 20401028 | G13: 当前在线 | H13: - | I13: 148 | J13: 481 | K13: 4.76 | L13: 0.5541 | M13: 5 | N13: 13 | O13: 13 | P13: 5 | Q13: 5 | R13: 1372 | S13: 0.0338 | T13: 5 | U13: 5 | V13: 1372 | W13: 0.0338 | X13: 5 | Y13: 0 | Z13: 0 | AA13: 0 | AB13: 9.27 | AC13: 1134 | AD13: - | AE13: 1372 | AF13: 1372 | AG13: 5 | AH13: 0.037 | AI13: 54 | AJ13: 2 | AK13: - | AL13: -
A14: 2026-01-01 | B14: 843240069717 | C14: LENNEA连帽羽绒服女冬季2025新款面包服超好看设计感小众过冬外套 | D14: '843240069717 | E14: 主商品 | F14: KPAW2023904 | G14: 当前在线 | H14: - | I14: 124 | J14: 318 | K14: 5.05 | L14: 0.3065 | M14: 4 | N14: 5 | O14: 4 | P14: 3 | Q14: 3 | R14: 1191 | S14: 0.0242 | T14: 3 | U14: 3 | V14: 1191 | W14: 0.0242 | X14: 3 | Y14: 0 | Z14: 0 | AA14: 0 | AB14: 9.6 | AC14: 397 | AD14: - | AE14: 1191 | AF14: 1191 | AG14: 3 | AH14: 0.0571 | AI14: 35 | AJ14: 2 | AK14: - | AL14: -
A15: 2026-01-01 | B15: 825738021055 | C15: LENNEA原创高质感白色小香风圆领毛呢上衣肌理感加棉短外套 | D15: '825738021055 | E15: 主商品 | F15: 2024879 | G15: 当前在线 | H15: - | I15: 380 | J15: 675 | K15: 21.53 | L15: 0.7553 | M15: 3 | N15: 11 | O15: 10 | P15: 4 | Q15: 5 | R15: 1190 | S15: 0.0105 | T15: 4 | U15: 5 | V15: 1190 | W15: 0.0105 | X15: 4 | Y15: 0 | Z15: 0 | AA15: 0 | AB15: 3.13 | AC15: 0 | AD15: - | AE15: 1190 | AF15: 1190 | AG15: 5 | AH15: 0 | AI15: 25 | AJ15: 0 | AK15: - | AL15: -
A16: 2026-01-01 | B16: 959252941279 | C16: LENNEA波点花边袖黑色长袖针织开衫女百搭修身打底衫早秋上衣 | D16: '959252941279 | E16: 主商品 | F16: - | G16: 当前在线 | H16: - | I16: 548 | J16: 1623 | K16: 4.95 | L16: 0.5675 | M16: 9 | N16: 60 | O16: 49 | P16: 8 | Q16: 9 | R16: 1332 | S16: 0.0146 | T16: 8 | U16: 8 | V16: 1184 | W16: 0.0146 | X16: 8 | Y16: 0 | Z16: 0 | AA16: 0 | AB16: 2.16 | AC16: 1142 | AD16: - | AE16: 1184 | AF16: 1184 | AG16: 8 | AH16: 0.0247 | AI16: 81 | AJ16: 2 | AK16: - | AL16: -
A17: 2026-01-01 | B17: 847216230061 | C17: LENNEA原创设计感条纹蝴蝶结棉服外套冬季加绒加厚保暖棉衣女 | D17: '847216230061 | E17: 主商品 | F17: 2024911 | G17: 当前在线 | H17: - | I17: 227 | J17: 540 | K17: 5.58 | L17: 0.37 | M17: 6 | N17: 11 | O17: 11 | P17: 3 | Q17: 3 | R17: 783 | S17: 0.0132 | T17: 3 | U17: 3 | V17: 783 | W17: 0.0132 | X17: 3 | Y17: 0 | Z17: 0 | AA17: 0 | AB17: 3.45 | AC17: 783 | AD17: - | AE17: 783 | AF17: 783 | AG17: 3 | AH17: 0 | AI17: 28 | AJ17: 0 | AK17: - | AL17: -
A18: 2026-01-01 | B18: 987920341922 | C18: LENNEA复古毛领连帽卫衣女202秋冬韩系慵懒风高级感拉链加厚外套 | D18: '987920341922 | E18: 主商品 | F18: 2025303 | G18: 当前在线 | H18: - | I18: 230 | J18: 613 | K18: 3.78 | L18: 0.4652 | M18: 6 | N18: 12 | O18: 12 | P18: 2 | Q18: 3 | R18: 774 | S18: 0.0087 | T18: 1 | U18: 2 | V18: 516 | W18: 0.0043 | X18: 1 | Y18: 0 | Z18: 0 | AA18: 0 | AB18: 2.24 | AC18: 258 | AD18: - | AE18: 516 | AF18: 516 | AG18: 2 | AH18: 0 | AI18: 20 | AJ18: 0 | AK18: - | AL18: -
A19: 2026-01-01 | B19: 990762914987 | C19: LENNEA白色收腰羽绒服女90白鸭绒冬季显瘦毛领连帽保暖外套小个子 | D19: '990762914987 | E19: 主商品 | F19: 2025306 | G19: 当前在线 | H19: - | I19: 159 | J19: 450 | K19: 3.94 | L19: 0.195 | M19: 8 | N19: 22 | O19: 22 | P19: 1 | Q19: 1 | R19: 488 | S19: 0.0063 | T19: 1 | U19: 1 | V19: 488 | W19: 0.0063 | X19: 1 | Y19: 0 | Z19: 0 | AA19: 0 | AB19: 3.07 | AC19: 488 | AD19: - | AE19: 488 | AF19: 488 | AG19: 1 | AH19: 0 | AI19: 17 | AJ19: 0 | AK19: - | AL19: -
A20: 2026-01-01 | B20: 970314453475 | C20: LENNEA藏青色毛领外套女秋冬季新款设计感短款修身显瘦夹棉上衣 | D20: '970314453475 | E20: 主商品 | F20: 2025901 | G20: 当前在线 | H20: - | I20: 610 | J20: 1154 | K20: 4.03 | L20: 0.5279 | M20: 9 | N20: 17 | O20: 16 | P20: 2 | Q20: 2 | R20: 456 | S20: 0.0033 | T20: 2 | U20: 2 | V20: 456 | W20: 0.0033 | X20: 2 | Y20: 0 | Z20: 0 | AA20: 0 | AB20: 0.75 | AC20: 683.9 | AD20: - | AE20: 456 | AF20: 456 | AG20: 2 | AH20: 0.0357 | AI20: 28 | AJ20: 1 | AK20: - | AL20: -
A21: 2026-01-01 | B21: 808571688488 | C21: LENNEA原创设计气质垂感直筒毛呢阔腿裤宽松百搭显瘦拖地休闲裤女 | D21: '808571688488 | E21: 主商品 | F21: 2024867 | G21: 当前在线 | H21: - | I21: 18 | J21: 24 | K21: 4.37 | L21: 0.0556 | M21: 0 | N21: 3 | O21: 3 | P21: 2 | Q21: 2 | R21: 370 | S21: 0.1111 | T21: 2 | U21: 2 | V21: 370 | W21: 0.1111 | X21: 2 | Y21: 0 | Z21: 0 | AA21: 0 | AB21: 20.56 | AC21: 185 | AD21: - | AE21: 370 | AF21: 370 | AG21: 2 | AH21: 0 | AI21: 0 | AJ21: 0 | AK21: - | AL21: -
A22: 2026-01-01 | B22: 1008943112755 | C22: LENNEA 费尔岛风大毛领连帽棉服女冬季宽松加厚保暖面包服外套 | D22: '1008943112755 | E22: 主商品 | F22: 2025890-2 | G22: 当前在线 | H22: - | I22: 84 | J22: 131 | K22: 4.04 | L22: 0.369 | M22: 1 | N22: 4 | O22: 4 | P22: 1 | Q22: 1 | R22: 298 | S22: 0.0119 | T22: 1 | U22: 1 | V22: 298 | W22: 0.0119 | X22: 1 | Y22: 0 | Z22: 0 | AA22: 0 | AB22: 3.55 | AC22: 0 | AD22: - | AE22: 298 | AF22: 298 | AG22: 1 | AH22: 0 | AI22: 0 | AJ22: 0 | AK22: - | AL22: -
A23: 2026-01-01 | B23: 825530682410 | C23: LENNEA仿皮草环保韩女托卡毛毛外套立领加厚款秋冬羊羔毛大衣 | D23: '825530682410 | E23: 主商品 | F23: 2024881 | G23: 当前在线 | H23: - | I23: 19 | J23: 37 | K23: 2.54 | L23: 0.3684 | M23: 1 | N23: 0 | O23: 0 | P23: 2 | Q23: 2 | R23: 556 | S23: 0.1053 | T23: 1 | U23: 1 | V23: 278 | W23: 0.0526 | X23: 0 | Y23: 1 | Z23: 278 | AA23: 0 | AB23: 14.63 | AC23: 278 | AD23: - | AE23: 278 | AF23: 278 | AG23: 1 | AH23: 0 | AI23: 2 | AJ23: 0 | AK23: - | AL23: -
A24: 2026-01-01 | B24: 980262719728 | C24: LENNEA复古美拉德棕色毛呢外套短款修身冬季小个子羊羔毛毛上衣 | D24: '980262719728 | E24: 主商品 | F24: 2025987 | G24: 当前在线 | H24: - | I24: 1084 | J24: 1662 | K24: 5.72 | L24: 0.7122 | M24: 12 | N24: 22 | O24: 22 | P24: 1 | Q24: 1 | R24: 278 | S24: 0.0009 | T24: 1 | U24: 1 | V24: 278 | W24: 0.0009 | X24: 1 | Y24: 0 | Z24: 0 | AA24: 0 | AB24: 0.26 | AC24: 0 | AD24: - | AE24: 278 | AF24: 278 | AG24: 1 | AH24: 0 | AI24: 13 | AJ24: 0 | AK24: - | AL24: -
A25: 2026-01-01 | B25: 847170293443 | C25: LENNEA原创短款格子棉服简约立领高级感通勤复古百搭棉袄保暖外套 | D25: '847170293443 | E25: 主商品 | F25: 2024909 | G25: 当前在线 | H25: - | I25: 69 | J25: 118 | K25: 6.09 | L25: 0.1739 | M25: 2 | N25: 5 | O25: 5 | P25: 1 | Q25: 1 | R25: 270 | S25: 0.0145 | T25: 1 | U25: 1 | V25: 270 | W25: 0.0145 | X25: 1 | Y25: 0 | Z25: 0 | AA25: 0 | AB25: 3.91 | AC25: 0 | AD25: - | AE25: 270 | AF25: 270 | AG25: 1 | AH25: 0 | AI25: 8 | AJ25: 0 | AK25: - | AL25: -
A26: 2026-01-01 | B26: 987928549020 | C26: LENNEA连帽毛领棉服宽松简约棉衣冬季短款面包服连帽外套上衣女 | D26: '987928549020 | E26: 主商品 | F26: 2025890 | G26: 当前在线 | H26: - | I26: 222 | J26: 361 | K26: 4.05 | L26: 0.3198 | M26: 2 | N26: 8 | O26: 8 | P26: 1 | Q26: 1 | R26: 270 | S26: 0.0045 | T26: 1 | U26: 1 | V26: 270 | W26: 0.0045 | X26: 1 | Y26: 0 | Z26: 0 | AA26: 0 | AB26: 1.22 | AC26: 0 | AD26: - | AE26: 270 | AF26: 270 | AG26: 1 | AH26: 0.125 | AI26: 8 | AJ26: 1 | AK26: - | AL26: -
A27: 2026-01-01 | B27: 874018241490 | C27: LENNEA原创蓝色小香风春秋新款财阀千金风气质收腰开衫毛呢外套女 | D27: '874018241490 | E27: 主商品 | F27: 2025605 | G27: 当前在线 | H27: - | I27: 47 | J27: 162 | K27: 2.74 | L27: 0.4681 | M27: 2 | N27: 1 | O27: 1 | P27: 1 | Q27: 1 | R27: 261 | S27: 0.0213 | T27: 1 | U27: 1 | V27: 261 | W27: 0.0213 | X27: 1 | Y27: 0 | Z27: 0 | AA27: 0 | AB27: 5.55 | AC27: 261 | AD27: - | AE27: 261 | AF27: 261 | AG27: 1 | AH27: 0 | AI27: 6 | AJ27: 0 | AK27: - | AL27: -
A28: 2026-01-01 | B28: 987173298099 | C28: LENNEA棕色系带麂皮外套女2025秋冬新款皮毛一体高级感修身短上衣 | D28: '987173298099 | E28: 主商品 | F28: 2025999 | G28: 当前在线 | H28: - | I28: 23 | J28: 75 | K28: 4.39 | L28: 0.3043 | M28: 2 | N28: 3 | O28: 3 | P28: 1 | Q28: 1 | R28: 258 | S28: 0.0435 | T28: 1 | U28: 1 | V28: 258 | W28: 0.0435 | X28: 1 | Y28: 0 | Z28: 0 | AA28: 0 | AB28: 11.22 | AC28: 0 | AD28: - | AE28: 258 | AF28: 258 | AG28: 1 | AH28: 0 | AI28: 2 | AJ28: 0 | AK28: - | AL28: -
A29: 2026-01-01 | B29: 972565039550 | C29: LENNEA韩系奶黄色立领羽绒棉服女2025年秋冬新款小个子保暖棉衣 | D29: '972565039550 | E29: 主商品 | F29: 2025897 | G29: 当前在线 | H29: - | I29: 82 | J29: 178 | K29: 7.28 | L29: 0.3659 | M29: 2 | N29: 14 | O29: 12 | P29: 1 | Q29: 1 | R29: 248 | S29: 0.0122 | T29: 1 | U29: 1 | V29: 248 | W29: 0.0122 | X29: 1 | Y29: 0 | Z29: 0 | AA29: 0 | AB29: 3.02 | AC29: 0 | AD29: - | AE29: 248 | AF29: 248 | AG29: 1 | AH29: 0 | AI29: 13 | AJ29: 0 | AK29: - | AL29: -
A30: 2026-01-01 | B30: 1007363114226 | C30: LENNEA 波点毛绒连帽外套女冬大毛领毛球装饰软糯可爱减龄短外套 | D30: '1007363114226 | E30: 主商品 | F30: 2025327 | G30: 当前在线 | H30: - | I30: 104 | J30: 144 | K30: 4.57 | L30: 0.5865 | M30: 1 | N30: 9 | O30: 8 | P30: 2 | Q30: 2 | R30: 496 | S30: 0.0192 | T30: 1 | U30: 1 | V30: 248 | W30: 0.0096 | X30: 1 | Y30: 0 | Z30: 0 | AA30: 0 | AB30: 2.38 | AC30: 0 | AD30: - | AE30: 248 | AF30: 248 | AG30: 1 | AH30: 0 | AI30: 0 | AJ30: 0 | AK30: - | AL30: -
A31: 2026-01-01 | B31: 728037000377 | C31: LENNEA 25/AW 原创秋冬无领女正肩修身短款小香风学院夹克外套 | D31: '728037000377 | E31: 主商品 | F31: - | G31: 当前在线 | H31: - | I31: 86 | J31: 330 | K31: 5.77 | L31: 0.4651 | M31: 3 | N31: 11 | O31: 6 | P31: 2 | Q31: 3 | R31: 593 | S31: 0.0233 | T31: 1 | U31: 1 | V31: 238 | W31: 0.0116 | X31: 1 | Y31: 0 | Z31: 0 | AA31: 0 | AB31: 2.77 | AC31: 117 | AD31: - | AE31: 238 | AF31: 238 | AG31: 1 | AH31: 0 | AI31: 17 | AJ31: 0 | AK31: - | AL31: -
A32: 2026-01-01 | B32: 920335022314 | C32: LENNEA法式拼接连衣裙女夏季新款简约气质收腰显瘦无袖小众裙子 | D32: '920335022314 | E32: 主商品 | F32: 2025837 | G32: 当前在线 | H32: - | I32: 8 | J32: 9 | K32: 5.86 | L32: 0.25 | M32: 0 | N32: 1 | O32: 1 | P32: 1 | Q32: 1 | R32: 236 | S32: 0.125 | T32: 1 | U32: 1 | V32: 236 | W32: 0.125 | X32: 1 | Y32: 0 | Z32: 0 | AA32: 0 | AB32: 29.5 | AC32: 236 | AD32: - | AE32: 236 | AF32: 236 | AG32: 1 | AH32: 0 | AI32: 0 | AJ32: 0 | AK32: - | AL32: -
A33: 2026-01-01 | B33: 980263183781 | C33: LENNEA撞色条纹连帽大毛领羊羔毛外套女冬季宽松保暖圈圈毛棉衣 | D33: '980263183781 | E33: 主商品 | F33: 2025990 | G33: 已下架 | H33: - | I33: 153 | J33: 367 | K33: 2.87 | L33: 0.451 | M33: 1 | N33: 5 | O33: 5 | P33: 1 | Q33: 1 | R33: 228 | S33: 0.0065 | T33: 1 | U33: 1 | V33: 228 | W33: 0.0065 | X33: 1 | Y33: 0 | Z33: 0 | AA33: 0 | AB33: 1.49 | AC33: 228 | AD33: - | AE33: 228 | AF33: 228 | AG33: 1 | AH33: 0 | AI33: 20 | AJ33: 0 | AK33: - | AL33: -
A34: 2026-01-01 | B34: 905004041827 | C34: LENNEA原创蕾丝荡领短袖t恤女夏季纯欲设计感斜肩别致韩系上衣 | D34: '905004041827 | E34: 主商品 | F34: 2025932 | G34: 当前在线 | H34: - | I34: 37 | J34: 88 | K34: 3.71 | L34: 0.2973 | M34: 2 | N34: 5 | O34: 4 | P34: 1 | Q34: 1 | R34: 227 | S34: 0.027 | T34: 1 | U34: 1 | V34: 227 | W34: 0.027 | X34: 0 | Y34: 1 | Z34: 227 | AA34: 0 | AB34: 6.14 | AC34: 0 | AD34: - | AE34: 227 | AF34: 227 | AG34: 1 | AH34: 0 | AI34: 2 | AJ34: 0 | AK34: - | AL34: -
A35: 2026-01-01 | B35: 858672318475 | C35: LENNEA蝴蝶结格子拼接设计感宽松直筒拖地高腰牛仔裤女显瘦长裤 | D35: '858672318475 | E35: 主商品 | F35: 2024913 | G35: 当前在线 | H35: - | I35: 76 | J35: 172 | K35: 5.12 | L35: 0.2763 | M35: 4 | N35: 7 | O35: 7 | P35: 1 | Q35: 2 | R35: 370 | S35: 0.0132 | T35: 1 | U35: 1 | V35: 185 | W35: 0.0132 | X35: 1 | Y35: 0 | Z35: 0 | AA35: 0 | AB35: 2.43 | AC35: 370 | AD35: - | AE35: 185 | AF35: 185 | AG35: 1 | AH35: 0 | AI35: 10 | AJ35: 0 | AK35: - | AL35: -
A36: 2026-01-01 | B36: 847172837136 | C36: LENNEA宽松休闲毛呢裤女高腰百搭显瘦阔腿裤直筒简约拖地长裤 | D36: '847172837136 | E36: 主商品 | F36: 2024910 | G36: 当前在线 | H36: - | I36: 22 | J36: 40 | K36: 5.4 | L36: 0.4545 | M36: 0 | N36: 2 | O36: 2 | P36: 1 | Q36: 1 | R36: 170 | S36: 0.0455 | T36: 1 | U36: 1 | V36: 170 | W36: 0.0455 | X36: 1 | Y36: 0 | Z36: 0 | AA36: 0 | AB36: 7.73 | AC36: 0 | AD36: - | AE36: 170 | AF36: 170 | AG36: 1 | AH36: 0 | AI36: 5 | AJ36: 0 | AK36: - | AL36: -
A37: 2026-01-01 | B37: 988564242366 | C37: 【秋冬合集】LENNEA双十一惊喜福袋粉丝福利抢购秋冬款上衣外套 | D37: '988564242366 | E37: 主商品 | F37: - | G37: 当前在线 | H37: - | I37: 156 | J37: 363 | K37: 9.49 | L37: 0.3333 | M37: 2 | N37: 10 | O37: 10 | P37: 1 | Q37: 1 | R37: 127 | S37: 0.0064 | T37: 1 | U37: 1 | V37: 127 | W37: 0.0064 | X37: 0 | Y37: 1 | Z37: 127 | AA37: 0 | AB37: 0.81 | AC37: 412 | AD37: - | AE37: 127 | AF37: 127 | AG37: 1 | AH37: 0 | AI37: 39 | AJ37: 0 | AK37: - | AL37: -
A38: 2026-01-01 | B38: 926919925240 | C38: LENNEA粉色蓬蓬花苞半身裙女夏季新款设计感高腰显瘦a字芭蕾裤裙 | D38: '926919925240 | E38: 主商品 | F38: 2025999 | G38: 当前在线 | H38: - | I38: 23 | J38: 40 | K38: 5.27 | L38: 0.4783 | M38: 0 | N38: 2 | O38: 2 | P38: 1 | Q38: 1 | R38: 125 | S38: 0.0435 | T38: 1 | U38: 1 | V38: 125 | W38: 0.0435 | X38: 1 | Y38: 0 | Z38: 0 | AA38: 0 | AB38: 5.43 | AC38: 0 | AD38: - | AE38: 125 | AF38: 125 | AG38: 1 | AH38: 0.0769 | AI38: 13 | AJ38: 1 | AK38: - | AL38: -
A39: 2026-01-01 | B39: 920848709238 | C39: LENNEA甜美少女感娃娃领衬衫女白色短袖衬衣纯色显瘦休闲薄款上衣 | D39: '920848709238 | E39: 主商品 | F39: 2025954 | G39: 当前在线 | H39: - | I39: 14 | J39: 22 | K39: 4.11 | L39: 0.5 | M39: 1 | N39: 1 | O39: 1 | P39: 1 | Q39: 1 | R39: 114 | S39: 0.0714 | T39: 1 | U39: 1 | V39: 114 | W39: 0.0714 | X39: 1 | Y39: 0 | Z39: 0 | AA39: 0 | AB39: 8.14 | AC39: 114 | AD39: - | AE39: 114 | AF39: 114 | AG39: 1 | AH39: 0 | AI39: 1 | AJ39: 0 | AK39: - | AL39: -
A40: 2026-01-01 | B40: 728030472469 | C40: LENNEA 23/AW 原创秋冬女长袖通勤宽松宽松高腰学生设计条纹衬衫 | D40: '728030472469 | E40: 主商品 | F40: - | G40: 当前在线 | H40: - | I40: 14 | J40: 25 | K40: 5.54 | L40: 0.3571 | M40: 2 | N40: 0 | O40: 0 | P40: 0 | Q40: 0 | R40: 0 | S40: 0 | T40: 0 | U40: 0 | V40: 0 | W40: 0 | X40: 0 | Y40: 0 | Z40: 0 | AA40: 0 | AB40: 0 | AC40: 0 | AD40: - | AE40: 0 | AF40: 0 | AG40: 0 | AH40: 0 | AI40: 2 | AJ40: 0 | AK40: - | AL40: -
A41: 2026-01-01 | B41: 728377574604 | C41: LENNEA 23/AW 秋冬女上衣短款高腰长袖正装白色打底通勤学生衬衫 | D41: '728377574604 | E41: 主商品 | F41: - | G41: 当前在线 | H41: - | I41: 1 | J41: 1 | K41: 3.96 | L41: 0 | M41: 1 | N41: 0 | O41: 0 | P41: 0 | Q41: 0 | R41: 0 | S41: 0 | T41: 0 | U41: 0 | V41: 0 | W41: 0 | X41: 0 | Y41: 0 | Z41: 0 | AA41: 0 | AB41: 0 | AC41: 0 | AD41: - | AE41: 0 | AF41: 0 | AG41: 0 | AH41: 0 | AI41: 0 | AJ41: 0 | AK41: - | AL41: -
A42: 2026-01-01 | B42: 741229892202 | C42: LENNEA 23/AW 冬季女士翻领拼接羊羔毛白鸭绒毛领加厚羽绒服外套 | D42: '741229892202 | E42: 主商品 | F42: 10304017 | G42: 已下架 | H42: - | I42: 4 | J42: 15 | K42: 9.22 | L42: 0 | M42: 0 | N42: 0 | O42: 0 | P42: 0 | Q42: 0 | R42: 0 | S42: 0 | T42: 0 | U42: 0 | V42: 0 | W42: 0 | X42: 0 | Y42: 0 | Z42: 0 | AA42: 0 | AB42: 0 | AC42: 0 | AD42: - | AE42: 0 | AF42: 0 | AG42: 0 | AH42: 0 | AI42: 1 | AJ42: 0 | AK42: - | AL42: -
A43: 2026-01-01 | B43: 741613131637 | C43: LENNEA 24/AW 原创冬季 富家千金 冰雪飞狐 环保皮草毛绒外套 | D43: '741613131637 | E43: 主商品 | F43: 10304019 | G43: 已下架 | H43: - | I43: 1 | J43: 1 | K43: 1.89 | L43: 0 | M43: 0 | N43: 0 | O43: 0 | P43: 0 | Q43: 0 | R43: 0 | S43: 0 | T43: 0 | U43: 0 | V43: 0 | W43: 0 | X43: 0 | Y43: 0 | Z43: 0 | AA43: 0 | AB43: 0 | AC43: 0 | AD43: - | AE43: 0 | AF43: 0 | AG43: 0 | AH43: 0 | AI43: 0 | AJ43: 0 | AK43: - | AL43: -
A44: 2026-01-01 | B44: 750458195077 | C44: 补差价专用 | D44: '750458195077 | E44: 主商品 | F44: - | G44: 当前在线 | H44: - | I44: 0 | J44: 0 | K44: 0 | L44: 0 | M44: 0 | N44: 0 | O44: 0 | P44: 0 | Q44: 0 | R44: 0 | S44: 0 | T44: 0 | U44: 0 | V44: 0 | W44: 0 | X44: 0 | Y44: 0 | Z44: 0 | AA44: 0 | AB44: 0 | AC44: 5 | AD44: - | AE44: 0 | AF44: 0 | AG44: 0 | AH44: 0 | AI44: 0 | AJ44: 0 | AK44: - | AL44: -
A45: 2026-01-01 | B45: 763369721441 | C45: LENNEA美式复古做旧显瘦牛仔裤高腰水洗微喇叭长裤2025春新款 | D45: '763369721441 | E45: 主商品 | F45: 20401027 | G45: 已下架 | H45: - | I45: 3 | J45: 5 | K45: 1.58 | L45: 0.3333 | M45: 0 | N45: 0 | O45: 0 | P45: 0 | Q45: 0 | R45: 0 | S45: 0 | T45: 0 | U45: 0 | V45: 0 | W45: 0 | X45: 0 | Y45: 0 | Z45: 0 | AA45: 0 | AB45: 0 | AC45: 0 | AD45: - | AE45: 0 | AF45: 0 | AG45: 0 | AH45: 0 | AI45: 0 | AJ45: 0 | AK45: - | AL45: -
A46: 2026-01-01 | B46: 774529517007 | C46: LENNEA温柔学院风白色连衣裙女夏季A字气质百褶裙显瘦辣妹茶歇裙 | D46: '774529517007 | E46: 主商品 | F46: 20402031 | G46: 已下架 | H46: - | I46: 4 | J46: 4 | K46: 9 | L46: 0 | M46: 2 | N46: 0 | O46: 0 | P46: 0 | Q46: 0 | R46: 0 | S46: 0 | T46: 0 | U46: 0 | V46: 0 | W46: 0 | X46: 0 | Y46: 0 | Z46: 0 | AA46: 0 | AB46: 0 | AC46: 0 | AD46: - | AE46: 0 | AF46: 0 | AG46: 0 | AH46: 0 | AI46: 3 | AJ46: 0 | AK46: - | AL46: -
A47: 2026-01-01 | B47: 808201759709 | C47: LENNEA原创设计美式甜酷复古夹克上衣重工做旧宽松皮衣外套女 | D47: '808201759709 | E47: 主商品 | F47: 2024868 | G47: 当前在线 | H47: - | I47: 8 | J47: 8 | K47: 2.31 | L47: 0.125 | M47: 0 | N47: 0 | O47: 0 | P47: 0 | Q47: 0 | R47: 0 | S47: 0 | T47: 0 | U47: 0 | V47: 0 | W47: 0 | X47: 0 | Y47: 0 | Z47: 0 | AA47: 0 | AB47: 0 | AC47: 0 | AD47: - | AE47: 0 | AF47: 0 | AG47: 0 | AH47: 0 | AI47: 0 | AJ47: 0 | AK47: - | AL47: -
A48: 2026-01-01 | B48: 808316978088 | C48: LENNEA原创设计法式条纹衬衫连衣裙女高级感气质收腰长袖裙子 | D48: '808316978088 | E48: 主商品 | F48: 2024863 | G48: 已下架 | H48: - | I48: 1 | J48: 1 | K48: 5.41 | L48: 0 | M48: 0 | N48: 0 | O48: 0 | P48: 0 | Q48: 0 | R48: 0 | S48: 0 | T48: 0 | U48: 0 | V48: 0 | W48: 0 | X48: 0 | Y48: 0 | Z48: 0 | AA48: 0 | AB48: 0 | AC48: 0 | AD48: - | AE48: 0 | AF48: 0 | AG48: 0 | AH48: 0 | AI48: 0 | AJ48: 0 | AK48: - | AL48: -
A49: 2026-01-01 | B49: 808344030423 | C49: LENNEA原创设计复古文艺粉色条纹衬衫新款防晒外套小个子上衣女 | D49: '808344030423 | E49: 主商品 | F49: 2024869 | G49: 已下架 | H49: - | I49: 1 | J49: 1 | K49: 1.15 | L49: 0 | M49: 0 | N49: 0 | O49: 0 | P49: 0 | Q49: 0 | R49: 0 | S49: 0 | T49: 0 | U49: 0 | V49: 0 | W49: 0 | X49: 0 | Y49: 0 | Z49: 0 | AA49: 0 | AB49: 0 | AC49: 0 | AD49: - | AE49: 0 | AF49: 0 | AG49: 0 | AH49: 0 | AI49: 0 | AJ49: 0 | AK49: - | AL49: -
A50: 2026-01-01 | B50: 808474401399 | C50: LENNEA原创设计财阀千金气质黑色毛呢西装外套修身显瘦收腰上衣 | D50: '808474401399 | E50: 主商品 | F50: 2024865 | G50: 当前在线 | H50: - | I50: 13 | J50: 14 | K50: 4.93 | L50: 0.2308 | M50: 0 | N50: 0 | O50: 0 | P50: 0 | Q50: 0 | R50: 0 | S50: 0 | T50: 0 | U50: 0 | V50: 0 | W50: 0 | X50: 0 | Y50: 0 | Z50: 0 | AA50: 0 | AB50: 0 | AC50: 0 | AD50: - | AE50: 0 | AF50: 0 | AG50: 0 | AH50: 0 | AI50: 0 | AJ50: 0 | AK50: - | AL50: -
A51: 2026-01-01 | B51: 808500037559 | C51: LENNEA原创设计简约通勤修身半高领打底衫刺绣秋冬内搭长袖T恤女 | D51: '808500037559 | E51: 主商品 | F51: 2024868 | G51: 当前在线 | H51: - | I51: 23 | J51: 26 | K51: 4.09 | L51: 0.2174 | M51: 0 | N51: 1 | O51: 1 | P51: 0 | Q51: 0 | R51: 0 | S51: 0 | T51: 0 | U51: 0 | V51: 0 | W51: 0 | X51: 0 | Y51: 0 | Z51: 0 | AA51: 0 | AB51: 0 | AC51: 0 | AD51: - | AE51: 0 | AF51: 0 | AG51: 0 | AH51: 0 | AI51: 2 | AJ51: 0 | AK51: - | AL51: -
A52: 2026-01-01 | B52: 809022193130 | C52: LENNEA简约百搭白色梭织长裤松紧腰显瘦宽松休闲直筒裤子女 | D52: '809022193130 | E52: 主商品 | F52: 2024870 | G52: 当前在线 | H52: - | I52: 9 | J52: 13 | K52: 8.55 | L52: 0.4444 | M52: 0 | N52: 1 | O52: 1 | P52: 0 | Q52: 0 | R52: 0 | S52: 0 | T52: 0 | U52: 0 | V52: 0 | W52: 0 | X52: 0 | Y52: 0 | Z52: 0 | AA52: 0 | AB52: 0 | AC52: 0 | AD52: - | AE52: 0 | AF52: 0 | AG52: 0 | AH52: 0 | AI52: 2 | AJ52: 0 | AK52: - | AL52: -
A53: 2026-01-01 | B53: 811797505172 | C53: LENNEA原创设计感连帽贝壳毛衣开衫针织衫女秋季外套慵懒风上衣 | D53: '811797505172 | E53: 主商品 | F53: 2024874 | G53: 当前在线 | H53: - | I53: 190 | J53: 438 | K53: 4.61 | L53: 0.6105 | M53: 8 | N53: 15 | O53: 14 | P53: 0 | Q53: 0 | R53: 0 | S53: 0 | T53: 0 | U53: 0 | V53: 0 | W53: 0 | X53: 0 | Y53: 0 | Z53: 0 | AA53: 0 | AB53: 0 | AC53: 0 | AD53: - | AE53: 0 | AF53: 0 | AG53: 0 | AH53: 0 | AI53: 20 | AJ53: 0 | AK53: - | AL53: -
A54: 2026-01-01 | B54: 839931809012 | C54: LENNEA 2025秋季新款长袖宽松设计感蓝色条纹衬衫翻领衬衣开衫女 | D54: '839931809012 | E54: 主商品 | F54: 2024895 | G54: 当前在线 | H54: - | I54: 4 | J54: 5 | K54: 5.01 | L54: 0.25 | M54: 0 | N54: 0 | O54: 0 | P54: 0 | Q54: 0 | R54: 0 | S54: 0 | T54: 0 | U54: 0 | V54: 0 | W54: 0 | X54: 0 | Y54: 0 | Z54: 0 | AA54: 0 | AB54: 0 | AC54: 0 | AD54: - | AE54: 0 | AF54: 0 | AG54: 0 | AH54: 0 | AI54: 2 | AJ54: 0 | AK54: - | AL54: -
A55: 2026-01-01 | B55: 840669155400 | C55: LENNEA搞怪小熊耳朵羊羔毛外套女秋冬加厚夹棉连帽毛毛上衣外套女 | D55: '840669155400 | E55: 主商品 | F55: 2024905 | G55: 已下架 | H55: - | I55: 22 | J55: 56 | K55: 4.08 | L55: 0.3182 | M55: 3 | N55: 0 | O55: 0 | P55: 0 | Q55: 0 | R55: 0 | S55: 0 | T55: 0 | U55: 0 | V55: 0 | W55: 0 | X55: 0 | Y55: 0 | Z55: 0 | AA55: 0 | AB55: 0 | AC55: 0 | AD55: - | AE55: 0 | AF55: 0 | AG55: 0 | AH55: 0 | AI55: 1 | AJ55: 0 | AK55: - | AL55: -
A56: 2026-01-01 | B56: 843354347895 | C56: LENNEA驼色牛角扣呢子大衣女秋冬学院风宽松中长款驼色毛呢外套 | D56: '843354347895 | E56: 主商品 | F56: KPSS2024130Z | G56: 当前在线 | H56: - | I56: 10 | J56: 17 | K56: 2.09 | L56: 0.4 | M56: 1 | N56: 0 | O56: 0 | P56: 0 | Q56: 0 | R56: 0 | S56: 0 | T56: 0 | U56: 0 | V56: 0 | W56: 0 | X56: 0 | Y56: 0 | Z56: 0 | AA56: 0 | AB56: 0 | AC56: 0 | AD56: - | AE56: 0 | AF56: 0 | AG56: 0 | AH56: 0 | AI56: 2 | AJ56: 0 | AK56: - | AL56: -
A57: 2026-01-01 | B57: 843429440872 | C57: LENNEA中长款围脖方格棉服冬季2025新款韩版宽松显瘦设计感外套 | D57: '843429440872 | E57: 主商品 | F57: KPFW2024042F | G57: 当前在线 | H57: - | I57: 25 | J57: 39 | K57: 4.99 | L57: 0.28 | M57: 1 | N57: 1 | O57: 1 | P57: 0 | Q57: 0 | R57: 0 | S57: 0 | T57: 0 | U57: 0 | V57: 0 | W57: 0 | X57: 0 | Y57: 0 | Z57: 0 | AA57: 0 | AB57: 0 | AC57: 0 | AD57: - | AE57: 0 | AF57: 0 | AG57: 0 | AH57: 0 | AI57: 4 | AJ57: 0 | AK57: - | AL57: -
A58: 2026-01-01 | B58: 843733033154 | C58: LENNEA碎花立领棉服冬季休闲宽松面包服加厚保暖棉衣2025年新款 | D58: '843733033154 | E58: 主商品 | F58: KPFW2024002F | G58: 当前在线 | H58: - | I58: 29 | J58: 37 | K58: 2.57 | L58: 0.1379 | M58: 1 | N58: 0 | O58: 0 | P58: 0 | Q58: 0 | R58: 0 | S58: 0 | T58: 0 | U58: 0 | V58: 0 | W58: 0 | X58: 0 | Y58: 0 | Z58: 0 | AA58: 0 | AB58: 0 | AC58: 261 | AD58: - | AE58: 0 | AF58: 0 | AG58: 0 | AH58: 0 | AI58: 0 | AJ58: 0 | AK58: - | AL58: -
A59: 2026-01-01 | B59: 843918088890 | C59: LENNEA基础轻薄款羽绒服女冬季2025新款超好看不臃肿显瘦保暖外套 | D59: '843918088890 | E59: 主商品 | F59: KPFW2024030F | G59: 当前在线 | H59: - | I59: 895 | J59: 1378 | K59: 19.25 | L59: 0.6458 | M59: 6 | N59: 18 | O59: 18 | P59: 0 | Q59: 0 | R59: 0 | S59: 0 | T59: 0 | U59: 0 | V59: 0 | W59: 0 | X59: 0 | Y59: 0 | Z59: 0 | AA59: 0 | AB59: 0 | AC59: 199 | AD59: - | AE59: 0 | AF59: 0 | AG59: 0 | AH59: 0 | AI59: 17 | AJ59: 0 | AK59: - | AL59: -
A60: 2026-01-01 | B60: 858684938403 | C60: LENNEA原创系带蝴蝶结宽松插肩袖可调节毛圈套头卫衣 | D60: '858684938403 | E60: 主商品 | F60: 2024914 | G60: 已下架 | H60: - | I60: 2 | J60: 2 | K60: 14.88 | L60: 0 | M60: 0 | N60: 0 | O60: 0 | P60: 0 | Q60: 0 | R60: 0 | S60: 0 | T60: 0 | U60: 0 | V60: 0 | W60: 0 | X60: 0 | Y60: 0 | Z60: 0 | AA60: 0 | AB60: 0 | AC60: 0 | AD60: - | AE60: 0 | AF60: 0 | AG60: 0 | AH60: 0 | AI60: 0 | AJ60: 0 | AK60: - | AL60: -
A61: 2026-01-01 | B61: 873651242365 | C61: LENNEA原创小香风外套海军领设计感春秋新款收腰羊毛呢上衣女 | D61: '873651242365 | E61: 主商品 | F61: 2025606 | G61: 当前在线 | H61: - | I61: 17 | J61: 49 | K61: 5.1 | L61: 0.7059 | M61: 1 | N61: 3 | O61: 3 | P61: 0 | Q61: 0 | R61: 0 | S61: 0 | T61: 0 | U61: 0 | V61: 0 | W61: 0 | X61: 0 | Y61: 0 | Z61: 0 | AA61: 0 | AB61: 0 | AC61: 0 | AD61: - | AE61: 0 | AF61: 0 | AG61: 0 | AH61: 0 | AI61: 1 | AJ61: 0 | AK61: - | AL61: -
A62: 2026-01-01 | B62: 874014085141 | C62: LENNEA原创杂灰色毛呢小香风春秋原创短外套设计感保暖上衣女 | D62: '874014085141 | E62: 主商品 | F62: 2025604 | G62: 当前在线 | H62: - | I62: 12 | J62: 31 | K62: 5.57 | L62: 0.1667 | M62: 0 | N62: 2 | O62: 2 | P62: 0 | Q62: 0 | R62: 0 | S62: 0 | T62: 0 | U62: 0 | V62: 0 | W62: 0 | X62: 0 | Y62: 0 | Z62: 0 | AA62: 0 | AB62: 0 | AC62: 0 | AD62: - | AE62: 0 | AF62: 0 | AG62: 0 | AH62: 0 | AI62: 0 | AJ62: 0 | AK62: - | AL62: -
A63: 2026-01-01 | B63: 874289396218 | C63: LENNEA原创连帽针织拉链开衫美式复古休闲百搭新款上衣毛衣外套女 | D63: '874289396218 | E63: 主商品 | F63: 2025601 | G63: 已下架 | H63: - | I63: 1 | J63: 1 | K63: 5.64 | L63: 0 | M63: 0 | N63: 0 | O63: 0 | P63: 0 | Q63: 0 | R63: 0 | S63: 0 | T63: 0 | U63: 0 | V63: 0 | W63: 0 | X63: 0 | Y63: 0 | Z63: 0 | AA63: 0 | AB63: 0 | AC63: 0 | AD63: - | AE63: 0 | AF63: 0 | AG63: 0 | AH63: 0 | AI63: 0 | AJ63: 0 | AK63: - | AL63: -
A64: 2026-01-01 | B64: 887191087761 | C64: LENNEA白色印花小猫kitty短袖纯棉T恤女夏可爱卡通宽松上衣女 | D64: '887191087761 | E64: 主商品 | F64: 2025922 | G64: 已下架 | H64: - | I64: 1 | J64: 1 | K64: 0.95 | L64: 0 | M64: 0 | N64: 0 | O64: 0 | P64: 0 | Q64: 0 | R64: 0 | S64: 0 | T64: 0 | U64: 0 | V64: 0 | W64: 0 | X64: 0 | Y64: 0 | Z64: 0 | AA64: 0 | AB64: 0 | AC64: 0 | AD64: - | AE64: 0 | AF64: 0 | AG64: 0 | AH64: 0 | AI64: 0 | AJ64: 0 | AK64: - | AL64: -
A65: 2026-01-01 | B65: 887250512573 | C65: LENNEA一字肩长袖针织衫女春季新款百搭修身显瘦气质小香露肩上衣 | D65: '887250512573 | E65: 主商品 | F65: 2025918 | G65: 已下架 | H65: - | I65: 2 | J65: 3 | K65: 14.08 | L65: 0 | M65: 1 | N65: 0 | O65: 0 | P65: 0 | Q65: 0 | R65: 0 | S65: 0 | T65: 0 | U65: 0 | V65: 0 | W65: 0 | X65: 0 | Y65: 0 | Z65: 0 | AA65: 0 | AB65: 0 | AC65: 0 | AD65: - | AE65: 0 | AF65: 0 | AG65: 0 | AH65: 0 | AI65: 0 | AJ65: 0 | AK65: - | AL65: -
A66: 2026-01-01 | B66: 887948314178 | C66: LENNEA创意蝴蝶圆领短袖T恤女外穿修身短款正肩收腰显瘦上衣内搭 | D66: '887948314178 | E66: 主商品 | F66: 2025926 | G66: 当前在线 | H66: - | I66: 1 | J66: 1 | K66: 5.83 | L66: 0 | M66: 0 | N66: 1 | O66: 1 | P66: 0 | Q66: 0 | R66: 0 | S66: 0 | T66: 0 | U66: 0 | V66: 0 | W66: 0 | X66: 0 | Y66: 0 | Z66: 0 | AA66: 0 | AB66: 0 | AC66: 0 | AD66: - | AE66: 0 | AF66: 0 | AG66: 0 | AH66: 0 | AI66: 0 | AJ66: 0 | AK66: - | AL66: -
A67: 2026-01-01 | B67: 888341137806 | C67: LENNEA辣妹一字吊带背心女春夏款内搭打底修身显瘦外穿上衣 | D67: '888341137806 | E67: 主商品 | F67: 2025923 | G67: 当前在线 | H67: - | I67: 4 | J67: 7 | K67: 8.82 | L67: 0.5 | M67: 0 | N67: 1 | O67: 1 | P67: 0 | Q67: 0 | R67: 0 | S67: 0 | T67: 0 | U67: 0 | V67: 0 | W67: 0 | X67: 0 | Y67: 0 | Z67: 0 | AA67: 0 | AB67: 0 | AC67: 0 | AD67: - | AE67: 0 | AF67: 0 | AG67: 0 | AH67: 0 | AI67: 1 | AJ67: 0 | AK67: - | AL67: -
A68: 2026-01-01 | B68: 888343437864 | C68: LENNEA芭蕾风蛋糕裙半身短裙女高腰显瘦小个子A字蓬蓬短裙半身裙 | D68: '888343437864 | E68: 主商品 | F68: 2025924 | G68: 当前在线 | H68: - | I68: 6 | J68: 12 | K68: 3.26 | L68: 0.3333 | M68: 1 | N68: 2 | O68: 2 | P68: 0 | Q68: 0 | R68: 0 | S68: 0 | T68: 0 | U68: 0 | V68: 0 | W68: 0 | X68: 0 | Y68: 0 | Z68: 0 | AA68: 0 | AB68: 0 | AC68: 0 | AD68: - | AE68: 0 | AF68: 0 | AG68: 0 | AH68: 0 | AI68: 1 | AJ68: 0 | AK68: - | AL68: -
A69: 2026-01-01 | B69: 888405241497 | C69: LENNEA梦幻芭蕾网纱蓬蓬蛋糕裙女法式浪漫层次感高腰显瘦半身裙 | D69: '888405241497 | E69: 主商品 | F69: 2025928 | G69: 当前在线 | H69: - | I69: 28 | J69: 33 | K69: 2.93 | L69: 0.2143 | M69: 1 | N69: 1 | O69: 1 | P69: 0 | Q69: 0 | R69: 0 | S69: 0 | T69: 0 | U69: 0 | V69: 0 | W69: 0 | X69: 0 | Y69: 0 | Z69: 0 | AA69: 0 | AB69: 0 | AC69: 0 | AD69: - | AE69: 0 | AF69: 0 | AG69: 0 | AH69: 0 | AI69: 0 | AJ69: 0 | AK69: - | AL69: -
A70: 2026-01-01 | B70: 888761084881 | C70: LENNEA学院风百褶裙女甜辣风修身显瘦小个子防走光a字短裙春夏 | D70: '888761084881 | E70: 主商品 | F70: 2025927 | G70: 当前在线 | H70: - | I70: 9 | J70: 10 | K70: 4.41 | L70: 0.2222 | M70: 0 | N70: 0 | O70: 0 | P70: 0 | Q70: 0 | R70: 0 | S70: 0 | T70: 0 | U70: 0 | V70: 0 | W70: 0 | X70: 0 | Y70: 0 | Z70: 0 | AA70: 0 | AB70: 0 | AC70: 0 | AD70: - | AE70: 0 | AF70: 0 | AG70: 0 | AH70: 0 | AI70: 0 | AJ70: 0 | AK70: - | AL70: -
A71: 2026-01-01 | B71: 890104547276 | C71: LENNEA韩系复古黑粉色格子衬衫女春秋宽松慵懒风设计感长袖外套 | D71: '890104547276 | E71: 主商品 | F71: 2024896 | G71: 已下架 | H71: - | I71: 1 | J71: 1 | K71: 0.77 | L71: 0 | M71: 0 | N71: 0 | O71: 0 | P71: 0 | Q71: 0 | R71: 0 | S71: 0 | T71: 0 | U71: 0 | V71: 0 | W71: 0 | X71: 0 | Y71: 0 | Z71: 0 | AA71: 0 | AB71: 0 | AC71: 0 | AD71: - | AE71: 0 | AF71: 0 | AG71: 0 | AH71: 0 | AI71: 0 | AJ71: 0 | AK71: - | AL71: -
... A92: 2026-01-01 | B92: 926371874519 | C92: LENNEA黑粉斜肩蝴蝶结绑带t恤女夏设计感露肩辣妹修身短袖上衣 | D92: '926371874519 | E92: 主商品 | F92: 2025853 | G92: 已下架 | H92: - | I92: 1 | J92: 4 | K92: 25.04 | L92: 0 | M92: 2 | N92: 0 | O92: 0 | P92: 0 | Q92: 0 | R92: 0 | S92: 0 | T92: 0 | U92: 0 | V92: 0 | W92: 0 | X92: 0 | Y92: 0 | Z92: 0 | AA92: 0 | AB92: 0 | AC92: 0 | AD92: - | AE92: 0 | AF92: 0 | AG92: 0 | AH92: 0 | AI92: 1 | AJ92: 0 | AK92: - | AL92: -
A93: 2026-01-01 | B93: 926395318191 | C93: LENNEA夏季斜肩女士灰色短袖t恤韩系露肩设计感花边一字肩上衣 | D93: '926395318191 | E93: 主商品 | F93: 2025950-1 | G93: 当前在线 | H93: - | I93: 2 | J93: 3 | K93: 26.44 | L93: 0 | M93: 0 | N93: 0 | O93: 0 | P93: 0 | Q93: 0 | R93: 0 | S93: 0 | T93: 0 | U93: 0 | V93: 0 | W93: 0 | X93: 0 | Y93: 0 | Z93: 0 | AA93: 0 | AB93: 0 | AC93: 0 | AD93: - | AE93: 0 | AF93: 0 | AG93: 0 | AH93: 0 | AI93: 0 | AJ93: 0 | AK93: - | AL93: -
A94: 2026-01-01 | B94: 949025047353 | C94: LENNEA粉色条纹连衣裙韩系百搭秋季新款学院风设计感花苞衬衫短裙 | D94: '949025047353 | E94: 主商品 | F94: 2025867 | G94: 当前在线 | H94: - | I94: 31 | J94: 61 | K94: 4.26 | L94: 0.4194 | M94: 1 | N94: 2 | O94: 2 | P94: 0 | Q94: 0 | R94: 0 | S94: 0 | T94: 0 | U94: 0 | V94: 0 | W94: 0 | X94: 0 | Y94: 0 | Z94: 0 | AA94: 0 | AB94: 0 | AC94: 0 | AD94: - | AE94: 0 | AF94: 0 | AG94: 0 | AH94: 0 | AI94: 3 | AJ94: 0 | AK94: - | AL94: -
A95: 2026-01-01 | B95: 949034219575 | C95: LENNEA慵懒感减龄海军领毛衣女秋季温柔设计感学院风针织上衣女 | D95: '949034219575 | E95: 主商品 | F95: 2025919 | G95: 当前在线 | H95: - | I95: 82 | J95: 167 | K95: 3.26 | L95: 0.4634 | M95: 1 | N95: 2 | O95: 2 | P95: 0 | Q95: 0 | R95: 0 | S95: 0 | T95: 0 | U95: 0 | V95: 0 | W95: 0 | X95: 0 | Y95: 0 | Z95: 0 | AA95: 0 | AB95: 0 | AC95: 0 | AD95: - | AE95: 0 | AF95: 0 | AG95: 0 | AH95: 0 | AI95: 7 | AJ95: 0 | AK95: - | AL95: -
A96: 2026-01-01 | B96: 949280151045 | C96: LENNEA假两件蕾丝拼接套装氛围感开衫秋季新款长袖上衣针织衫女 | D96: '949280151045 | E96: 主商品 | F96: 2025906 | G96: 当前在线 | H96: - | I96: 11 | J96: 29 | K96: 3.66 | L96: 0.0909 | M96: 0 | N96: 0 | O96: 0 | P96: 0 | Q96: 0 | R96: 0 | S96: 0 | T96: 0 | U96: 0 | V96: 0 | W96: 0 | X96: 0 | Y96: 0 | Z96: 0 | AA96: 0 | AB96: 0 | AC96: 0 | AD96: - | AE96: 0 | AF96: 0 | AG96: 0 | AH96: 0 | AI96: 0 | AJ96: 0 | AK96: - | AL96: -
A97: 2026-01-01 | B97: 949297551623 | C97: LENNEA花卉印花白色插肩长袖t恤女纯棉宽松慵懒风圆领长袖上衣 | D97: '949297551623 | E97: 主商品 | F97: 2025908-2 | G97: 已下架 | H97: - | I97: 1 | J97: 1 | K97: 1.45 | L97: 0 | M97: 0 | N97: 0 | O97: 0 | P97: 0 | Q97: 0 | R97: 0 | S97: 0 | T97: 0 | U97: 0 | V97: 0 | W97: 0 | X97: 0 | Y97: 0 | Z97: 0 | AA97: 0 | AB97: 0 | AC97: 0 | AD97: - | AE97: 0 | AF97: 0 | AG97: 0 | AH97: 0 | AI97: 0 | AJ97: 0 | AK97: - | AL97: -
A98: 2026-01-01 | B98: 949490570323 | C98: LENNEA韩系假两件格纹上衣蓬蓬花苞半裙两件套学院风针织衫套装 | D98: '949490570323 | E98: 主商品 | F98: 2025903 | G98: 当前在线 | H98: - | I98: 45 | J98: 100 | K98: 4.23 | L98: 0.1333 | M98: 2 | N98: 1 | O98: 1 | P98: 0 | Q98: 0 | R98: 0 | S98: 0 | T98: 0 | U98: 0 | V98: 0 | W98: 0 | X98: 0 | Y98: 0 | Z98: 0 | AA98: 0 | AB98: 0 | AC98: 0 | AD98: - | AE98: 0 | AF98: 0 | AG98: 0 | AH98: 0 | AI98: 7 | AJ98: 0 | AK98: - | AL98: -
A99: 2026-01-01 | B99: 949730586867 | C99: LENNEA黄色假两件长袖T恤女慵懒风撞色叠穿两件套上衣服针织衫 | D99: '949730586867 | E99: 主商品 | F99: 2025928 | G99: 当前在线 | H99: - | I99: 17 | J99: 69 | K99: 5.99 | L99: 0.4118 | M99: 1 | N99: 3 | O99: 3 | P99: 0 | Q99: 0 | R99: 0 | S99: 0 | T99: 0 | U99: 0 | V99: 0 | W99: 0 | X99: 0 | Y99: 0 | Z99: 0 | AA99: 0 | AB99: 0 | AC99: 0 | AD99: - | AE99: 0 | AF99: 0 | AG99: 0 | AH99: 0 | AI99: 3 | AJ99: 0 | AK99: - | AL99: -
A100: 2026-01-01 | B100: 949737670717 | C100: LENNEA毛领连帽结构卫衣外套女收腰显瘦短款长袖开衫休闲上衣外套 | D100: '949737670717 | E100: 主商品 | F100: 2025909 | G100: 当前在线 | H100: - | I100: 97 | J100: 155 | K100: 3.66 | L100: 0.4639 | M100: 1 | N100: 3 | O100: 3 | P100: 0 | Q100: 0 | R100: 0 | S100: 0 | T100: 0 | U100: 0 | V100: 0 | W100: 0 | X100: 0 | Y100: 0 | Z100: 0 | AA100: 0 | AB100: 0 | AC100: 0 | AD100: - | AE100: 0 | AF100: 0 | AG100: 0 | AH100: 0 | AI100: 3 | AJ100: 0 | AK100: - | AL100: -
A101: 2026-01-01 | B101: 949747750368 | C101: LENNEA浅蓝色少女感木耳花边短外套秋季新款韩系休闲上衣夹克女 | D101: '949747750368 | E101: 主商品 | F101: 2025917 | G101: 已下架 | H101: - | I101: 3 | J101: 3 | K101: 7.25 | L101: 0.6667 | M101: 0 | N101: 0 | O101: 0 | P101: 0 | Q101: 0 | R101: 0 | S101: 0 | T101: 0 | U101: 0 | V101: 0 | W101: 0 | X101: 0 | Y101: 0 | Z101: 0 | AA101: 0 | AB101: 0 | AC101: 0 | AD101: - | AE101: 0 | AF101: 0 | AG101: 0 | AH101: 0 | AI101: 1 | AJ101: 0 | AK101: - | AL101: -
A102: 2026-01-01 | B102: 949754058834 | C102: LENNEA黑色小香风外套女短款长袖针织开衫气质高级感排扣外套上衣 | D102: '949754058834 | E102: 主商品 | F102: 2025869 | G102: 当前在线 | H102: - | I102: 40 | J102: 50 | K102: 3.86 | L102: 0.6 | M102: 0 | N102: 1 | O102: 1 | P102: 0 | Q102: 0 | R102: 0 | S102: 0 | T102: 0 | U102: 0 | V102: 0 | W102: 0 | X102: 0 | Y102: 0 | Z102: 0 | AA102: 0 | AB102: 0 | AC102: 0 | AD102: - | AE102: 0 | AF102: 0 | AG102: 0 | AH102: 0 | AI102: 3 | AJ102: 0 | AK102: - | AL102: -
A103: 2026-01-01 | B103: 950077029212 | C103: LENNEA衬衫拼接一字肩绑带长袖上衣秋季新款小众风设计感衬衣女 | D103: '950077029212 | E103: 主商品 | F103: 2025931 | G103: 当前在线 | H103: - | I103: 5 | J103: 9 | K103: 7.61 | L103: 0 | M103: 0 | N103: 0 | O103: 0 | P103: 0 | Q103: 0 | R103: 0 | S103: 0 | T103: 0 | U103: 0 | V103: 0 | W103: 0 | X103: 0 | Y103: 0 | Z103: 0 | AA103: 0 | AB103: 0 | AC103: 0 | AD103: - | AE103: 0 | AF103: 0 | AG103: 0 | AH103: 0 | AI103: 1 | AJ103: 0 | AK103: - | AL103: -
A104: 2026-01-01 | B104: 950084969730 | C104: LENNEA复古撞色花朵长袖纯棉T恤女宽松百搭休闲新款正肩圆领上衣 | D104: '950084969730 | E104: 主商品 | F104: 2025908-1 | G104: 已下架 | H104: - | I104: 2 | J104: 3 | K104: 1.48 | L104: 0 | M104: 0 | N104: 0 | O104: 0 | P104: 0 | Q104: 0 | R104: 0 | S104: 0 | T104: 0 | U104: 0 | V104: 0 | W104: 0 | X104: 0 | Y104: 0 | Z104: 0 | AA104: 0 | AB104: 0 | AC104: 0 | AD104: - | AE104: 0 | AF104: 0 | AG104: 0 | AH104: 0 | AI104: 0 | AJ104: 0 | AK104: - | AL104: -
A105: 2026-01-01 | B105: 950098965863 | C105: LENNEA原创蕾丝荡领长袖t恤纯欲设计感斜肩别致韩系网纱上衣女 | D105: '950098965863 | E105: 主商品 | F105: 2025888 | G105: 当前在线 | H105: - | I105: 13 | J105: 17 | K105: 4.13 | L105: 0.1538 | M105: 1 | N105: 0 | O105: 0 | P105: 0 | Q105: 0 | R105: 0 | S105: 0 | T105: 0 | U105: 0 | V105: 0 | W105: 0 | X105: 0 | Y105: 0 | Z105: 0 | AA105: 0 | AB105: 0 | AC105: 0 | AD105: - | AE105: 0 | AF105: 0 | AG105: 0 | AH105: 0 | AI105: 0 | AJ105: 0 | AK105: - | AL105: -
A106: 2026-01-01 | B106: 950127313803 | C106: LENNEA花边一字肩宽松小众复古卫衣女收腰显瘦秋季百搭长袖上衣 | D106: '950127313803 | E106: 主商品 | F106: 2025858 | G106: 当前在线 | H106: - | I106: 15 | J106: 23 | K106: 2.96 | L106: 0.4 | M106: 1 | N106: 0 | O106: 0 | P106: 0 | Q106: 0 | R106: 0 | S106: 0 | T106: 0 | U106: 0 | V106: 0 | W106: 0 | X106: 0 | Y106: 0 | Z106: 0 | AA106: 0 | AB106: 0 | AC106: 0 | AD106: - | AE106: 0 | AF106: 0 | AG106: 0 | AH106: 0 | AI106: 1 | AJ106: 0 | AK106: - | AL106: -
A107: 2026-01-01 | B107: 950661068182 | C107: LENNEA仿貂毛针织衫两件套坎肩连帽套头毛衣黄色秋冬慵懒穿搭上衣 | D107: '950661068182 | E107: 主商品 | F107: MY002 | G107: 当前在线 | H107: - | I107: 60 | J107: 100 | K107: 4.42 | L107: 0.2 | M107: 1 | N107: 2 | O107: 2 | P107: 0 | Q107: 0 | R107: 0 | S107: 0 | T107: 0 | U107: 0 | V107: 0 | W107: 0 | X107: 0 | Y107: 0 | Z107: 0 | AA107: 0 | AB107: 0 | AC107: 0 | AD107: - | AE107: 0 | AF107: 0 | AG107: 0 | AH107: 0 | AI107: 6 | AJ107: 0 | AK107: - | AL107: -
A108: 2026-01-01 | B108: 952989667628 | C108: LENNEA白色牛仔裤女宽松垂感阔腿裤高腰显瘦休闲百搭拖地长裤子 | D108: '952989667628 | E108: 主商品 | F108: NH003 | G108: 当前在线 | H108: - | I108: 23 | J108: 42 | K108: 4.53 | L108: 0.1304 | M108: 1 | N108: 2 | O108: 2 | P108: 0 | Q108: 0 | R108: 0 | S108: 0 | T108: 0 | U108: 0 | V108: 0 | W108: 0 | X108: 0 | Y108: 0 | Z108: 0 | AA108: 0 | AB108: 0 | AC108: 148 | AD108: - | AE108: 0 | AF108: 0 | AG108: 0 | AH108: 0 | AI108: 1 | AJ108: 0 | AK108: - | AL108: -
A109: 2026-01-01 | B109: 954086441085 | C109: LENNEA蕾丝拼接花边裤子女弯刀裤双腰头假两件西装直筒宽松休闲裤 | D109: '954086441085 | E109: 主商品 | F109: 2025973 | G109: 当前在线 | H109: - | I109: 12 | J109: 85 | K109: 3.79 | L109: 0.25 | M109: 0 | N109: 1 | O109: 1 | P109: 0 | Q109: 0 | R109: 0 | S109: 0 | T109: 0 | U109: 0 | V109: 0 | W109: 0 | X109: 0 | Y109: 0 | Z109: 0 | AA109: 0 | AB109: 0 | AC109: 0 | AD109: - | AE109: 0 | AF109: 0 | AG109: 0 | AH109: 0 | AI109: 4 | AJ109: 0 | AK109: - | AL109: -
A110: 2026-01-01 | B110: 958610070738 | C110: LENNEA蓝色V领针织开衫女早秋花边拼接修身显瘦慵懒气质长袖上衣 | D110: '958610070738 | E110: 主商品 | F110: MY003 | G110: 当前在线 | H110: - | I110: 7 | J110: 20 | K110: 2.3 | L110: 0.2857 | M110: 0 | N110: 1 | O110: 1 | P110: 0 | Q110: 0 | R110: 0 | S110: 0 | T110: 0 | U110: 0 | V110: 0 | W110: 0 | X110: 0 | Y110: 0 | Z110: 0 | AA110: 0 | AB110: 0 | AC110: 0 | AD110: - | AE110: 0 | AF110: 0 | AG110: 0 | AH110: 0 | AI110: 2 | AJ110: 0 | AK110: - | AL110: -
A111: 2026-01-01 | B111: 959849148750 | C111: LENNEA假两件连帽斜襟撞色条纹拼接卫衣开衫设计感小众拉链薄外套 | D111: '959849148750 | E111: 主商品 | F111: 2025975 | G111: 当前在线 | H111: - | I111: 13 | J111: 32 | K111: 2.09 | L111: 0.2308 | M111: 0 | N111: 2 | O111: 1 | P111: 0 | Q111: 0 | R111: 0 | S111: 0 | T111: 0 | U111: 0 | V111: 0 | W111: 0 | X111: 0 | Y111: 0 | Z111: 0 | AA111: 0 | AB111: 0 | AC111: 0 | AD111: - | AE111: 0 | AF111: 0 | AG111: 0 | AH111: 0 | AI111: 1 | AJ111: 0 | AK111: - | AL111: -
A112: 2026-01-01 | B112: 966240427493 | C112: LENNEA黄色麻花针织开衫女早秋新款修身显瘦短款毛衣外套上衣 | D112: '966240427493 | E112: 主商品 | F112: MY005 | G112: 已下架 | H112: - | I112: 3 | J112: 4 | K112: 1.89 | L112: 0.6667 | M112: 1 | N112: 0 | O112: 0 | P112: 0 | Q112: 0 | R112: 0 | S112: 0 | T112: 0 | U112: 0 | V112: 0 | W112: 0 | X112: 0 | Y112: 0 | Z112: 0 | AA112: 0 | AB112: 0 | AC112: 0 | AD112: - | AE112: 0 | AF112: 0 | AG112: 0 | AH112: 0 | AI112: 0 | AJ112: 0 | AK112: - | AL112: -
A113: 2026-01-01 | B113: 966250011546 | C113: LENNEA针织衫连帽格子拼接毛衣外套休闲宽松外搭长袖开衫外套秋冬 | D113: '966250011546 | E113: 主商品 | F113: 2025923 | G113: 当前在线 | H113: - | I113: 19 | J113: 47 | K113: 2.06 | L113: 0.4211 | M113: 1 | N113: 2 | O113: 2 | P113: 0 | Q113: 0 | R113: 0 | S113: 0 | T113: 0 | U113: 0 | V113: 0 | W113: 0 | X113: 0 | Y113: 0 | Z113: 0 | AA113: 0 | AB113: 0 | AC113: 238 | AD113: - | AE113: 0 | AF113: 0 | AG113: 0 | AH113: 0 | AI113: 1 | AJ113: 0 | AK113: - | AL113: -
A114: 2026-01-01 | B114: 966724894105 | C114: LENNEA灰色彩点镶钻毛衣外套女针织开衫miu系高级感软糯上衣外套 | D114: '966724894105 | E114: 主商品 | F114: MY004 | G114: 当前在线 | H114: - | I114: 149 | J114: 385 | K114: 3.78 | L114: 0.5772 | M114: 1 | N114: 12 | O114: 12 | P114: 0 | Q114: 0 | R114: 0 | S114: 0 | T114: 0 | U114: 0 | V114: 0 | W114: 0 | X114: 0 | Y114: 0 | Z114: 0 | AA114: 0 | AB114: 0 | AC114: 0 | AD114: - | AE114: 0 | AF114: 0 | AG114: 0 | AH114: 0 | AI114: 23 | AJ114: 0 | AK114: - | AL114: -
A115: 2026-01-01 | B115: 967427093175 | C115: LENNEA可拆卸大毛领连帽开衫毛衣宽松外套软糯氛围感温柔针织上衣 | D115: '967427093175 | E115: 主商品 | F115: MY006 | G115: 已下架 | H115: - | I115: 1 | J115: 3 | K115: 6.38 | L115: 0 | M115: 0 | N115: 0 | O115: 0 | P115: 0 | Q115: 0 | R115: 0 | S115: 0 | T115: 0 | U115: 0 | V115: 0 | W115: 0 | X115: 0 | Y115: 0 | Z115: 0 | AA115: 0 | AB115: 0 | AC115: 0 | AD115: - | AE115: 0 | AF115: 0 | AG115: 0 | AH115: 0 | AI115: 0 | AJ115: 0 | AK115: - | AL115: -
A116: 2026-01-01 | B116: 968024928913 | C116: LENNEA法式花瓣一字肩撞色长袖T恤女早秋绝美锁骨修身露肩上衣 | D116: '968024928913 | E116: 主商品 | F116: 2025971 | G116: 已下架 | H116: - | I116: 5 | J116: 6 | K116: 2.1 | L116: 0.4 | M116: 0 | N116: 0 | O116: 0 | P116: 0 | Q116: 0 | R116: 0 | S116: 0 | T116: 0 | U116: 0 | V116: 0 | W116: 0 | X116: 0 | Y116: 0 | Z116: 0 | AA116: 0 | AB116: 0 | AC116: 0 | AD116: - | AE116: 0 | AF116: 0 | AG116: 0 | AH116: 0 | AI116: 0 | AJ116: 0 | AK116: - | AL116: -
A117: 2026-01-01 | B117: 969111863463 | C117: LENNEA灰色连帽毛领羊毛呢子大衣女秋冬季拉链卫衣开衫外套 | D117: '969111863463 | E117: 主商品 | F117: 2025922 | G117: 当前在线 | H117: - | I117: 50 | J117: 79 | K117: 3.51 | L117: 0.24 | M117: 0 | N117: 1 | O117: 1 | P117: 0 | Q117: 0 | R117: 0 | S117: 0 | T117: 0 | U117: 0 | V117: 0 | W117: 0 | X117: 0 | Y117: 0 | Z117: 0 | AA117: 0 | AB117: 0 | AC117: 0 | AD117: - | AE117: 0 | AF117: 0 | AG117: 0 | AH117: 0 | AI117: 5 | AJ117: 0 | AK117: - | AL117: -
A118: 2026-01-01 | B118: 969613018510 | C118: LENNEA波点拼接假两件套头针织衫毛衣秋冬宽松甜美慵懒风软糯上衣 | D118: '969613018510 | E118: 主商品 | F118: - | G118: 当前在线 | H118: - | I118: 30 | J118: 89 | K118: 4.37 | L118: 0.0667 | M118: 2 | N118: 6 | O118: 6 | P118: 0 | Q118: 0 | R118: 0 | S118: 0 | T118: 0 | U118: 0 | V118: 0 | W118: 0 | X118: 0 | Y118: 0 | Z118: 0 | AA118: 0 | AB118: 0 | AC118: 336 | AD118: - | AE118: 0 | AF118: 0 | AG118: 0 | AH118: 0 | AI118: 5 | AJ118: 0 | AK118: - | AL118: -
A119: 2026-01-01 | B119: 969627326446 | C119: LENNEA蝴蝶扣羊羔毛外套女秋冬加厚宽松小个子黑色皮毛一体大衣 | D119: '969627326446 | E119: 主商品 | F119: 2025915 | G119: 当前在线 | H119: - | I119: 200 | J119: 323 | K119: 3.87 | L119: 0.705 | M119: 4 | N119: 6 | O119: 6 | P119: 0 | Q119: 0 | R119: 0 | S119: 0 | T119: 0 | U119: 0 | V119: 0 | W119: 0 | X119: 0 | Y119: 0 | Z119: 0 | AA119: 0 | AB119: 0 | AC119: 0 | AD119: - | AE119: 0 | AF119: 0 | AG119: 0 | AH119: 0 | AI119: 5 | AJ119: 0 | AK119: - | AL119: -
A120: 2026-01-01 | B120: 970292825766 | C120: LENNEA多巴胺黄色基础连帽羊羔毛秋冬棉服纽扣毛茸保暖外套上衣女 | D120: '970292825766 | E120: 主商品 | F120: - | G120: 已下架 | H120: - | I120: 2 | J120: 3 | K120: 4.1 | L120: 0 | M120: 0 | N120: 0 | O120: 0 | P120: 0 | Q120: 0 | R120: 0 | S120: 0 | T120: 0 | U120: 0 | V120: 0 | W120: 0 | X120: 0 | Y120: 0 | Z120: 0 | AA120: 0 | AB120: 0 | AC120: 0 | AD120: - | AE120: 0 | AF120: 0 | AG120: 0 | AH120: 0 | AI120: 0 | AJ120: 0 | AK120: - | AL120: -
...

Sheet 指标统计
A1: 序号 | B1: 一级分类 | C1: 表 | D1: 列名 | E1: 字段类型 | F1: 数据来源 | G1: 备注
A2: 1 | B2: 数据管理 | C2: 博主库 | D2: 联系人 | E2: 源数据 | F2: 人工 | G2: -
A3: 2 | B3: 数据管理 | C3: 博主库 | D3: 小红书昵称 | E3: 源数据 | F3: 人工 | G3: -
A4: 3 | B4: 数据管理 | C4: 博主库 | D4: 小红书ID | E4: 源数据 | F4: 人工 | G4: -
A5: 4 | B5: 数据管理 | C5: 博主库 | D5: 邮箱(联系上的可不填) | E5: 源数据 | F5: 人工 | G5: -
A6: 5 | B6: 数据管理 | C6: 博主库 | D6: 微信号 | E6: 源数据 | F6: 人工 | G6: -
A7: 6 | B7: 数据管理 | C7: 博主库 | D7: 报价 | E7: 源数据 | F7: 人工 | G7: -
A8: 7 | B8: 数据管理 | C8: 博主库 | D8: 粉丝量 | E8: 爬虫 | F8: 影刀 | G8: 每天增量更新到固定文件夹
A9: 8 | B9: 数据管理 | C9: 博主库 | D9: 3篇阅读量 | E9: 爬虫 | F9: 影刀 | G9: 每天增量更新到固定文件夹
A10: 9 | B10: 数据管理 | C10: 博主库 | D10: 3篇点赞数 | E10: 爬虫 | F10: 影刀 | G10: 每天增量更新到固定文件夹
A11: 10 | B11: 数据管理 | C11: 博主库 | D11: 3篇收藏数 | E11: 爬虫 | F11: 影刀 | G11: 每天增量更新到固定文件夹
A12: 11 | B12: 数据管理 | C12: 博主库 | D12: 3篇评论数 | E12: 爬虫 | F12: 影刀 | G12: 每天增量更新到固定文件夹
A13: 12 | B13: 数据管理 | C13: 博主库 | D13: 7篇阅读量 | E13: 爬虫 | F13: 影刀 | G13: 每天增量更新到固定文件夹
... A227: 226 | B227: 财务管理 | C227: 余额核对 | D227: 备注 | E227: 源数据 | F227: 人工 | G227: -

Sheet 余额核对
A1: 日期 | B1: 充值收入 | C1: 推广支出 | D1: 刷/拍单支出 | E1: 余额 | F1: 余额截图 | G1: 备注
A2: 45930 | B2: 4272.02 | C2: 4077 | D2: 2558.37 | E2: 195.02
A3: 45931 | B3: 0 | C3: 500 | D3: 2558.37 | E3: -500 | G3: -200
A4: 45939 | B4: 36195.02 | C4: 26943.06 | D4: 2558.37 | E4: 9251.96

Sheet 拍单
A1: 销售类型 | B1: 拍单日期 | C1: 订单号 | D1: 博主ID/微信ID | E1: 款式 | F1: 款号 | G1: 金额 | H1: 付款金额 | I1: 付款日期
A2: 拍单 | B2: 46029 | C2: 3161196303779557591 | D2: 小红书：Zzz- | E2: 波点套 费尔岛毛衣 蕾丝防晒衬衫 一字肩针织连衣裙 | F2: 2025933 | G2: 298 | H2: 298 | I2: 46035
A3: 刷单 | B3: 46032 | C3: 3059182310768877461 | D3: 155的瑶瑶阿 | E3: 波点套 双排扣小香 一字肩针织连衣裙 蕾丝防晒衬衫 | F3: 2025933 | G3: 298 | H3: 298 | I3: 46036
A4: 刷单 | B4: 46032 | C4: 4877572609413972718 | D4: 丰腴幼软 | E4: 波点套 一字肩针织连衣裙 拼接针织套 | F4: 2025933 | G4: 298 | H4: 298 | I4: 46037
A5: 刷单 | B5: 46057 | C5: 3226009117153132788 | D5: -coin88 | E5: 波点套 费尔岛毛衣 蕾丝防晒衬衫 一字肩针织连衣裙 | F5: 2025933 | G5: 298 | H5: 298 | I5: 46038
A6: 刷单 | B6: 46057 | C6: 3226185192668351880 | D6: 沙琪奶芙 | E6: 波点套 双排扣小香 一字肩针织连衣裙 蕾丝防晒衬衫 | F6: 2025933 | G6: 298 | H6: 298 | I6: 46039
A7: 刷单 | B7: 46057 | C7: 3226185192668351880 | D7: D子别买了 | E7: 波点套 一字肩针织连衣裙 拼接针织套 | F7: 2025933 | G7: 298 | H7: 298 | I7: 46040
A8: 刷单 | B8: 46111 | C8: 2701784750043047564 | D8: 淡淡的绿 | E8: 波点套 费尔岛毛衣 蕾丝防晒衬衫 一字肩针织连衣裙 | F8: 2025933 | G8: 298 | H8: 298 | I8: 46041
A9: 刷单 | B9: 46111 | C9: 2701775281166026593 | D9: HTG | E9: 波点套 双排扣小香 一字肩针织连衣裙 蕾丝防晒衬衫 | F9: 2025933 | G9: 298 | H9: 298 | I9: 46042
A10: 刷单 | B10: 46111 | C10: 2701789717049023590 | D10: 果仁儿曦 | E10: 波点套 一字肩针织连衣裙 拼接针织套 | F10: 2025933 | G10: 298 | H10: 298 | I10: 46043
A11: 刷单 | B11: 46111 | C11: 2701786263037039088 | D11: 邪恶的00 | E11: 波点套 费尔岛毛衣 蕾丝防晒衬衫 一字肩针织连衣裙 | F11: 2025933 | G11: 298 | H11: 298 | I11: 46044
A12: 刷单 | B12: 46111 | C12: 4502207631032004708 | D12: 睡觉了 | E12: 波点套 双排扣小香 一字肩针织连衣裙 蕾丝防晒衬衫 | F12: 2025933 | G12: 298 | H12: 298 | I12: 46045
A13: 刷单 | B13: 46111 | C13: 2701774526065001370 | D13: 好甜 | E13: 波点套 一字肩针织连衣裙 拼接针织套 | F13: 2025933 | G13: 298 | H13: 298 | I13: 46046
... A48: 刷单 | B48: 46129 | C48: 4502264871185007827 | D48: quqookicu | E48: 波点套 双排扣小香 一字肩针织连衣裙 蕾丝防晒衬衫 | F48: 2025933 | G48: 298 | H48: 298 | I48: 46081

Sheet 单品站内推广数据
A1: 日期 | B1: 主体ID | C1: 主体类型 | D1: 主体名称 | E1: 展现量 | F1: 点击量 | G1: 花费 | H1: 点击率 | I1: 平均点击花费 | J1: 千次展现花费 | K1: 总预售成交金额 | L1: 总预售成交笔数 | M1: 直接预售成交金额 | N1: 直接预售成交笔数 | O1: 间接预售成交金额 | P1: 间接预售成交笔数 | Q1: 直接成交金额 | R1: 间接成交金额 | S1: 总成交金额 | T1: 总成交笔数 | U1: 直接成交笔数 | V1: 间接成交笔数 | W1: 点击转化率 | X1: 投入产出比 | Y1: 含预售投产比 | Z1: 总成交成本 | AA1: 总购物车数 | AB1: 直接购物车数 | AC1: 间接购物车数 | AD1: 加购率 | AE1: 收藏宝贝数 | AF1: 收藏店铺数 | AG1: 店铺收藏成本 | AH1: 总收藏加购数 | AI1: 总收藏加购成本 | AJ1: 宝贝收藏加购数 | AK1: 宝贝收藏加购成本 | AL1: 总收藏数 | AM1: 宝贝收藏成本 | AN1: 宝贝收藏率 | AO1: 加购成本 | AP1: 拍下订单笔数 | AQ1: 拍下订单金额 | AR1: 直接收藏宝贝数 | AS1: 间接收藏宝贝数 | AT1: 优惠券领取量 | AU1: 购物金充值笔数 | AV1: 购物金充值金额 | AW1: 旺旺咨询量 | AX1: 引导访问量 | AY1: 引导访问人数 | AZ1: 引导访问潜客数 | BA1: 引导访问潜客占比 | BB1: 入会率 | BC1: 入会量 | BD1: 引导访问率 | BE1: 深度访问量 | BF1: 平均访问页面数 | BG1: 成交新客数 | BH1: 成交新客占比 | BI1: 会员首购人数 | BJ1: 会员成交金额 | BK1: 会员成交笔数 | BL1: 成交人数 | BM1: 人均成交笔数 | BN1: 人均成交金额 | BO1: 自然流量转化金额 | BP1: 自然流量曝光量 | BQ1: 宝贝优惠券抵扣金额 | BR1: 宝贝优惠券撬动总成交 | BS1: 宝贝优惠券撬动直接成交 | BT1: 宝贝优惠券撬动点击
A2: 46104 | B2: 1027636684171 | C2: 商品 | D2: LENNEA法式小个子设计感减龄蓝色连衣裙子女夏季无袖背心花苞短裙 | E2: 3556 | F2: 172 | G2: 45.08 | H2: 0.04837 | I2: 0.26 | J2: 12.68 | K2: 0 | L2: 0 | M2: 0 | N2: 0 | O2: 0 | P2: 0 | Q2: 352 | R2: 292 | S2: 644 | T2: 4 | U2: 2 | V2: 2 | W2: 0.02326 | X2: 14.29 | Y2: 14.29 | Z2: 11.27 | AA2: 13 | AB2: 11 | AC2: 2 | AD2: 0.07558 | AE2: 3 | AF2: 0 | AH2: 16 | AI2: 2.82 | AJ2: 16 | AK2: 2.82 | AL2: 3 | AM2: 15.03 | AN2: 0.01744 | AO2: 3.47 | AP2: 4 | AQ2: 761 | AR2: 3 | AS2: 0 | AT2: 0 | AU2: 0 | AV2: 0 | AW2: 1 | AX2: 338 | AY2: 163 | AZ2: 137 | BA2: 0.84049 | BB2: 0 | BC2: 0 | BD2: 0.09505 | BE2: 150 | BF2: 2 | BG2: 3 | BH2: 1 | BI2: 0 | BJ2: 0 | BK2: 0 | BL2: 3 | BM2: 1 | BN2: 214.67 | BO2: 0 | BP2: 0 | BQ2: 0 | BR2: 0 | BS2: 0 | BT2: 0
A3: 46104 | B3: 1024058244420 | C3: 商品 | D3: LENNEA法式油画网纱连衣裙夏季原创设计收腰圆领无袖背心碎花短裙 | E3: 390 | F3: 27 | G3: 2.83 | H3: 0.06923 | I3: 0.1 | J3: 7.26 | K3: 0 | L3: 0 | M3: 0 | N3: 0 | O3: 0 | P3: 0 | Q3: 0 | R3: 0 | S3: 0 | T3: 0 | U3: 0 | V3: 0 | W3: 0 | X3: 0 | Y3: 0 | AA3: 1 | AB3: 1 | AC3: 0 | AD3: 0.03704 | AE3: 1 | AF3: 1 | AG3: 2.83 | AH3: 3 | AI3: 0.94 | AJ3: 2 | AK3: 1.42 | AL3: 2 | AM3: 2.83 | AN3: 0.03704 | AO3: 2.83 | AP3: 0 | AQ3: 0 | AR3: 0 | AS3: 1 | AT3: 0 | AU3: 0 | AV3: 0 | AW3: 0 | AX3: 42 | AY3: 26 | AZ3: 22 | BA3: 0.84615 | BB3: 0 | BC3: 0 | BD3: 0.10769 | BE3: 15 | BF3: 2 | BG3: 0 | BI3: 0 | BJ3: 0 | BK3: 0 | BL3: 0 | BO3: 0 | BP3: 0 | BQ3: 0 | BR3: 0 | BS3: 0 | BT3: 0
A4: 46104 | B4: 1024056756230 | C4: 商品 | D4: LENNEA粉色碎花雪纺鱼尾裙夏季女高腰显瘦半身裙小个子短裙包臀裙 | E4: 114 | F4: 15 | G4: 1.38 | H4: 0.13158 | I4: 0.09 | J4: 12.11 | K4: 0 | L4: 0 | M4: 0 | N4: 0 | O4: 0 | P4: 0 | Q4: 0 | R4: 0 | S4: 0 | T4: 0 | U4: 0 | V4: 0 | W4: 0 | X4: 0 | Y4: 0 | AA4: 1 | AB4: 1 | AC4: 0 | AD4: 0.06667 | AE4: 0 | AF4: 0 | AH4: 1 | AI4: 1.38 | AJ4: 1 | AK4: 1.38 | AL4: 0 | AN4: 0 | AO4: 1.38 | AP4: 0 | AQ4: 0 | AR4: 0 | AS4: 0 | AT4: 0 | AU4: 0 | AV4: 0 | AW4: 0 | AX4: 22 | AY4: 14 | AZ4: 13 | BA4: 0.92857 | BB4: 0 | BC4: 0 | BD4: 0.19298 | BE4: 7 | BF4: 2 | BG4: 0 | BI4: 0 | BJ4: 0 | BK4: 0 | BL4: 0 | BO4: 0 | BP4: 0 | BQ4: 0 | BR4: 0 | BS4: 0 | BT4: 0
A5: 46104 | B5: 1024056572913 | C5: 商品 | D5: LENNEA假两件坎肩长袖针织衫女早春修身甜美内搭抹胸打底辣妹上衣 | E5: 279 | F5: 28 | G5: 12.47 | H5: 0.10036 | I5: 0.45 | J5: 44.7 | K5: 0 | L5: 0 | M5: 0 | N5: 0 | O5: 0 | P5: 0 | Q5: 0 | R5: 0 | S5: 0 | T5: 0 | U5: 0 | V5: 0 | W5: 0 | X5: 0 | Y5: 0 | AA5: 13 | AB5: 0 | AC5: 13 | AD5: 0.46429 | AE5: 5 | AF5: 1 | AG5: 12.47 | AH5: 19 | AI5: 0.66 | AJ5: 18 | AK5: 0.69 | AL5: 6 | AM5: 2.49 | AN5: 0.17857 | AO5: 0.96 | AP5: 0 | AQ5: 0 | AR5: 0 | AS5: 5 | AT5: 0 | AU5: 0 | AV5: 0 | AW5: 1 | AX5: 223 | AY5: 28 | AZ5: 22 | BA5: 0.78571 | BB5: 0 | BC5: 0 | BD5: 0.79928 | BE5: 195 | BF5: 8 | BG5: 0 | BI5: 0 | BJ5: 0 | BK5: 0 | BL5: 0 | BO5: 0 | BP5: 0 | BQ5: 0 | BR5: 0 | BS5: 0 | BT5: 0
A6: 46104 | B6: 1023269465985 | C6: 商品 | D6: LENNEA天丝荷叶边沙滩海边度假风吊带上衣夏季小个子连衣裙两件套 | E6: 644 | F6: 49 | G6: 5.13 | H6: 0.07609 | I6: 0.1 | J6: 7.97 | K6: 0 | L6: 0 | M6: 0 | N6: 0 | O6: 0 | P6: 0 | Q6: 0 | R6: 0 | S6: 0 | T6: 0 | U6: 0 | V6: 0 | W6: 0 | X6: 0 | Y6: 0 | AA6: 2 | AB6: 2 | AC6: 0 | AD6: 0.04082 | AE6: 0 | AF6: 0 | AH6: 2 | AI6: 2.57 | AJ6: 2 | AK6: 2.57 | AL6: 0 | AN6: 0 | AO6: 2.57 | AP6: 0 | AQ6: 0 | AR6: 0 | AS6: 0 | AT6: 0 | AU6: 0 | AV6: 0 | AW6: 0 | AX6: 72 | AY6: 48 | AZ6: 41 | BA6: 0.85417 | BB6: 0 | BC6: 0 | BD6: 0.1118 | BE6: 22 | BF6: 2 | BG6: 0 | BI6: 0 | BJ6: 0 | BK6: 0 | BL6: 0 | BO6: 0 | BP6: 0 | BQ6: 0 | BR6: 0 | BS6: 0 | BT6: 0
A7: 46104 | B7: 1022374874271 | C7: 商品 | D7: LENNEA初恋小白裙春夏季甜美减龄娃娃领短袖连衣裙小个子宽松短裙 | E7: 122 | F7: 6 | G7: 0.99 | H7: 0.04918 | I7: 0.17 | J7: 8.11 | K7: 0 | L7: 0 | M7: 0 | N7: 0 | O7: 0 | P7: 0 | Q7: 0 | R7: 0 | S7: 0 | T7: 0 | U7: 0 | V7: 0 | W7: 0 | X7: 0 | Y7: 0 | AA7: 0 | AB7: 0 | AC7: 0 | AD7: 0 | AE7: 0 | AF7: 0 | AH7: 0 | AJ7: 0 | AL7: 0 | AN7: 0 | AP7: 0 | AQ7: 0 | AR7: 0 | AS7: 0 | AT7: 0 | AU7: 0 | AV7: 0 | AW7: 0 | AX7: 20 | AY7: 7 | AZ7: 5 | BA7: 0.71429 | BB7: 0 | BC7: 0 | BD7: 0.16393 | BE7: 10 | BF7: 3 | BG7: 0 | BI7: 0 | BJ7: 0 | BK7: 0 | BL7: 0 | BO7: 0 | BP7: 0 | BQ7: 0 | BR7: 0 | BS7: 0 | BT7: 0
A8: 46104 | B8: 1018640025168 | C8: 商品 | D8: LENNEA黑色气质收腰娃娃领短袖连衣裙夏季小个子高级感小黑裙短裙 | E8: 484 | F8: 19 | G8: 6.45 | H8: 0.03926 | I8: 0.34 | J8: 13.33 | K8: 0 | L8: 0 | M8: 0 | N8: 0 | O8: 0 | P8: 0 | Q8: 0 | R8: 0 | S8: 0 | T8: 0 | U8: 0 | V8: 0 | W8: 0 | X8: 0 | Y8: 0 | AA8: 1 | AB8: 1 | AC8: 0 | AD8: 0.05263 | AE8: 0 | AF8: 0 | AH8: 1 | AI8: 6.45 | AJ8: 1 | AK8: 6.45 | AL8: 0 | AN8: 0 | AO8: 6.45 | AP8: 0 | AQ8: 0 | AR8: 0 | AS8: 0 | AT8: 0 | AU8: 0 | AV8: 0 | AW8: 0 | AX8: 32 | AY8: 18 | AZ8: 14 | BA8: 0.77778 | BB8: 0 | BC8: 0 | BD8: 0.06612 | BE8: 14 | BF8: 2 | BG8: 0 | BI8: 0 | BJ8: 0 | BK8: 0 | BL8: 0 | BO8: 0 | BP8: 0 | BQ8: 0 | BR8: 0 | BS8: 0 | BT8: 0
A9: 46104 | B9: 1017763274224 | C9: 商品 | D9: LENNEA芭蕾风蓝色收腰连衣裙夏季无袖蓬蓬裙公主裙小个子千金短裙 | E9: 6389 | F9: 549 | G9: 215.36 | H9: 0.08593 | I9: 0.39 | J9: 33.71 | K9: 0 | L9: 0 | M9: 0 | N9: 0 | O9: 0 | P9: 0 | Q9: 0 | R9: 1297 | S9: 1297 | T9: 9 | U9: 0 | V9: 9 | W9: 0.01639 | X9: 6.02 | Y9: 6.02 | Z9: 23.93 | AA9: 177 | AB9: 5 | AC9: 172 | AD9: 0.3224 | AE9: 31 | AF9: 15 | AG9: 14.36 | AH9: 223 | AI9: 0.97 | AJ9: 208 | AK9: 1.04 | AL9: 46 | AM9: 6.95 | AN9: 0.05647 | AO9: 1.22 | AP9: 10 | AQ9: 1740 | AR9: 4 | AS9: 27 | AT9: 0 | AU9: 0 | AV9: 0 | AW9: 12 | AX9: 2824 | AY9: 506 | AZ9: 448 | BA9: 0.88538 | BB9: 0 | BC9: 0 | BD9: 0.44201 | BE9: 2253 | BF9: 6 | BG9: 6 | BH9: 1 | BI9: 0 | BJ9: 0 | BK9: 0 | BL9: 6 | BM9: 2 | BN9: 216.17 | BO9: 0 | BP9: 0 | BQ9: 0 | BR9: 0 | BS9: 0 | BT9: 0
A10: 46104 | B10: 1017116707008 | C10: 商品 | D10: LENNEA波点花边袖黑色短袖针织T恤女圆领修身打底衫早春小众上衣 | E10: 6345 | F10: 361 | G10: 116.21 | H10: 0.0569 | I10: 0.32 | J10: 18.32 | K10: 0 | L10: 0 | M10: 0 | N10: 0 | O10: 0 | P10: 0 | Q10: 282 | R10: 588 | S10: 870 | T10: 6 | U10: 2 | V10: 4 | W10: 0.01662 | X10: 7.49 | Y10: 7.49 | Z10: 19.37 | AA10: 51 | AB10: 36 | AC10: 15 | AD10: 0.14127 | AE10: 15 | AF10: 5 | AG10: 23.24 | AH10: 71 | AI10: 1.64 | AJ10: 66 | AK10: 1.76 | AL10: 20 | AM10: 7.75 | AN10: 0.04155 | AO10: 2.28 | AP10: 6 | AQ10: 1028 | AR10: 6 | AS10: 9 | AT10: 0 | AU10: 0 | AV10: 0 | AW10: 8 | AX10: 1050 | AY10: 341 | AZ10: 219 | BA10: 0.64223 | BB10: 0 | BC10: 0 | BD10: 0.16548 | BE10: 649 | BF10: 3 | BG10: 5 | BH10: 1 | BI10: 0 | BJ10: 0 | BK10: 0 | BL10: 5 | BM10: 1 | BN10: 174 | BO10: 0 | BP10: 0 | BQ10: 0 | BR10: 0 | BS10: 0 | BT10: 0
A11: 46104 | B11: 1008947108996 | C11: 商品 | D11: LENNEA 学院风娃娃领纽扣短外套女韩系春季长袖开衫白色半裙套装 | E11: 5998 | F11: 319 | G11: 45.54 | H11: 0.05318 | I11: 0.14 | J11: 7.59 | K11: 0 | L11: 0 | M11: 0 | N11: 0 | O11: 0 | P11: 0 | Q11: 187 | R11: 144 | S11: 331 | T11: 2 | U11: 1 | V11: 1 | W11: 0.00627 | X11: 7.27 | Y11: 7.27 | Z11: 22.77 | AA11: 12 | AB11: 4 | AC11: 8 | AD11: 0.03762 | AE11: 1 | AF11: 3 | AG11: 15.18 | AH11: 16 | AI11: 2.85 | AJ11: 13 | AK11: 3.5 | AL11: 4 | AM11: 45.54 | AN11: 0.00313 | AO11: 3.8 | AP11: 2 | AQ11: 391 | AR11: 0 | AS11: 1 | AT11: 0 | AU11: 0 | AV11: 0 | AW11: 2 | AX11: 731 | AY11: 305 | AZ11: 232 | BA11: 0.76066 | BB11: 0 | BC11: 0 | BD11: 0.12187 | BE11: 372 | BF11: 2 | BG11: 2 | BH11: 1 | BI11: 0 | BJ11: 0 | BK11: 0 | BL11: 2 | BM11: 1 | BN11: 165.5 | BO11: 0 | BP11: 0 | BQ11: 0 | BR11: 0 | BS11: 0 | BT11: 0
A12: 46104 | B12: 1008945688714 | C12: 商品 | D12: LENNEA 春季少女风蕾丝拼接衬衫女长袖宽松防晒薄款外套休闲百搭 | E12: 8727 | F12: 577 | G12: 90.42 | H12: 0.06612 | I12: 0.16 | J12: 10.36 | K12: 0 | L12: 0 | M12: 0 | N12: 0 | O12: 0 | P12: 0 | Q12: 447 | R12: 0 | S12: 447 | T12: 3 | U12: 3 | V12: 0 | W12: 0.0052 | X12: 4.94 | Y12: 4.94 | Z12: 30.14 | AA12: 31 | AB12: 28 | AC12: 3 | AD12: 0.05373 | AE12: 7 | AF12: 1 | AG12: 90.42 | AH12: 39 | AI12: 2.32 | AJ12: 38 | AK12: 2.38 | AL12: 8 | AM12: 12.92 | AN12: 0.01213 | AO12: 2.92 | AP12: 3 | AQ12: 528 | AR12: 7 | AS12: 0 | AT12: 0 | AU12: 0 | AV12: 0 | AW12: 1 | AX12: 1175 | AY12: 560 | AZ12: 424 | BA12: 0.75714 | BB12: 0 | BC12: 0 | BD12: 0.13464 | BE12: 573 | BF12: 2 | BG12: 3 | BH12: 1 | BI12: 0 | BJ12: 0 | BK12: 0 | BL12: 3 | BM12: 1 | BN12: 149 | BO12: 0 | BP12: 0 | BQ12: 0 | BR12: 0 | BS12: 0 | BT12: 0
A13: 46104 | B13: 1008197333492 | C13: 商品 | D13: LENNEA 2026年春季千金风一字肩针织连衣裙女蓝色系腰带短裙子 | E13: 158 | F13: 12 | G13: 3.22 | H13: 0.07595 | I13: 0.27 | J13: 20.38 | K13: 0 | L13: 0 | M13: 0 | N13: 0 | O13: 0 | P13: 0 | Q13: 0 | R13: 0 | S13: 0 | T13: 0 | U13: 0 | V13: 0 | W13: 0 | X13: 0 | Y13: 0 | AA13: 2 | AB13: 0 | AC13: 2 | AD13: 0.16667 | AE13: 3 | AF13: 1 | AG13: 3.22 | AH13: 6 | AI13: 0.54 | AJ13: 5 | AK13: 0.64 | AL13: 4 | AM13: 1.07 | AN13: 0.25 | AO13: 1.61 | AP13: 0 | AQ13: 0 | AR13: 0 | AS13: 3 | AT13: 0 | AU13: 0 | AV13: 0 | AW13: 0 | AX13: 52 | AY13: 12 | AZ13: 12 | BA13: 1 | BB13: 0 | BC13: 0 | BD13: 0.32911 | BE13: 40 | BF13: 4 | BG13: 0 | BI13: 0 | BJ13: 0 | BK13: 0 | BL13: 0 | BO13: 0 | BP13: 0 | BQ13: 0 | BR13: 0 | BS13: 0 | BT13: 0
A14: 46104 | B14: 1008191325407 | C14: 商品 | D14: LENNEA学院风高领麻花毛衣女春秋宽松不对称斗篷针织衫慵懒风上衣 | E14: 319 | F14: 20 | G14: 2.95 | H14: 0.0627 | I14: 0.15 | J14: 9.25 | K14: 0 | L14: 0 | M14: 0 | N14: 0 | O14: 0 | P14: 0 | Q14: 189 | R14: 0 | S14: 189 | T14: 1 | U14: 1 | V14: 0 | W14: 0.05 | X14: 64.07 | Y14: 64.07 | Z14: 2.95 | AA14: 3 | AB14: 1 | AC14: 2 | AD14: 0.15 | AE14: 0 | AF14: 0 | AH14: 3 | AI14: 0.98 | AJ14: 3 | AK14: 0.98 | AL14: 0 | AN14: 0 | AO14: 0.98 | AP14: 1 | AQ14: 223 | AR14: 0 | AS14: 0 | AT14: 0 | AU14: 0 | AV14: 0 | AW14: 1 | AX14: 40 | AY14: 19 | AZ14: 18 | BA14: 0.94737 | BB14: 0 | BC14: 0 | BD14: 0.12539 | BE14: 18 | BF14: 2 | BG14: 1 | BH14: 1 | BI14: 0 | BJ14: 0 | BK14: 0 | BL14: 1 | BM14: 1 | BN14: 189 | BO14: 0 | BP14: 0 | BQ14: 0 | BR14: 0 | BS14: 0 | BT14: 0
A15: 46104 | B15: 1007371530025 | C15: 商品 | D15: LENNEA 复古风立领短款风衣女春季双排扣设计感长袖休闲外套宽松 | E15: 9425 | F15: 721 | G15: 100.85 | H15: 0.0765 | I15: 0.14 | J15: 10.7 | K15: 0 | L15: 0 | M15: 0 | N15: 0 | O15: 0 | P15: 0 | Q15: 1485 | R15: 0 | S15: 1485 | T15: 4 | U15: 4 | V15: 0 | W15: 0.00555 | X15: 14.72 | Y15: 14.72 | Z15: 25.21 | AA15: 20 | AB15: 19 | AC15: 1 | AD15: 0.02774 | AE15: 2 | AF15: 0 | AH15: 22 | AI15: 4.58 | AJ15: 22 | AK15: 4.58 | AL15: 2 | AM15: 50.43 | AN15: 0.00277 | AO15: 5.04 | AP15: 5 | AQ15: 2100 | AR15: 2 | AS15: 0 | AT15: 0 | AU15: 0 | AV15: 0 | AW15: 0 | AX15: 1397 | AY15: 701 | AZ15: 630 | BA15: 0.89872 | BB15: 0 | BC15: 0 | BD15: 0.14822 | BE15: 643 | BF15: 2 | BG15: 4 | BH15: 1 | BI15: 0 | BJ15: 0 | BK15: 0 | BL15: 4 | BM15: 1 | BN15: 371.25 | BO15: 0 | BP15: 0 | BQ15: 0 | BR15: 0 | BS15: 0 | BT15: 0
A16: 46104 | B16: 1006744639564 | C16: 商品 | D16: LENNEA 费尔岛风连帽拉链针织开衫女春秋冬宽松学院风毛衣外套 | E16: 39 | F16: 5 | G16: 0.73 | H16: 0.12821 | I16: 0.15 | J16: 18.72 | K16: 0 | L16: 0 | M16: 0 | N16: 0 | O16: 0 | P16: 0 | Q16: 0 | R16: 0 | S16: 0 | T16: 0 | U16: 0 | V16: 0 | W16: 0 | X16: 0 | Y16: 0 | AA16: 1 | AB16: 0 | AC16: 1 | AD16: 0.2 | AE16: 0 | AF16: 0 | AH16: 1 | AI16: 0.73 | AJ16: 1 | AK16: 0.73 | AL16: 0 | AN16: 0 | AO16: 0.73 | AP16: 0 | AQ16: 0 | AR16: 0 | AS16: 0 | AT16: 0 | AU16: 0 | AV16: 0 | AW16: 0 | AX16: 10 | AY16: 5 | AZ16: 5 | BA16: 1 | BB16: 0 | BC16: 0 | BD16: 0.25641 | BE16: 5 | BF16: 2 | BG16: 0 | BI16: 0 | BJ16: 0 | BK16: 0 | BL16: 0 | BO16: 0 | BP16: 0 | BQ16: 0 | BR16: 0 | BS16: 0 | BT16: 0
A17: 46104 | B17: 992234348721 | C17: 商品 | D17: LENNEA冬季新款绞花针织拼接长袖波点棉服女上衣保暖短外套棉衣 | E17: 142 | F17: 16 | G17: 1.68 | H17: 0.11268 | I17: 0.11 | J17: 11.83 | K17: 0 | L17: 0 | M17: 0 | N17: 0 | O17: 0 | P17: 0 | Q17: 0 | R17: 0 | S17: 0 | T17: 0 | U17: 0 | V17: 0 | W17: 0 | X17: 0 | Y17: 0 | AA17: 1 | AB17: 0 | AC17: 1 | AD17: 0.0625 | AE17: 0 | AF17: 0 | AH17: 1 | AI17: 1.68 | AJ17: 1 | AK17: 1.68 | AL17: 0 | AN17: 0 | AO17: 1.68 | AP17: 0 | AQ17: 0 | AR17: 0 | AS17: 0 | AT17: 0 | AU17: 0 | AV17: 0 | AW17: 0 | AX17: 31 | AY17: 16 | AZ17: 14 | BA17: 0.875 | BB17: 0 | BC17: 0 | BD17: 0.21831 | BE17: 14 | BF17: 2 | BG17: 0 | BI17: 0 | BJ17: 0 | BK17: 0 | BL17: 0 | BO17: 0 | BP17: 0 | BQ17: 0 | BR17: 0 | BS17: 0 | BT17: 0
A18: 46104 | B18: 988780710366 | C18: 商品 | D18: LENNEA小香风白色外套女春2025新款深秋初冬高级短款羊毛感上衣 | E18: 190 | F18: 10 | G18: 3 | H18: 0.05263 | I18: 0.3 | J18: 15.79 | K18: 0 | L18: 0 | M18: 0 | N18: 0 | O18: 0 | P18: 0 | Q18: 0 | R18: 0 | S18: 0 | T18: 0 | U18: 0 | V18: 0 | W18: 0 | X18: 0 | Y18: 0 | AA18: 0 | AB18: 0 | AC18: 0 | AD18: 0 | AE18: 0 | AF18: 0 | AH18: 0 | AJ18: 0 | AL18: 0 | AN18: 0 | AP18: 0 | AQ18: 0 | AR18: 0 | AS18: 0 | AT18: 0 | AU18: 0 | AV18: 0 | AW18: 0 | AX18: 15 | AY18: 10 | AZ18: 8 | BA18: 0.8 | BB18: 0 | BC18: 0 | BD18: 0.07895 | BE18: 5 | BF18: 2 | BG18: 0 | BI18: 0 | BJ18: 0 | BK18: 0 | BL18: 0 | BO18: 0 | BP18: 0 | BQ18: 0 | BR18: 0 | BS18: 0 | BT18: 0
A19: 46104 | B19: 987169874467 | C19: 商品 | D19: LENNEA毛领双排扣短款毛呢羊毛大衣连帽外套女收腰秋冬加厚上衣 | E19: 59 | F19: 2 | G19: 0.33 | H19: 0.0339 | I19: 0.17 | J19: 5.59 | K19: 0 | L19: 0 | M19: 0 | N19: 0 | O19: 0 | P19: 0 | Q19: 0 | R19: 0 | S19: 0 | T19: 0 | U19: 0 | V19: 0 | W19: 0 | X19: 0 | Y19: 0 | AA19: 0 | AB19: 0 | AC19: 0 | AD19: 0 | AE19: 0 | AF19: 0 | AH19: 0 | AJ19: 0 | AL19: 0 | AN19: 0 | AP19: 0 | AQ19: 0 | AR19: 0 | AS19: 0 | AT19: 0 | AU19: 0 | AV19: 0 | AW19: 0 | AX19: 9 | AY19: 2 | AZ19: 2 | BA19: 1 | BB19: 0 | BC19: 0 | BD19: 0.15254 | BE19: 7 | BF19: 5 | BG19: 0 | BI19: 0 | BJ19: 0 | BK19: 0 | BL19: 0 | BO19: 0 | BP19: 0 | BQ19: 0 | BR19: 0 | BS19: 0 | BT19: 0
A20: 46104 | B20: 986610503692 | C20: 商品 | D20: LENNEA毛毛外套女冬季短款翻领正肩皮毛一体环保毛皮草上衣女冬 | E20: 167 | F20: 14 | G20: 1.17 | H20: 0.08383 | I20: 0.08 | J20: 7.01 | K20: 0 | L20: 0 | M20: 0 | N20: 0 | O20: 0 | P20: 0 | Q20: 0 | R20: 0 | S20: 0 | T20: 0 | U20: 0 | V20: 0 | W20: 0 | X20: 0 | Y20: 0 | AA20: 1 | AB20: 1 | AC20: 0 | AD20: 0.07143 | AE20: 0 | AF20: 0 | AH20: 1 | AI20: 1.17 | AJ20: 1 | AK20: 1.17 | AL20: 0 | AN20: 0 | AO20: 1.17 | AP20: 0 | AQ20: 0 | AR20: 0 | AS20: 0 | AT20: 0 | AU20: 0 | AV20: 0 | AW20: 0 | AX20: 29 | AY20: 12 | AZ20: 7 | BA20: 0.58333 | BB20: 0 | BC20: 0 | BD20: 0.17365 | BE20: 14 | BF20: 2 | BG20: 0 | BI20: 0 | BJ20: 0 | BK20: 0 | BL20: 0 | BO20: 0 | BP20: 0 | BQ20: 0 | BR20: 0 | BS20: 0 | BT20: 0
A21: 46104 | B21: 972548387983 | C21: 商品 | D21: LENNEA藏青色毛领连帽棉服女冬季新款宽松保暖小个子百搭棉衣外套 | E21: 53 | F21: 2 | G21: 2.2 | H21: 0.03774 | I21: 1.1 | J21: 41.51 | K21: 0 | L21: 0 | M21: 0 | N21: 0 | O21: 0 | P21: 0 | Q21: 0 | R21: 0 | S21: 0 | T21: 0 | U21: 0 | V21: 0 | W21: 0 | X21: 0 | Y21: 0 | AA21: 0 | AB21: 0 | AC21: 0 | AD21: 0 | AE21: 0 | AF21: 0 | AH21: 0 | AJ21: 0 | AL21: 0 | AN21: 0 | AP21: 0 | AQ21: 0 | AR21: 0 | AS21: 0 | AT21: 0 | AU21: 0 | AV21: 0 | AW21: 0 | AX21: 8 | AY21: 2 | AZ21: 2 | BA21: 1 | BB21: 0 | BC21: 0 | BD21: 0.15094 | BE21: 6 | BF21: 4 | BG21: 0 | BI21: 0 | BJ21: 0 | BK21: 0 | BL21: 0 | BO21: 0 | BP21: 0 | BQ21: 0 | BR21: 0 | BS21: 0 | BT21: 0
A22: 46104 | B22: 970286397535 | C22: 商品 | D22: LENNEA小香风外套女秋冬2025新款深秋初冬高级短款羊毛感上衣春 | E22: 511 | F22: 24 | G22: 6.4 | H22: 0.04697 | I22: 0.27 | J22: 12.52 | K22: 0 | L22: 0 | M22: 0 | N22: 0 | O22: 0 | P22: 0 | Q22: 0 | R22: 0 | S22: 0 | T22: 0 | U22: 0 | V22: 0 | W22: 0 | X22: 0 | Y22: 0 | AA22: 0 | AB22: 0 | AC22: 0 | AD22: 0 | AE22: 0 | AF22: 0 | AH22: 0 | AJ22: 0 | AL22: 0 | AN22: 0 | AP22: 0 | AQ22: 0 | AR22: 0 | AS22: 0 | AT22: 0 | AU22: 0 | AV22: 0 | AW22: 1 | AX22: 48 | AY22: 24 | AZ22: 19 | BA22: 0.79167 | BB22: 0 | BC22: 0 | BD22: 0.09393 | BE22: 24 | BF22: 2 | BG22: 0 | BI22: 0 | BJ22: 0 | BK22: 0 | BL22: 0 | BO22: 0 | BP22: 0 | BQ22: 0 | BR22: 0 | BS22: 0 | BT22: 0
A23: 46104 | B23: 969105067992 | C23: 商品 | D23: LENNEA气质大毛领羽绒服外套女秋冬季连帽毛呢上衣小个子夹棉保暖 | E23: 492 | F23: 34 | G23: 8.99 | H23: 0.06911 | I23: 0.26 | J23: 18.27 | K23: 0 | L23: 0 | M23: 0 | N23: 0 | O23: 0 | P23: 0 | Q23: 0 | R23: 0 | S23: 0 | T23: 0 | U23: 0 | V23: 0 | W23: 0 | X23: 0 | Y23: 0 | AA23: 1 | AB23: 1 | AC23: 0 | AD23: 0.02941 | AE23: 0 | AF23: 0 | AH23: 1 | AI23: 8.99 | AJ23: 1 | AK23: 8.99 | AL23: 0 | AN23: 0 | AO23: 8.99 | AP23: 0 | AQ23: 0 | AR23: 0 | AS23: 0 | AT23: 0 | AU23: 0 | AV23: 0 | AW23: 0 | AX23: 47 | AY23: 30 | AZ23: 26 | BA23: 0.86667 | BB23: 0 | BC23: 0 | BD23: 0.09553 | BE23: 13 | BF23: 2 | BG23: 0 | BI23: 0 | BJ23: 0 | BK23: 0 | BL23: 0 | BO23: 0 | BP23: 0 | BQ23: 0 | BR23: 0 | BS23: 0 | BT23: 0
A24: 46104 | B24: 966724894105 | C24: 商品 | D24: LENNEA灰色彩点镶钻毛衣外套女针织开衫miu系高级感软糯上衣外套 | E24: 1187 | F24: 64 | G24: 13.17 | H24: 0.05392 | I24: 0.21 | J24: 11.1 | K24: 0 | L24: 0 | M24: 0 | N24: 0 | O24: 0 | P24: 0 | Q24: 0 | R24: 176 | S24: 176 | T24: 1 | U24: 0 | V24: 1 | W24: 0.01563 | X24: 13.36 | Y24: 13.36 | Z24: 13.17 | AA24: 8 | AB24: 4 | AC24: 4 | AD24: 0.125 | AE24: 1 | AF24: 1 | AG24: 13.17 | AH24: 10 | AI24: 1.32 | AJ24: 9 | AK24: 1.46 | AL24: 2 | AM24: 13.17 | AN24: 0.01563 | AO24: 1.65 | AP24: 1 | AQ24: 208 | AR24: 0 | AS24: 1 | AT24: 0 | AU24: 0 | AV24: 0 | AW24: 0 | AX24: 182 | AY24: 62 | AZ24: 48 | BA24: 0.77419 | BB24: 0 | BC24: 0 | BD24: 0.15333 | BE24: 114 | BF24: 3 | BG24: 1 | BH24: 1 | BI24: 0 | BJ24: 0 | BK24: 0 | BL24: 1 | BM24: 1 | BN24: 176 | BO24: 0 | BP24: 0 | BQ24: 0 | BR24: 0 | BS24: 0 | BT24: 0
A25: 46104 | B25: 959252941279 | C25: 商品 | D25: LENNEA波点花边袖黑色长袖针织开衫女miu系修身打底衫早秋上衣春 | E25: 86109 | F25: 4526 | G25: 1672.86 | H25: 0.05256 | I25: 0.37 | J25: 19.43 | K25: 0 | L25: 0 | M25: 0 | N25: 0 | O25: 0 | P25: 0 | Q25: 17650 | R25: 2974 | S25: 20624 | T25: 138 | U25: 121 | V25: 17 | W25: 0.03049 | X25: 12.33 | Y25: 12.33 | Z25: 12.12 | AA25: 657 | AB25: 528 | AC25: 129 | AD25: 0.14516 | AE25: 107 | AF25: 44 | AG25: 38.02 | AH25: 808 | AI25: 2.07 | AJ25: 764 | AK25: 2.19 | AL25: 151 | AM25: 15.63 | AN25: 0.02364 | AO25: 2.55 | AP25: 149 | AQ25: 26206 | AR25: 90 | AS25: 17 | AT25: 0 | AU25: 0 | AV25: 0 | AW25: 27 | AX25: 12126 | AY25: 4198 | AZ25: 3405 | BA25: 0.8111 | BB25: 0 | BC25: 0 | BD25: 0.14082 | BE25: 7127 | BF25: 3 | BG25: 75 | BH25: 0.98684 | BI25: 0 | BJ25: 0 | BK25: 0 | BL25: 76 | BM25: 2 | BN25: 271.37 | BO25: 0 | BP25: 0 | BQ25: 0 | BR25: 0 | BS25: 0 | BT25: 0
A26: 46104 | B26: 952989667628 | C26: 商品 | D26: LENNEA白色牛仔裤女宽松垂感阔腿裤高腰显瘦休闲百搭拖地长裤子 | E26: 1334 | F26: 165 | G26: 63.56 | H26: 0.12369 | I26: 0.39 | J26: 47.65 | K26: 0 | L26: 0 | M26: 0 | N26: 0 | O26: 0 | P26: 0 | Q26: 0 | R26: 0 | S26: 0 | T26: 0 | U26: 0 | V26: 0 | W26: 0 | X26: 0 | Y26: 0 | AA26: 42 | AB26: 2 | AC26: 40 | AD26: 0.25455 | AE26: 7 | AF26: 5 | AG26: 12.71 | AH26: 54 | AI26: 1.18 | AJ26: 49 | AK26: 1.3 | AL26: 12 | AM26: 9.08 | AN26: 0.04242 | AO26: 1.51 | AP26: 0 | AQ26: 0 | AR26: 0 | AS26: 7 | AT26: 0 | AU26: 0 | AV26: 0 | AW26: 6 | AX26: 906 | AY26: 156 | AZ26: 141 | BA26: 0.90385 | BB26: 0 | BC26: 0 | BD26: 0.67916 | BE26: 733 | BF26: 6 | BG26: 0 | BI26: 0 | BJ26: 0 | BK26: 0 | BL26: 0 | BO26: 0 | BP26: 0 | BQ26: 0 | BR26: 0 | BS26: 0 | BT26: 0
A27: 46104 | B27: 949754058834 | C27: 商品 | D27: LENNEA黑色小香风外套女短款长袖针织开衫气质高级感排扣外套上衣 | E27: 3108 | F27: 299 | G27: 68.84 | H27: 0.0962 | I27: 0.23 | J27: 22.15 | K27: 0 | L27: 0 | M27: 0 | N27: 0 | O27: 0 | P27: 0 | Q27: 672 | R27: 485 | S27: 1157 | T27: 7 | U27: 4 | V27: 3 | W27: 0.02341 | X27: 16.81 | Y27: 16.81 | Z27: 9.83 | AA27: 66 | AB27: 7 | AC27: 59 | AD27: 0.22074 | AE27: 16 | AF27: 10 | AG27: 6.88 | AH27: 92 | AI27: 0.75 | AJ27: 82 | AK27: 0.84 | AL27: 26 | AM27: 4.3 | AN27: 0.05351 | AO27: 1.04 | AP27: 8 | AQ27: 1563 | AR27: 2 | AS27: 14 | AT27: 0 | AU27: 0 | AV27: 0 | AW27: 5 | AX27: 1266 | AY27: 283 | AZ27: 250 | BA27: 0.88339 | BB27: 0 | BC27: 0 | BD27: 0.40734 | BE27: 948 | BF27: 4 | BG27: 5 | BH27: 1 | BI27: 0 | BJ27: 0 | BK27: 0 | BL27: 5 | BM27: 1 | BN27: 231.4 | BO27: 0 | BP27: 0 | BQ27: 0 | BR27: 0 | BS27: 0 | BT27: 0
A28: 46104 | B28: 949034219575 | C28: 商品 | D28: LENNEA慵懒感减龄海军领毛衣女秋季温柔设计感学院风针织上衣女春 | E28: 2070 | F28: 121 | G28: 24.27 | H28: 0.05845 | I28: 0.2 | J28: 11.72 | K28: 0 | L28: 0 | M28: 0 | N28: 0 | O28: 0 | P28: 0 | Q28: 0 | R28: 0 | S28: 0 | T28: 0 | U28: 0 | V28: 0 | W28: 0 | X28: 0 | Y28: 0 | AA28: 8 | AB28: 5 | AC28: 3 | AD28: 0.06612 | AE28: 2 | AF28: 0 | AH28: 10 | AI28: 2.43 | AJ28: 10 | AK28: 2.43 | AL28: 2 | AM28: 12.14 | AN28: 0.01653 | AO28: 3.03 | AP28: 0 | AQ28: 0 | AR28: 2 | AS28: 0 | AT28: 0 | AU28: 0 | AV28: 0 | AW28: 0 | AX28: 252 | AY28: 119 | AZ28: 92 | BA28: 0.77311 | BB28: 0 | BC28: 0 | BD28: 0.12174 | BE28: 103 | BF28: 2 | BG28: 0 | BI28: 0 | BJ28: 0 | BK28: 0 | BL28: 0 | BO28: 0 | BP28: 0 | BQ28: 0 | BR28: 0 | BS28: 0 | BT28: 0
A29: 46104 | B29: 926919925240 | C29: 商品 | D29: LENNEA粉色蓬蓬花苞半身裙女夏季新款设计感高腰显瘦a字芭蕾裤裙 | E29: 564 | F29: 31 | G29: 9.93 | H29: 0.05496 | I29: 0.32 | J29: 17.61 | K29: 0 | L29: 0 | M29: 0 | N29: 0 | O29: 0 | P29: 0 | Q29: 0 | R29: 0 | S29: 0 | T29: 0 | U29: 0 | V29: 0 | W29: 0 | X29: 0 | Y29: 0 | AA29: 2 | AB29: 0 | AC29: 2 | AD29: 0.06452 | AE29: 3 | AF29: 0 | AH29: 5 | AI29: 1.99 | AJ29: 5 | AK29: 1.99 | AL29: 3 | AM29: 3.31 | AN29: 0.09677 | AO29: 4.97 | AP29: 0 | AQ29: 0 | AR29: 3 | AS29: 0 | AT29: 0 | AU29: 0 | AV29: 0 | AW29: 0 | AX29: 50 | AY29: 29 | AZ29: 28 | BA29: 0.96552 | BB29: 0 | BC29: 0 | BD29: 0.08865 | BE29: 19 | BF29: 2 | BG29: 0 | BI29: 0 | BJ29: 0 | BK29: 0 | BL29: 0 | BO29: 0 | BP29: 0 | BQ29: 0 | BR29: 0 | BS29: 0 | BT29: 0
A30: 46104 | B30: 920335022314 | C30: 商品 | D30: LENNEA法式拼接连衣裙女夏季新款简约气质收腰显瘦无袖小众裙子 | E30: 327 | F30: 20 | G30: 4.3 | H30: 0.06116 | I30: 0.22 | J30: 13.15 | K30: 0 | L30: 0 | M30: 0 | N30: 0 | O30: 0 | P30: 0 | Q30: 0 | R30: 0 | S30: 0 | T30: 0 | U30: 0 | V30: 0 | W30: 0 | X30: 0 | Y30: 0 | AA30: 7 | AB30: 0 | AC30: 7 | AD30: 0.35 | AE30: 1 | AF30: 2 | AG30: 2.15 | AH30: 10 | AI30: 0.43 | AJ30: 8 | AK30: 0.54 | AL30: 3 | AM30: 4.3 | AN30: 0.05 | AO30: 0.61 | AP30: 0 | AQ30: 0 | AR30: 0 | AS30: 1 | AT30: 0 | AU30: 0 | AV30: 0 | AW30: 0 | AX30: 97 | AY30: 20 | AZ30: 16 | BA30: 0.8 | BB30: 0 | BC30: 0 | BD30: 0.29664 | BE30: 76 | BF30: 5 | BG30: 0 | BI30: 0 | BJ30: 0 | BK30: 0 | BL30: 0 | BO30: 0 | BP30: 0 | BQ30: 0 | BR30: 0 | BS30: 0 | BT30: 0
A31: 46104 | B31: 905381044899 | C31: 商品 | D31: LENNEA法式小个子设计感减龄黄色连衣裙子女夏季无袖背心花苞短裙 | E31: 120444 | F31: 5680 | G31: 1262.24 | H31: 0.04716 | I31: 0.22 | J31: 10.48 | K31: 0 | L31: 0 | M31: 0 | N31: 0 | O31: 0 | P31: 0 | Q31: 3889 | R31: 0 | S31: 3889 | T31: 22 | U31: 22 | V31: 0 | W31: 0.00387 | X31: 3.08 | Y31: 3.08 | Z31: 57.37 | AA31: 398 | AB31: 359 | AC31: 39 | AD31: 0.07007 | AE31: 153 | AF31: 26 | AG31: 48.55 | AH31: 577 | AI31: 2.19 | AJ31: 551 | AK31: 2.29 | AL31: 179 | AM31: 8.25 | AN31: 0.02694 | AO31: 3.17 | AP31: 22 | AQ31: 4596 | AR31: 142 | AS31: 11 | AT31: 0 | AU31: 0 | AV31: 0 | AW31: 15 | AX31: 11229 | AY31: 5357 | AZ31: 4881 | BA31: 0.91114 | BB31: 0 | BC31: 0 | BD31: 0.09323 | BE31: 5008 | BF31: 2 | BG31: 22 | BH31: 1 | BI31: 0 | BJ31: 0 | BK31: 0 | BL31: 22 | BM31: 1 | BN31: 176.77 | BO31: 0 | BP31: 0 | BQ31: 0 | BR31: 0 | BS31: 0 | BT31: 0
A32: 46104 | B32: 905004041827 | C32: 商品 | D32: LENNEA原创蕾丝荡领短袖t恤女夏季纯欲设计感斜肩别致韩系上衣 | E32: 1996 | F32: 94 | G32: 33.49 | H32: 0.04709 | I32: 0.36 | J32: 16.78 | K32: 0 | L32: 0 | M32: 0 | N32: 0 | O32: 0 | P32: 0 | Q32: 0 | R32: 0 | S32: 0 | T32: 0 | U32: 0 | V32: 0 | W32: 0 | X32: 0 | Y32: 0 | AA32: 6 | AB32: 2 | AC32: 4 | AD32: 0.06383 | AE32: 3 | AF32: 0 | AH32: 9 | AI32: 3.72 | AJ32: 9 | AK32: 3.72 | AL32: 3 | AM32: 11.16 | AN32: 0.03191 | AO32: 5.58 | AP32: 0 | AQ32: 0 | AR32: 2 | AS32: 1 | AT32: 0 | AU32: 0 | AV32: 0 | AW32: 0 | AX32: 187 | AY32: 87 | AZ32: 78 | BA32: 0.89655 | BB32: 0 | BC32: 0 | BD32: 0.09369 | BE32: 91 | BF32: 2 | BG32: 0 | BI32: 0 | BJ32: 0 | BK32: 0 | BL32: 0 | BO32: 0 | BP32: 0 | BQ32: 0 | BR32: 0 | BS32: 0 | BT32: 0
A33: 46104 | B33: 904997441508 | C33: 商品 | D33: LENNEA芭蕾风法式复古低腰花苞a字半身裙女夏季甜美蓬蓬灯笼短裙 | E33: 4436 | F33: 283 | G33: 75.38 | H33: 0.0638 | I33: 0.27 | J33: 16.99 | K33: 0 | L33: 0 | M33: 0 | N33: 0 | O33: 0 | P33: 0 | Q33: 0 | R33: 0 | S33: 0 | T33: 0 | U33: 0 | V33: 0 | W33: 0 | X33: 0 | Y33: 0 | AA33: 14 | AB33: 13 | AC33: 1 | AD33: 0.04947 | AE33: 7 | AF33: 0 | AH33: 21 | AI33: 3.59 | AJ33: 21 | AK33: 3.59 | AL33: 7 | AM33: 10.77 | AN33: 0.02473 | AO33: 5.38 | AP33: 0 | AQ33: 0 | AR33: 6 | AS33: 1 | AT33: 0 | AU33: 0 | AV33: 0 | AW33: 0 | AX33: 425 | AY33: 274 | AZ33: 247 | BA33: 0.90146 | BB33: 0 | BC33: 0 | BD33: 0.09581 | BE33: 136 | BF33: 2 | BG33: 0 | BI33: 0 | BJ33: 0 | BK33: 0 | BL33: 0 | BO33: 0 | BP33: 0 | BQ33: 0 | BR33: 0 | BS33: 0 | BT33: 0
A34: 46104 | B34: 874018241490 | C34: 商品 | D34: LENNEA原创蓝色小香风春秋新款财阀千金风气质收腰开衫毛呢外套女 | E34: 3711 | F34: 225 | G34: 39.26 | H34: 0.06063 | I34: 0.17 | J34: 10.58 | K34: 0 | L34: 0 | M34: 0 | N34: 0 | O34: 0 | P34: 0 | Q34: 0 | R34: 0 | S34: 0 | T34: 0 | U34: 0 | V34: 0 | W34: 0 | X34: 0 | Y34: 0 | AA34: 2 | AB34: 1 | AC34: 1 | AD34: 0.00889 | AE34: 0 | AF34: 0 | AH34: 2 | AI34: 19.63 | AJ34: 2 | AK34: 19.63 | AL34: 0 | AN34: 0 | AO34: 19.63 | AP34: 0 | AQ34: 0 | AR34: 0 | AS34: 0 | AT34: 0 | AU34: 0 | AV34: 0 | AW34: 0 | AX34: 402 | AY34: 222 | AZ34: 173 | BA34: 0.77928 | BB34: 0 | BC34: 0 | BD34: 0.10833 | BE34: 171 | BF34: 2 | BG34: 0 | BI34: 0 | BJ34: 0 | BK34: 0 | BL34: 0 | BO34: 0 | BP34: 0 | BQ34: 0 | BR34: 0 | BS34: 0 | BT34: 0
A35: 46104 | B35: 858672318475 | C35: 商品 | D35: LENNEA蝴蝶结格子拼接设计感宽松直筒拖地高腰牛仔裤女显瘦长裤 | E35: 42 | F35: 5 | G35: 4.51 | H35: 0.11905 | I35: 0.9 | J35: 107.38 | K35: 0 | L35: 0 | M35: 0 | N35: 0 | O35: 0 | P35: 0 | Q35: 185 | R35: 0 | S35: 185 | T35: 1 | U35: 1 | V35: 0 | W35: 0.2 | X35: 41.02 | Y35: 41.02 | Z35: 4.51 | AA35: 2 | AB35: 1 | AC35: 1 | AD35: 0.4 | AE35: 0 | AF35: 0 | AH35: 2 | AI35: 2.26 | AJ35: 2 | AK35: 2.26 | AL35: 0 | AN35: 0 | AO35: 2.26 | AP35: 3 | AQ35: 490 | AR35: 0 | AS35: 0 | AT35: 0 | AU35: 0 | AV35: 0 | AW35: 2 | AX35: 12 | AY35: 4 | AZ35: 3 | BA35: 0.75 | BB35: 0 | BC35: 0 | BD35: 0.28571 | BE35: 7 | BF35: 3 | BG35: 1 | BH35: 1 | BI35: 0 | BJ35: 0 | BK35: 0 | BL35: 1 | BM35: 1 | BN35: 185 | BO35: 0 | BP35: 0 | BQ35: 0 | BR35: 0 | BS35: 0 | BT35: 0
A36: 46104 | B36: 811797505172 | C36: 商品 | D36: LENNEA原创设计感连帽贝壳毛衣开衫针织衫女秋季外套慵懒风上衣春 | E36: 5501 | F36: 456 | G36: 54.94 | H36: 0.08289 | I36: 0.12 | J36: 9.99 | K36: 0 | L36: 0 | M36: 0 | N36: 0 | O36: 0 | P36: 0 | Q36: 0 | R36: 0 | S36: 0 | T36: 0 | U36: 0 | V36: 0 | W36: 0 | X36: 0 | Y36: 0 | AA36: 14 | AB36: 13 | AC36: 1 | AD36: 0.0307 | AE36: 2 | AF36: 0 | AH36: 16 | AI36: 3.43 | AJ36: 16 | AK36: 3.43 | AL36: 2 | AM36: 27.47 | AN36: 0.00439 | AO36: 3.92 | AP36: 0 | AQ36: 0 | AR36: 2 | AS36: 0 | AT36: 0 | AU36: 0 | AV36: 0 | AW36: 0 | AX36: 593 | AY36: 427 | AZ36: 390 | BA36: 0.91335 | BB36: 0 | BC36: 0 | BD36: 0.1078 | BE36: 149 | BF36: 1 | BG36: 0 | BI36: 0 | BJ36: 0 | BK36: 0 | BL36: 0 | BO36: 0 | BP36: 0 | BQ36: 0 | BR36: 0 | BS36: 0 | BT36: 0
A37: 46104 | B37: 763414867633 | C37: 商品 | D37: LENNEA法式气质小香风短款外套女2025秋冬加绒显瘦高级感羽绒上衣 | E37: 8445 | F37: 511 | G37: 151.97 | H37: 0.06051 | I37: 0.3 | J37: 18 | K37: 0 | L37: 0 | M37: 0 | N37: 0 | O37: 0 | P37: 0 | Q37: 1190 | R37: 678 | S37: 1868 | T37: 9 | U37: 5 | V37: 4 | W37: 0.01761 | X37: 12.29 | Y37: 12.29 | Z37: 16.89 | AA37: 76 | AB37: 22 | AC37: 54 | AD37: 0.14873 | AE37: 13 | AF37: 5 | AG37: 30.39 | AH37: 94 | AI37: 1.62 | AJ37: 89 | AK37: 1.71 | AL37: 18 | AM37: 11.69 | AN37: 0.02544 | AO37: 2 | AP37: 10 | AQ37: 2480 | AR37: 4 | AS37: 9 | AT37: 0 | AU37: 0 | AV37: 0 | AW37: 3 | AX37: 1753 | AY37: 485 | AZ37: 406 | BA37: 0.83711 | BB37: 0 | BC37: 0 | BD37: 0.20758 | BE37: 1198 | BF37: 4 | BG37: 7 | BH37: 0.875 | BI37: 0 | BJ37: 0 | BK37: 0 | BL37: 8 | BM37: 1 | BN37: 233.5 | BO37: 0 | BP37: 0 | BQ37: 0 | BR37: 0 | BS37: 0 | BT37: 0
A38: 46104 | B38: 728037000377 | C38: 商品 | D38: LENNEA藏青色原创秋冬无领女正肩修身短款小香风学院夹克外套春季 | E38: 10928 | F38: 589 | G38: 98.86 | H38: 0.0539 | I38: 0.17 | J38: 9.05 | K38: 0 | L38: 0 | M38: 0 | N38: 0 | O38: 0 | P38: 0 | Q38: 1065 | R38: 176 | S38: 1241 | T38: 7 | U38: 6 | V38: 1 | W38: 0.01188 | X38: 12.55 | Y38: 12.55 | Z38: 14.12 | AA38: 35 | AB38: 15 | AC38: 20 | AD38: 0.05942 | AE38: 6 | AF38: 3 | AG38: 32.95 | AH38: 44 | AI38: 2.25 | AJ38: 41 | AK38: 2.41 | AL38: 9 | AM38: 16.48 | AN38: 0.01019 | AO38: 2.82 | AP38: 7 | AQ38: 1462 | AR38: 1 | AS38: 5 | AT38: 0 | AU38: 0 | AV38: 0 | AW38: 3 | AX38: 1072 | AY38: 542 | AZ38: 504 | BA38: 0.92989 | BB38: 0 | BC38: 0 | BD38: 0.0981 | BE38: 476 | BF38: 2 | BG38: 4 | BH38: 1 | BI38: 0 | BJ38: 0 | BK38: 0 | BL38: 4 | BM38: 2 | BN38: 310.25 | BO38: 0 | BP38: 0 | BQ38: 0 | BR38: 0 | BS38: 0 | BT38: 0
A39: 46104 | B39: 728030472469 | C39: 商品 | D39: LENNEA 原创秋冬女长袖通勤宽松宽松高腰学生设计条纹衬衫春 | E39: 3122 | F39: 196 | G39: 17.99 | H39: 0.06278 | I39: 0.09 | J39: 5.76 | K39: 0 | L39: 0 | M39: 0 | N39: 0 | O39: 0 | P39: 0 | Q39: 0 | R39: 0 | S39: 0 | T39: 0 | U39: 0 | V39: 0 | W39: 0 | X39: 0 | Y39: 0 | AA39: 12 | AB39: 1 | AC39: 11 | AD39: 0.06122 | AE39: 1 | AF39: 1 | AG39: 17.99 | AH39: 14 | AI39: 1.29 | AJ39: 13 | AK39: 1.38 | AL39: 2 | AM39: 17.99 | AN39: 0.0051 | AO39: 1.5 | AP39: 0 | AQ39: 0 | AR39: 0 | AS39: 1 | AT39: 0 | AU39: 0 | AV39: 0 | AW39: 0 | AX39: 374 | AY39: 186 | AZ39: 167 | BA39: 0.89785 | BB39: 0 | BC39: 0 | BD39: 0.1198 | BE39: 173 | BF39: 2 | BG39: 0 | BI39: 0 | BJ39: 0 | BK39: 0 | BL39: 0 | BO39: 0 | BP39: 0 | BQ39: 0 | BR39: 0 | BS39: 0 | BT39: 0

Sheet 站外结款表
A1: 月份 | B1: 日期 | C1: 大类 | D1: 项目 | E1: 款式编码（这个要对应商品成本表的编码 然后是通过审核之后直接自动跳出来） | F1: 款式 | G1: 金额 | H1: 寄/送 | I1: 博主名 | J1: 付款金额 | K1: 付款日期 | L1: 衣服成本（抓取对应的商品成本表的） | M1: 总成本（衣服成本加佣金成本） | N1: 付款图片 | O1: 备注
A2: 1月 | B2: 46026 | C2: 站外推广 | D2: 佣金 | F2: 波点棉服 | G2: 1100 | H2: 送 | I2: 小红书：笑榕船长 | J2: 1100 | K2: 46032 | M2: #VALUE!
A3: 1月 | B3: 46026 | C3: 站外推广 | D3: 佣金 | F3: 蝴蝶结条纹棉服 | G3: 400 | H3: 送 | I3: 小红书：小v（宫） | J3: 补发合集前三 | M3: 0
A4: 1月 | B4: 46026 | C4: 站外推广 | D4: 佣金 | F4: 系带麂皮外套 | G4: 100 | H4: 送 | I4: 小红书：黎梓辛 | J4: 100 | K4: 46032 | M4: #VALUE!
A5: 1月 | B5: 46026 | C5: 站外推广 | D5: 佣金 | F5: 大翻领皮草（卡其） | G5: 600 | H5: 送 | I5: 小红书：徐大囍Nancy | J5: 600 | K5: 46032 | M5: #VALUE!
A6: 1月 | B6: 46026 | C6: 站外推广 | D6: 佣金 | F6: 粉色毛领大衣 | G6: 180 | H6: 送 | I6: 小红书：团子不是圆圆的 | J6: 180 | K6: 46032 | M6: #VALUE!
A7: 1月 | B7: 46026 | C7: 站外推广 | D7: 佣金 | F7: 花苞羽绒服 | G7: 600 | H7: 送 | I7: 小红书：鱼鱼很乖 | J7: 600 | K7: 46032 | M7: #VALUE!
A8: 1月 | B8: 46026 | C8: 站外推广 | D8: 佣金 | F8: 条纹羊羔毛 | G8: 200 | H8: 送 | I8: 小红书：姜姜好困 | J8: 200 | K8: 46032 | M8: #VALUE!
A9: 1月 | B9: 46026 | C9: 站外推广 | D9: 佣金 | F9: 双排扣外套 | G9: 100 | H9: 送 | I9: 小红书：张芽芽 | J9: 100 | K9: 46032 | M9: #VALUE!
A10: 1月 | B10: 46026 | C10: 站外推广 | D10: 佣金 | F10: 系带麂皮外套 | G10: 710 | H10: 送 | I10: 小红书：都没有李甜 | J10: 710 | K10: 46032 | M10: #VALUE!
A11: 1月 | B11: 46026 | C11: 站外推广 | D11: 佣金 | F11: 双排扣外套 | G11: 800 | H11: 送 | I11: 小红书：啊喔开饭没 | J11: 800 | K11: 46032 | M11: #VALUE!
A12: 1月 | B12: 46026 | C12: 站外推广 | D12: 佣金 | F12: 木耳边棉服 | G12: 80 | H12: 送 | I12: 小红书：酱子西子 | J12: 80 | K12: 46032 | M12: #VALUE!
A13: 1月 | B13: 46026 | C13: 站外推广 | D13: 佣金 | F13: 大翻领皮草（卡其） | G13: 100 | H13: 已寄回 | I13: 小红书：涵涵爱拍照 | J13: 50 | K13: 46032 | M13: 100
A14: 1月 | B14: 46026 | C14: 站外推广 | D14: 佣金 | F14: 菲奥娜棉服 | G14: 250 | H14: 送 | I14: 小红书：奇妙小0 | J14: 补发 | M14: 0
A15: 1月 | B15: 46026 | C15: 站外推广 | D15: 佣金 | F15: 毛领棉服（蓝） | G15: 260 | H15: 送 | I15: 小红书：162的糕糕 | J15: 260 | K15: 46032 | M15: #VALUE!
A16: 1月 | B16: 46026 | C16: 站外推广 | D16: 佣金 | F16: 大翻领皮草（卡其） | G16: 730 | H16: 送 | I16: 抖音：我想吃西柚 | J16: 730 | K16: 46032 | M16: #VALUE!
A17: 1月 | B17: 46026 | C17: 站外推广 | D17: 佣金 | F17: 粉色毛领大衣 | G17: 300 | H17: 送 | I17: 小红书：莫娣 | J17: 300 | K17: 46032 | M17: #VALUE!
A18: 1月 | B18: 46026 | C18: 站外推广 | D18: 佣金 | F18: 双排扣外套 | G18: 300 | H18: 送 | I18: 小红书：好好酱 | J18: 300 | K18: 46032 | M18: #VALUE!
A19: 1月 | B19: 46026 | C19: 站外推广 | D19: 佣金 | F19: 收腰羽绒服 | G19: 550 | H19: 送 | I19: 小红书：柏含. | J19: 550 | K19: 46032 | M19: #VALUE!
A20: 1月 | B20: 46026 | C20: 站外推广 | D20: 佣金 | F20: 双排扣外套 | G20: 250 | H20: 已寄回 | I20: 小红书：被小帅骗走250万 | J20: 二维码失效 | M20: 250
A21: 1月 | B21: 46026 | C21: 站外推广 | D21: 佣金 | F21: 毛领棉服 | G21: 180 | H21: 送 | I21: 小红书：两个圈 | J21: 180 | K21: 46032 | M21: 180
A22: 1月 | B22: 46026 | C22: 站外推广 | D22: 佣金 | F22: 波点棉服 | G22: 900 | H22: 送 | I22: 小红书：一只鲸 | J22: 900 | K22: 46032 | M22: 900
A23: 1月 | B23: 46026 | C23: 站外推广 | D23: 佣金 | F23: 棕色大衣 | G23: 80 | H23: 已寄回 | I23: 小红书：罗汉果ii | J23: 80 | K23: 46032 | M23: 80
A24: 1月 | B24: 46026 | C24: 站外推广 | D24: 佣金 | F24: 棕色大衣（米色） | G24: 250 | H24: 送 | I24: 小红书：153的多多 | J24: 250 | K24: 46033 | M24: 250
A25: 1月 | B25: 46026 | C25: 站外推广 | D25: 佣金 | F25: 木耳边棉服 | G25: 180 | H25: 送 | I25: 小红书：冻冻荔 | J25: 补发 | M25: 0
A26: 1月 | B26: 46026 | C26: 站外推广 | D26: 佣金 | F26: 木耳边棉服 | G26: 100 | H26: 爆文奖励 | I26: 小红书：小椿 | J26: 100 | K26: 46032 | M26: 100
A27: 1月 | B27: 46026 | C27: 站外推广 | D27: 佣金 | F27: 棕色大衣 | G27: 300 | H27: 送 | I27: 小红书：Hikoy | J27: 300 | K27: 46033 | M27: 300
A28: 1月 | B28: 46026 | C28: 站外推广 | D28: 佣金 | F28: 棕色大衣 | G28: 500 | H28: 送 | I28: 小红书：子川木 | J28: 500 | K28: 46033 | M28: 500
A29: 1月 | B29: 46026 | C29: 站外推广 | D29: 佣金 | F29: 波点棉服 | G29: 90 | H29: 送 | I29: 小红书：睡够12h | J29: 90 | K29: 46032 | M29: 90
A30: 1月 | B30: 46026 | C30: 站外推广 | D30: 佣金 | F30: 粉色毛领大衣 | G30: 150 | H30: 已寄回 | I30: 小红书：一只小羊羔 | J30: 150 | K30: 46032 | M30: 150
A31: 1月 | B31: 46026 | C31: 站外推广 | D31: 佣金 | F31: 贝壳毛衣 | G31: 200 | H31: 送 | I31: 小红书：木头怪兽 | J31: 200 | K31: 46033 | M31: 200
A32: 1月 | B32: 46026 | C32: 站外推广 | D32: 佣金 | F32: 羊绒圈小香风 | G32: 60 | H32: 已寄回 | I32: 小红书：一只雪 | J32: 120 | K32: 46033 | M32: 60
A33: 1月 | B33: 46026 | C33: 站外推广 | D33: 佣金 | F33: 棕色大衣 | G33: 60 | H33: 已寄回 | I33: 小红书：一只雪 | M33: 60
A34: 1月 | B34: 46026 | C34: 站外推广 | D34: 佣金 | F34: 毛领棉服（蓝） | G34: 300 | H34: 送 | I34: 小红书：小羊没烦恼 | J34: 300 | K34: 46032 | M34: 300
A35: 1月 | B35: 46026 | C35: 站外推广 | D35: 佣金 | F35: 花苞羽绒服 | G35: 300 | H35: 送 | I35: 小红书：刘梦梦 | J35: 300 | K35: 46032 | M35: 300
A36: 1月 | B36: 46026 | C36: 站外推广 | D36: 佣金 | F36: 粉色毛领大衣 | G36: 100 | H36: 已寄回 | I36: 小红书：祝泥泥 | J36: 100 | K36: 46032 | M36: 100
A37: 1月 | B37: 46026 | C37: 站外推广 | D37: 佣金 | F37: 波点棉服 | G37: 100 | H37: 已寄回 | I37: 小红书：祝泥泥 | J37: 100 | K37: 46033 | M37: 100
A38: 1月 | B38: 46026 | C38: 站外推广 | D38: 佣金 | F38: 粉色毛领大衣 | G38: 400 | H38: 送 | I38: 小红书：纯情小绵羊 | J38: 400 | K38: 46033 | M38: 400
A39: 1月 | B39: 46026 | C39: 站外推广 | D39: 佣金 | F39: 双排扣外套 | G39: 600 | H39: 送 | I39: 小红书：小绿小绿 | J39: 600 | K39: 46033 | M39: 600
A40: 1月 | B40: 46026 | C40: 站外推广 | D40: 佣金 | F40: 波点棉服 | G40: 260 | H40: 送 | I40: 小红书：别烦凡凡 | J40: 260 | K40: 46033 | M40: 260
A41: 1月 | B41: 46026 | C41: 站外推广 | D41: 佣金 | F41: 双排扣外套 | G41: 320 | H41: 送 | I41: 小红书：耙耙柑 | J41: 320 | K41: 46033 | M41: 320
A42: 1月 | B42: 46026 | C42: 站外推广 | D42: 佣金 | F42: 大翻领皮草（米白） | G42: 45 | H42: 寄 | I42: 小红书：芽芽 | J42: 45 | K42: 46033 | M42: 45
A43: 1月 | B43: 46026 | C43: 站外推广 | D43: 佣金 | F43: 菲奥娜棉服 | G43: 130 | H43: 寄 | I43: 小红书：不说 | J43: 130 | K43: 46033 | M43: 130
A44: 1月 | B44: 46026 | C44: 站外推广 | D44: 佣金 | F44: 毛领棉服（蓝） | G44: 350 | H44: 送 | I44: 小红书：小小肥_ | J44: 350 | K44: 46033 | M44: 350
A45: 1月 | B45: 46026 | C45: 站外推广 | D45: 佣金 | F45: 收腰羽绒服 | G45: 350 | H45: 送 | I45: 小红书：小王在这er_ | J45: 350 | K45: 46043 | M45: 350
A46: 1月 | B46: 46026 | C46: 站外推广 | D46: 佣金 | F46: 棕色大衣 | G46: 150 | H46: 送 | I46: 小红书：lulu | J46: 150 | K46: 46033 | M46: 150
A47: 1月 | B47: 46026 | C47: 站外推广 | D47: 佣金 | F47: 毛领棉服（蓝） | G47: 150 | H47: 送 | I47: 小红书：lulu | J47: 问问补发或者结半 | M47: 0
A48: 1月 | B48: 46026 | C48: 站外推广 | D48: 佣金 | F48: 粉色毛领大衣 | G48: 300 | H48: 送 | I48: 小红书：开心绪 | J48: 300 | K48: 46034 | M48: 300
A49: 1月 | B49: 46026 | C49: 站外推广 | D49: 佣金 | F49: 双排扣外套 | G49: 150 | H49: 送 | I49: 小红书：九九158 | J49: 已结 | M49: 0
A50: 1月 | B50: 46026 | C50: 站外推广 | D50: 佣金 | F50: 冰蓝卫衣外套 | G50: 200 | H50: 送 | I50: 小红书：圆圆不呆噜 | J50: 200 | K50: 46033 | M50: 200
A51: 1月 | B51: 46026 | C51: 站外推广 | D51: 佣金 | F51: 羊绒圈小香风 | G51: 170 | H51: 已寄回 | I51: 小红书：一只小羊羔 | J51: 170 | K51: 46034 | M51: 170
A52: 1月 | B52: 46026 | C52: 站外推广 | D52: 佣金 | F52: 粉色毛领大衣 | G52: 150 | H52: 送 | I52: 小红书：动森的河马 | J52: 150 | K52: 46033 | M52: 150
A53: 1月 | B53: 46026 | C53: 站外推广 | D53: 佣金 | F53: 粉色毛领大衣 | G53: 60 | H53: 送 | I53: 小红书：甜甜不困咯 | J53: 60 | K53: 46033 | M53: 60
A54: 1月 | B54: 46026 | C54: 站外推广 | D54: 佣金 | F54: 波点棉服 | G54: 180 | H54: 已寄回 | I54: 小红书：一米六 | J54: 180 | K54: 46033 | M54: 180
A55: 1月 | B55: 46026 | C55: 站外推广 | D55: 佣金 | F55: 菲奥娜棉服 | G55: 100 | H55: 送 | I55: 小红书：羊美女 | J55: 100 | K55: 46033 | M55: 100
A56: 1月 | B56: 46026 | C56: 站外推广 | D56: 佣金 | F56: 粉色毛领大衣 | G56: 100 | H56: 送 | I56: 小红书：面包面包 | J56: 100 | K56: 46033 | M56: 100
A57: 1月 | B57: 46026 | C57: 站外推广 | D57: 佣金 | F57: 棕色大衣 | G57: 100 | H57: 送 | I57: 小红书：一支树懒 | J57: 100 | K57: 46033 | M57: 100
A58: 1月 | B58: 46026 | C58: 站外推广 | D58: 佣金 | F58: 粉色毛领大衣 | G58: 1800 | H58: 送 | I58: 小红书：肥猪靖仔子 | J58: 1800 | K58: 46034 | M58: 1800
A59: 1月 | B59: 46026 | C59: 站外推广 | D59: 佣金 | F59: 粉色毛领大衣 | G59: 260 | H59: 送 | I59: 小红书：荔枝小馨 | J59: 130 | K59: 46033 | M59: 130
A60: 1月 | B60: 46026 | C60: 站外推广 | D60: 佣金 | F60: 波点棉服 | G60: 40 | H60: 送 | I60: 小红书：咕噜噜 | J60: 40 | K60: 46033 | M60: 40
A61: 1月 | B61: 46026 | C61: 站外推广 | D61: 佣金 | F61: 菲奥娜棉服 | G61: 220 | H61: 送 | I61: 小红书：圆圆不呆噜 | J61: 220 | K61: 46033 | M61: 220
... A83: 1月 | B83: 46027 | C83: 站外推广 | D83: 佣金 | F83: 粉色毛领大衣 | G83: 125 | H83: 送 | I83: 小红书：绮妹妹耶 | J83: 125 | K83: 46034 | M83: 125
A84: 1月 | B84: 46027 | C84: 站外推广 | D84: 佣金 | F84: 双排扣外套 | G84: 230 | H84: 送 | I84: 小红书：轮到我发财啦 | J84: 账户问题 | K84: 46034 | M84: 0
A85: 1月 | B85: 46027 | C85: 站外推广 | D85: 佣金 | F85: 毛领棉服（蓝） | G85: 1200 | H85: 送 | I85: 小红书：七斤七斤 | J85: 1200 | K85: 46034 | M85: 1200
A86: 1月 | B86: 46027 | C86: 站外推广 | D86: 佣金 | F86: 蓝色毛领大衣 | G86: 300 | H86: 已寄回 | I86: 抖音：发际线1米7 | J86: 300 | K86: 46034 | M86: 300
A87: 1月 | B87: 46027 | C87: 站外推广 | D87: 佣金 | F87: 双排扣外套 | G87: 300 | H87: 已寄回 | I87: 抖音：空大姐姐 | J87: 300 | K87: 46034 | M87: 300
A88: 1月 | B88: 46027 | C88: 站外推广 | D88: 佣金 | F88: 大翻领皮草（卡其） | G88: 200 | H88: 已寄回 | I88: 小红书：爱吃麦辣鸡翅 | J88: 200 | K88: 46034 | M88: 200
A89: 1月 | B89: 46027 | C89: 站外推广 | D89: 佣金 | F89: 收腰羽绒服 | G89: 300 | H89: 送 | I89: 小红书：周周不烦恼 | J89: 300 | K89: 46034 | M89: 300
A90: 1月 | B90: 46027 | C90: 站外推广 | D90: 佣金 | F90: 棕色大衣 | G90: 200 | H90: 送 | I90: 小红书：支葵 | J90: 200 | K90: 46034 | M90: 200
A91: 1月 | B91: 46027 | C91: 站外推广 | D91: 佣金 | F91: 大翻领皮草（卡其） | G91: 150 | H91: 送 | I91: 小红书：凌十七 | J91: 补发 | M91: 0
A92: 1月 | B92: 46027 | C92: 站外推广 | D92: 佣金 | F92: 粉色毛领大衣 | G92: 1300 | H92: 送 | I92: 小红书：MongMong | J92: 1300 | K92: 46035 | M92: 1300
A93: 1月 | B93: 46027 | C93: 站外推广 | D93: 佣金 | F93: 收腰羽绒服 | G93: 500 | H93: 送 | I93: 小红书：猫猫比芭 | J93: 500 | K93: 46035 | M93: 500
A94: 1月 | B94: 46027 | C94: 站外推广 | D94: 佣金 | F94: 棕色大衣 | G94: 80 | H94: 送 | I94: 小红书：丫丫 | M94: 0
A95: 1月 | B95: 46027 | C95: 站外推广 | D95: 佣金 | F95: 粉色毛领大衣 | G95: 300 | H95: 送 | I95: 小红书：羊羊 | J95: 300 | K95: 46035 | M95: 300
A96: 1月 | B96: 46027 | C96: 站外推广 | D96: 佣金 | F96: 毛领棉服 | G96: 300 | H96: 送 | I96: 小红书：一粒小栗子 | J96: 300 | K96: 46035 | M96: 300
A97: 1月 | B97: 46027 | C97: 站外推广 | D97: 佣金 | F97: 棕色大衣 | G97: 150 | H97: 送 | I97: 小红书：小熊会倒立 | J97: 150 | K97: 46035 | M97: 150
A98: 1月 | B98: 46027 | C98: 站外推广 | D98: 佣金 | F98: 基础棉服（白） | G98: 150 | H98: 送 | I98: 小红书：小熊会倒立 | J98: 100 | K98: 46035 | M98: 100
A99: 1月 | B99: 46027 | C99: 站外推广 | D99: 佣金 | F99: 粉色毛领大衣 | G99: 250 | H99: 送 | I99: 小红书：奇妙小0 | J99: 250 | K99: 46035 | M99: 250
A100: 1月 | B100: 46027 | C100: 站外推广 | D100: 佣金 | F100: 基础棉服（白） | G100: 300 | H100: 送 | I100: 小红书：满分芝士 | J100: 300 | K100: 46035 | M100: 300
A101: 1月 | B101: 46027 | C101: 站外推广 | D101: 佣金 | F101: 粉色毛领大衣 | G101: 200 | H101: 送 | I101: 小红书：诀别诗 | J101: 200 | K101: 46035 | M101: 200
A102: 1月 | B102: 46027 | C102: 站外推广 | D102: 佣金 | F102: 小香风皮草 | G102: 1200 | H102: 送 | I102: 小红书：一麻袋橙子 | J102: 1200 | K102: 46035 | M102: 1200
A103: 1月 | B103: 46027 | C103: 站外推广 | D103: 佣金 | F103: 小香风皮草 | G103: 600 | H103: 送 | I103: 小红书：阔洛 | J103: 600 | K103: 46035 | M103: 600
A104: 1月 | B104: 46027 | C104: 站外推广 | D104: 佣金 | F104: 毛领棉服（蓝） | G104: 100 | H104: 送 | I104: 小红书：饭饭 | J104: 100 | K104: 46035 | M104: 100
A105: 1月 | B105: 46027 | C105: 站外推广 | D105: 佣金 | F105: 收腰羽绒服 | G105: 600 | H105: 送 | I105: 小红书：桃桃桃不掉呀 | J105: 600 | K105: 46035 | M105: 600
A106: 1月 | B106: 46027 | C106: 站外推广 | D106: 佣金 | F106: 毛领棉服（蓝） | G106: 666 | H106: 送 | I106: 小红书：大壳儿🦀 | J106: 666 | K106: 46035 | M106: 666
... A121: 1月 | B121: 46028 | C121: 站外推广 | D121: 佣金 | F121: 毛领棉服（蓝） | G121: 100 | H121: 已寄回 | I121: 小红书：涵涵爱拍照 | J121: 50 | K121: 46035 | M121: 100
A122: 1月 | B122: 46028 | C122: 站外推广 | D122: 佣金 | F122: 大翻领皮草（米白） | G122: 350 | H122: 送 | I122: 小红书：别烦凡凡 | M122: 0
A123: 1月 | B123: 46028 | C123: 站外推广 | D123: 佣金 | F123: 棕色毛呢外套 | G123: 300 | H123: 送 | I123: 小红书：一颗妹 | J123: 300 | K123: 46035 | M123: 300
A124: 1月 | B124: 46028 | C124: 站外推广 | D124: 佣金 | F124: 棕色大衣 | G124: 100 | H124: 送 | I124: 小红书：serendipity | M124: 0
A125: 1月 | B125: 46028 | C125: 站外推广 | D125: 佣金 | F125: 收腰羽绒服 | G125: 230 | H125: 送 | I125: 小红书：青柑普洱 | J125: 115 | K125: 46035 | M125: 115
A126: 1月 | B126: 46028 | C126: 站外推广 | D126: 佣金 | F126: 粉色毛领大衣 | G126: 150 | H126: 送 | I126: 小红书：冻冻荔 | M126: 0
A127: 1月 | B127: 46028 | C127: 站外推广 | D127: 佣金 | F127: 毛领棉服（蓝） | G127: 230 | H127: 送 | I127: 小红书：今天吃什么 | J127: 230 | K127: 46035 | M127: 230
A128: 1月 | B128: 46028 | C128: 站外推广 | D128: 佣金 | F128: 粉色毛领大衣 | G128: 230 | H128: 送 | I128: 小红书：今天吃什么 | J128: 230 | K128: 46035 | M128: 230
A129: 1月 | B129: 46028 | C129: 站外推广 | D129: 佣金 | F129: 粉色毛领大衣 | G129: 100 | H129: 送 | I129: 小红书：帆帆大眼妹 | J129: 50 | K129: 46035 | M129: 50
A130: 1月 | B130: 46028 | C130: 站外推广 | D130: 佣金 | F130: 粉色毛领大衣 | G130: 650 | H130: 送 | I130: 小红书：蜡 | J130: 650 | K130: 46035 | M130: 650
A131: 1月 | B131: 46028 | C131: 站外推广 | D131: 佣金 | F131: 花苞羽绒服 | G131: 150 | H131: 已寄回 | I131: 小红书：甜甜 | J131: 150 | K131: 46035 | M131: 150
A132: 1月 | B132: 46028 | C132: 站外推广 | D132: 佣金 | F132: 花苞羽绒服 | G132: 350 | H132: 送 | I132: 小红书：酉月十四白 | J132: 350 | K132: 46035 | M132: 350
A133: 1月 | B133: 46028 | C133: 站外推广 | D133: 佣金 | F133: 收腰羽绒服 | G133: 80 | H133: 已寄回 | I133: 小红书：哦椰🥥 | J133: 80 | K133: 46035 | M133: 80
A134: 1月 | B134: 46028 | C134: 站外推广 | D134: 佣金 | F134: 粉色毛领大衣 | G134: 150 | H134: 送 | I134: 小红书：九九鸭～ | J134: 300 | K134: 46037 | M134: 300
A135: 1月 | B135: 46028 | C135: 站外推广 | D135: 佣金 | F135: 大翻领皮草（卡其） | G135: 150 | H135: 送 | I135: 小红书：九九鸭～ | M135: 0
...

Sheet 站外推广表
A1: 重复后是否双平台 | B1: 检查是否重复 | C1: 负责PR | D1: 品名 | E1: 货号 | F1: 打单地址 | G1: 发货单号 | H1: 发货时间（填了发货单号的时间） | I1: 合作平台 | J1: 报价 | K1: 博主id | L1: 合作日期 | M1: 送达时间（发货时间+3天） | N1: 预定发布日期 | O1: 线上填订单号，线下填线下 | P1: 素人<1W粉丝KOC<10W粉丝KOL>10W粉丝 | Q1: 微信 | R1: 是否催发 自动生成 | S1: 是否召回 | T1: 寄回单号 | U1: 合作方式 | V1: 合作形式 | W1: 是否发布 | X1: 发布日期 | Y1: 发布链接 | Z1: 点赞量（发布7天后统计） | AA1: 收藏数 | AB1: 评论数 | AC1: 爆文（点赞过千） | AD1: 博主风格 | AE1: 买家秀发布（截图） | AF1: 是否报价过千 | AG1: 约篇月份 | AH1: 合作月份 | AI1: 发布剩余时间 | AJ1: 总成本 | AK1: 颜色 | AL1: 去重后点赞量 | AM1: 去重后实际点赞量（抖音➗️10） | AN1: 收藏赞比 | AO1: 单件点赞成本
C2: 阿咩 | D2: 飘带挂脖上衣 | E2: 2025320 | F2: 尺码：s 收件人: 陈虹羽 手机号码: 13307502767 所在地区: 海南省海口市美兰区海甸街道 详细地址: 中大公寓 | G2: YT7613967120582 | I2: 小红书 | J2: 80 | K2: #NAME? | L2: 46086 | N2: 46122 | P2: KOC | Q2: free-tu00 | R2: 超时 | U2: 送拍 | V2: 单篇 | W2: 未发布 | AC2: 否 | AF2: 否 | AI2: 超时 | AJ2: 125 | AL2: 0 | AN2: 0 | AO2: 0
C3: HE | D3: 斜门襟衬衫 | E3: 2026001 | I3: 小红书 | J3: 160 | K3: 左耳 | L3: 46084 | N3: 46132 | P3: 素人 | Q3: JIANGLT027 | R3: 已发布 | S3: 召回成功 | T3: 435124468134001 | U3: 寄拍 | V3: 单篇 | W3: 已发布 | X3: 46126 | Y3: https://www.xiaohongshu.com/discovery/item/69d9e40c000000001f000eb8?source=webshare&xhsshare=pc_web&xsec_token=CBY9JIjTrfeerO7FXYzvE_MpcVTNih1dd9q0wDXFFH1MQ=&xsec_source=pc_share | Z3: 30 | AA3: 11 | AB3: 6 | AC3: 否 | AF3: 否 | AI3: 已发布 | AJ3: 205 | AL3: 30 | AM3: 30 | AN3: 0.36666667 | AO3: 6.8333333
B4: 重复 | C4: 果片 | D4: 荷叶边沙滩裙 | E4: 2025322 | F4: 尺码：m 地址：安徽省合肥市庐阳区四里河畔小区D区（东苑）小王18225865706 | G4: YT7609046121616 | I4: 小红书 | J4: 150 | K4: 最后一只恐龙🦕 | L4: 46095 | N4: 46142 | P4: 素人 | Q4: Outs1dersXx | R4: 档期内 | U4: 送拍 | V4: 单篇 | W4: 未发布 | AC4: 否 | AF4: 否 | AI4: 12 | AJ4: 240 | AL4: 0 | AN4: 0 | AO4: 0
B5: 重复 | C5: 果片 | D5: 荷叶边沙滩上衣 | E5: 2025322 | F5: 尺码：m 地址：安徽省合肥市庐阳区四里河畔小区D区（东苑）小王18225865706 | G5: YT7609046121616 | I5: 小红书 | J5: 150 | K5: 最后一只恐龙🦕 | L5: 46095 | N5: 46142 | P5: 素人 | Q5: Outs1dersXx | R5: 档期内 | U5: 送拍 | V5: 单篇 | W5: 未发布 | AC5: 否 | AF5: 否 | AI5: 12 | AJ5: 240 | AL5: 0 | AN5: 0 | AO5: 0
C6: 一号 | D6: 飘带挂脖上衣 | E6: 2025320 | F6: 尺码：s 王一 15631415107 河北省邯郸市肥乡区肥乡镇广安路西97号自然资源和规划局 | G6: 已登记 | I6: 小红书 | J6: 110 | K6: 卓子 | L6: 46087 | N6: 46132 | P6: 素人 | Q6: grey5107 | R6: 重要催发 | U6: 送拍 | V6: 单篇 | W6: 未发布 | AC6: 否 | AF6: 否 | AI6: 2 | AJ6: 155 | AL6: 0 | AN6: 0 | AO6: 0
C7: 一号 | D7: 牛仔短裙 | E7: 2026014 | F7: 尺码：s 王一 15631415107 河北省邯郸市肥乡区肥乡镇广安路西97号自然资源和规划局 | G7: 已登记 | I7: 小红书 | J7: 0 | K7: 卓子 | L7: 46087 | N7: 46132 | P7: 素人 | Q7: grey5107 | R7: 重要催发 | U7: 送拍 | V7: 单篇 | W7: 未发布 | AC7: 否 | AF7: 否 | AI7: 2 | AJ7: 45 | AL7: 0 | AN7: 0 | AO7: 0
C8: 一号 | D8: 斜门襟衬衫 | E8: 2026001 | F8: 尺码：s 王一 15631415107 河北省邯郸市肥乡区肥乡镇广安路西97号自然资源和规划局 | G8: YT7609478404279 | I8: 小红书 | J8: 110 | K8: 卓子 | L8: 46087 | N8: 46122 | P8: 素人 | Q8: grey5107 | R8: 已发布 | U8: 送拍 | V8: 单篇 | W8: 已发布 | X8: 46119 | Y8: https://www.xiaohongshu.com/explore/69d52323000000001f0052d7?xsec_token=ABc40NZd4VQaEG2duM-PVO79YNIEAE8jj_Jutj6-vap5M=&xsec_source=pc_search&source=web_search_result_notes | Z8: 53 | AA8: 8 | AB8: 10 | AC8: 否 | AF8: 否 | AI8: 已发布 | AJ8: 155 | AL8: 53 | AM8: 53 | AN8: 0.1509434 | AO8: 2.9245283
C9: 一号 | D9: 横条小白裙 | E9: 2025339 | F9: 尺码：s 王一 15631415107 河北省邯郸市肥乡区肥乡镇广安路西97号自然资源和规划局 | I9: 小红书 | J9: 0 | K9: 卓子 | L9: 46087 | N9: 46122 | P9: 素人 | Q9: grey5107 | R9: 已发布 | U9: 送拍 | V9: 单篇 | W9: 已发布 | X9: 46119 | Y9: https://www.xiaohongshu.com/explore/69d52323000000001f0052d7?xsec_token=ABc40NZd4VQaEG2duM-PVO79YNIEAE8jj_Jutj6-vap5M=&xsec_source=pc_search&source=web_search_result_notes | Z9: 53 | AA9: 8 | AB9: 10 | AC9: 否 | AF9: 否 | AI9: 已发布 | AJ9: 58 | AN9: 0.1509434 | AO9: 0
C10: 阿咩 | D10: 波点花边长袖 | E10: 2025933 | I10: 小红书 | J10: 500 | K10: 卓舒茵 | L10: 46050 | N10: 46091 | P10: KOC | Q10: HiY1131 | R10: 已发布 | U10: 送拍 | V10: 单篇 | W10: 已发布 | X10: 46110 | Y10: https://www.xiaohongshu.com/explore/69c915f5000000001a024138?app_platform=ios&app_version=9.23&share_from_user_hidden=true&xsec_source=app_share&type=video&xsec_token=CBVX2PpH8cKcyRMG8e2c20elchmmSJQeFpOCpysJvOK-g=&author_share=1&xhsshare=CopyLink&shareRedId=ODY7RTg5Nzk2NzUyOTgwNjY0OThJNTtN&apptime=1774828517&share_id=55f5f97f4d1e4f94bd7fe9d79e189e68&wechatWid=197de0b9528d9f3a75eac472a6e2009c&wechatOrigin=menu | AC10: 否 | AF10: 否 | AI10: 已发布 | AJ10: 550 | AL10: 0 | AM10: 0 | AN10: 0 | AO10: 0
C11: 阿咩 | D11: 波点中裙 | E11: 2025329 | I11: 小红书 | J11: 0 | K11: 卓舒茵 | L11: 46050 | N11: 46091 | P11: KOC | Q11: HiY1131 | R11: 已发布 | U11: 送拍 | V11: 单篇 | W11: 已发布 | X11: 46110 | Y11: https://www.xiaohongshu.com/explore/69c915f5000000001a024138?app_platform=ios&app_version=9.23&share_from_user_hidden=true&xsec_source=app_share&type=video&xsec_token=CBVX2PpH8cKcyRMG8e2c20elchmmSJQeFpOCpysJvOK-g=&author_share=1&xhsshare=CopyLink&shareRedId=ODY7RTg5Nzk2NzUyOTgwNjY0OThJNTtN&apptime=1774828517&share_id=55f5f97f4d1e4f94bd7fe9d79e189e68&wechatWid=197de0b9528d9f3a75eac472a6e2009c&wechatOrigin=menu | AC11: 否 | AF11: 否 | AI11: 已发布 | AJ11: 52 | AN11: 0 | AO11: 0
C12: 阿咩 | D12: 藏青色小香风 | E12: 2023010 | I12: 小红书 | J12: 500 | K12: 卓舒茵 | L12: 46050 | N12: 46091 | P12: KOC | Q12: HiY1131 | R12: 超时 | U12: 送拍 | V12: 单篇 | W12: 未发布 | AC12: 否 | AF12: 否 | AI12: 超时 | AJ12: 585 | AL12: 0 | AN12: 0 | AO12: 0
C13: 阿咩 | D13: 复古泡泡袖套装 | E13: 2026059 2026060 | F13: 尺码：S kcliy 广东省广州市番禺区植村南约大街12号 17841899420 | G13: YT7614032157416 | I13: 小红书 | J13: 100 | K13: 卓惠玲漂亮吗 | L13: 46092 | N13: 46142 | P13: KOC | Q13: whdtjcxz | R13: 档期内 | U13: 送拍 | V13: 单篇 | W13: 未发布 | AC13: 否 | AF13: 否 | AI13: 12 | AJ13: 100 | AL13: 0 | AN13: 0 | AO13: 0
B14: 重复 | C14: 一号 | D14: 波点花边短袖 | E14: 2025317 | F14: 尺码：s 图图 13998873715广东省广州市云埔街道龙湖云峰原著1栋3802 | G14: YT7612472372916 | I14: 小红书 | J14: 1400 | K14: 卓别图 | L14: 46112 | N14: 46157 | P14: KOC | Q14: MovF-0119 | R14: 档期内 | U14: 送拍 | V14: 单篇 | W14: 未发布 | AC14: 否 | AF14: 是 | AI14: 27 | AJ14: 1450 | AL14: 0 | AN14: 0 | AO14: 0
B15: 重复 | C15: 一号 | D15: 波点中裙 | E15: 2025329 | F15: 尺码：s 图图 13998873715广东省广州市云埔街道龙湖云峰原著1栋3802 | G15: 已登记 | I15: 小红书 | J15: 0 | K15: 卓别图 | L15: 46112 | N15: 46157 | P15: KOC | Q15: MovF-0119 | R15: 档期内 | U15: 送拍 | V15: 单篇 | W15: 未发布 | AC15: 否 | AF15: 否 | AI15: 27 | AJ15: 52 | AL15: 0 | AN15: 0 | AO15: 0
A16: 双平台 | B16: 重复 | C16: 一号 | D16: 波点花边短袖 | E16: 2025317 | I16: 抖音 | J16: 0 | K16: 卓别图 | L16: 46112 | N16: 46157 | P16: KOL | Q16: MovF-0119 | R16: 档期内 | U16: 送拍 | V16: 单篇 | W16: 未发布 | AC16: 否 | AF16: 否 | AI16: 27 | AJ16: 50 | AL16: 0 | AN16: 0 | AO16: 0
B17: 重复 | C17: 一号 | D17: 波点中裙 | E17: 2025329 | I17: 抖音 | J17: 0 | K17: 卓别图 | L17: 46112 | N17: 46157 | P17: KOL | Q17: MovF-0119 | R17: 档期内 | U17: 送拍 | V17: 单篇 | W17: 未发布 | AC17: 否 | AF17: 否 | AI17: 27 | AJ17: 52 | AL17: 0 | AN17: 0 | AO17: 0
B18: 重复 | C18: 阿咩 | D18: 无袖花苞长裙（黄） | E18: 2025945 | F18: 尺码：S 姓名：小超人 电话：13672395588 地址：广东省广州市番禺区广州中医药大学大学城校区生活区 | G18: YT7607895562350 | I18: 小红书 | J18: 500 | K18: 赘肉掉了一地 | L18: 46090 | N18: 46132 | P18: KOC | Q18: Zrdlydx | R18: 已发布 | U18: 送拍 | V18: 单篇 | W18: 已发布 | X18: 46097 | Y18: https://www.xiaohongshu.com/explore/69b7c7410000000020038a54?app_platform=ios&app_version=9.21&share_from_user_hidden=true&xsec_source=app_share&type=normal&xsec_token=CB7jTqDRcPTmKOx_ZDxvYPo2nUb_jMEpRYhwmlA6jB0lw=&author_share=1&xhsshare=CopyLink&shareRedId=N0wyOURKSEo2NzUyOTgwNjY0OTc5PEdB&apptime=1773741394&share_id=efed7942b63d4cb3b736ade43ffa5227&wechatWid=197de0b9528d9f3a75eac472a6e2009c&wechatOrigin=menu | Z18: 706 | AA18: 96 | AB18: 18 | AC18: 否 | AF18: 否 | AI18: 已发布 | AJ18: 560 | AL18: 706 | AM18: 706 | AN18: 0.13597734 | AO18: 0.79320113
A19: 双平台 | B19: 重复 | C19: 阿咩 | D19: 无袖花苞长裙（黄） | E19: 2025945 | F19: 尺码：S 姓名：小超人 电话：13672395588 地址：广东省广州市番禺区广州中医药大学大学城校区生活区 | I19: 抖音 | J19: 0 | K19: 赘肉掉了一地 | L19: 46090 | N19: 46132 | P19: KOC | Q19: Zrdlydx | R19: 已发布 | U19: 送拍 | V19: 单篇 | W19: 已发布 | X19: 46097 | Y19: https://www.douyin.com/note/7617794625135292579?previous_page=app_code_link | Z19: 9809 | AA19: 812 | AB19: 91 | AC19: 是 | AF19: 否 | AI19: 已发布 | AJ19: 60 | AL19: 9809 | AM19: 980.9 | AN19: 0.082781119 | AO19: 0.061168315
C20: 一号 | D20: 葡萄冰萃上衣 | E20: 2026056 | F20: 追追别后悔15570350170江西省南昌市青山湖区艾溪湖四路新力渥园菜鸟驿站 尺码：m | I20: 小红书 | J20: 850 | K20: 追追别后悔 | L20: 46115 | N20: 46157 | P20: KOC | Q20: zhuizhuibiehouhui | R20: 档期内 | U20: 送拍 | V20: 单篇 | W20: 未发布 | AC20: 否 | AF20: 否 | AI20: 27 | AJ20: 850 | AL20: 0 | AN20: 0 | AO20: 0
C21: 一号 | D21: 蕾丝吊带 | E21: NH012 | F21: 追追别后悔15570350170江西省南昌市青山湖区艾溪湖四路新力渥园菜鸟驿站 尺码：m | G21: 已登记 | I21: 小红书 | J21: 0 | K21: 追追别后悔 | L21: 46115 | N21: 46157 | P21: KOC | Q21: zhuizhuibiehouhui | R21: 档期内 | U21: 送拍 | V21: 单篇 | W21: 未发布 | AC21: 否 | AF21: 否 | AI21: 27 | AJ21: 0 | AL21: 0 | AN21: 0 | AO21: 0
B22: 重复 | C22: 一号 | D22: 假两件波点短袖 | E22: 2026003 | F22: 追追别后悔15570350170江西省南昌市青山湖区艾溪湖四路新力渥园菜鸟驿站 尺码：m | I22: 小红书 | J22: 850 | K22: 追追别后悔 | L22: 46115 | N22: 46157 | P22: KOC | Q22: zhuizhuibiehouhui | R22: 档期内 | U22: 送拍 | V22: 单篇 | W22: 未发布 | AC22: 否 | AF22: 否 | AI22: 27 | AJ22: 895 | AL22: 0 | AN22: 0 | AO22: 0
C23: 馒头 | D23: 波点花边短袖 | E23: 2025317 | F23: m码 追追别后悔15570350170江西省南昌市青山湖区艾溪湖四路新力渥园菜鸟驿站 | G23: YT7615411973294 | I23: 小红书 | J23: 1350 | K23: 追追别后悔 | L23: 46125 | N23: 46162 | P23: KOC | Q23: zhuizhuibiehouhui | R23: 档期内 | U23: 送拍 | V23: 合集 | W23: 未发布 | AC23: 否 | AF23: 是 | AI23: 32 | AJ23: 1400 | AL23: 0 | AN23: 0 | AO23: 0
C24: 馒头 | D24: 波点中裙 | E24: 2025329 | F24: m码 追追别后悔15570350170江西省南昌市青山湖区艾溪湖四路新力渥园菜鸟驿站 | G24: YT7615411973294 | I24: 小红书 | J24: 0 | K24: 追追别后悔 | L24: 46125 | N24: 46162 | P24: KOC | Q24: zhuizhuibiehouhui | R24: 档期内 | U24: 送拍 | V24: 合集 | W24: 未发布 | AC24: 否 | AF24: 否 | AI24: 32 | AJ24: 52 | AL24: 0 | AN24: 0 | AO24: 0
C25: 馒头 | D25: 假两件波点短袖 | E25: 2026003 | F25: m码 追追别后悔15570350170江西省南昌市青山湖区艾溪湖四路新力渥园菜鸟驿站 | G25: YT7615411973294 | I25: 小红书 | J25: 900 | K25: 追追别后悔 | L25: 46125 | N25: 46162 | P25: KOC | Q25: zhuizhuibiehouhui | R25: 档期内 | U25: 送拍 | V25: 合集 | W25: 未发布 | AC25: 否 | AF25: 否 | AI25: 32 | AJ25: 945 | AL25: 0 | AN25: 0 | AO25: 0
C26: 馒头 | D26: 卡其风衣 | E26: 2025321 | I26: 小红书 | J26: 100 | K26: 祝我好运 | L26: 46009 | N26: 46073 | P26: 素人 | Q26: xf-99214 | R26: 超时 | U26: 送拍 | V26: 单篇 | W26: 未发布 | AC26: 否 | AF26: 否 | AI26: 超时 | AJ26: 200 | AL26: 0 | AN26: 0 | AO26: 0
C27: jing | D27: 无袖花苞长裙（黄） | E27: 2025945 | F27: 尺码：s 地址是：浙江省丽水市莲都区好溪路瓯景园8-502 收件人：阮软 电话：15088202792 | G27: YT7607952777662 | I27: 小红书 | J27: 50 | K27: 猪脚肘子 | L27: 46086 | N27: 46122 | P27: KOC | Q27: xxxRy5 | R27: 超时 | U27: 送拍 | V27: 合集 | W27: 未发布 | AC27: 否 | AF27: 否 | AI27: 超时 | AJ27: 110 | AL27: 0 | AN27: 0 | AO27: 0
C28: 六六 | D28: 波点花边短袖 | E28: 2025317 | F28: m码 收件人: 纯粹 手机号码: 15992317917 所在地区: 广东省佛山市南海区大沥镇 详细地址: 白沙社区三乡路2号创基广场1号楼7楼12房 需送货上门 | G28: YT7612455682744 | I28: 小红书 | J28: 500 | K28: 朱朱要睡觉 | L28: 46113 | N28: 46157 | P28: KOC | Q28: AZJAJUNYI | R28: 档期内 | U28: 送拍 | V28: 合集 | W28: 未发布 | AC28: 否 | AF28: 否 | AI28: 27 | AJ28: 550 | AL28: 0 | AN28: 0 | AO28: 0
C29: 一号 | D29: 抽绳波点吊带 | E29: 2026053 | F29: S码 收件人: 朱朱 手机号码: 15558189085 所在地区: 浙江省杭州市拱墅区文晖街道诸葛龙吟院6-501 | G29: 已登记 | I29: 小红书 | J29: 250 | K29: 朱朱不出门 | L29: 46101 | N29: 46152 | P29: 素人 | Q29: zhuyaxian18 | R29: 档期内 | U29: 送拍 | V29: 单篇 | W29: 未发布 | AC29: 否 | AF29: 否 | AI29: 22 | AJ29: 250 | AL29: 0 | AN29: 0 | AO29: 0
C30: 一号 | D30: 莫代尔防晒开衫（黑） | E30: 2026039外套 | F30: S码 收件人: 朱朱 手机号码: 15558189085 所在地区: 浙江省杭州市拱墅区文晖街道诸葛龙吟院6-501 | I30: 小红书 | J30: 0 | K30: 朱朱不出门 | L30: 46101 | N30: 46152 | P30: 素人 | Q30: zhuyaxian18 | R30: 档期内 | U30: 送拍 | V30: 单篇 | W30: 未发布 | AC30: 否 | AF30: 否 | AI30: 22 | AJ30: 30 | AL30: 0 | AN30: 0 | AO30: 0
C31: HE | D31: 人间秀珠套装 | E31: 2026058 | F31: S码 收件人: 朱朱 手机号码: 15558189085 所在地区: 浙江省杭州市拱墅区文晖街道诸葛龙吟院6-501 | G31: 已登记 | I31: 小红书 | J31: 280 | K31: 朱朱不出门 | L31: 46125 | N31: 46157 | P31: KOC | Q31: zhuyaxian18 | R31: 档期内 | U31: 送拍 | V31: 单篇 | W31: 未发布 | AC31: 否 | AF31: 否 | AI31: 27 | AJ31: 280 | AL31: 0 | AN31: 0 | AO31: 0
C32: XN | D32: 波点花边短袖 | E32: 2025317 | F32: S码 收件人: 朱朱 手机号码: 15558189085 所在地区: 浙江省杭州市拱墅区文晖街道诸葛龙吟院6-501 | G32: 已登记 | I32: 小红书 | J32: 400 | K32: 朱朱不出门 | L32: 46126 | N32: 46162 | P32: KOC | Q32: zhuyaxian18 | U32: 送拍 | V32: 单篇 | W32: 未发布 | AC32: 否 | AF32: 否 | AI32: 32 | AJ32: 450 | AL32: 0 | AN32: 0 | AO32: 0
C33: XN | D33: 波点中裙（黑） | E33: 2025329 | F33: S码 收件人: 朱朱 手机号码: 15558189085 所在地区: 浙江省杭州市拱墅区文晖街道诸葛龙吟院6-501 | G33: 已登记 | I33: 小红书 | J33: 0 | K33: 朱朱不出门 | L33: 46126 | N33: 46162 | P33: KOC | Q33: zhuyaxian18 | U33: 送拍 | V33: 单篇 | W33: 未发布 | AC33: 否 | AF33: 否 | AI33: 32 | AJ33: 52 | AL33: 0 | AN33: 0 | AO33: 0
C34: jing | D34: 黑白条衬衫 | E34: 2026062 | F34: 尺码：s 广东省佛山市南海区狮山镇小塘绿地丽雅香榭花苑 粥粥13246545703 | G34: YT7612793383477 | I34: 小红书 | J34: 450 | K34: 粥粥粥女士 | L34: 46093 | N34: 46142 | P34: KOL | Q34: zhouzi201499 | R34: 档期内 | U34: 送拍 | V34: 单篇 | W34: 未发布 | AC34: 否 | AF34: 否 | AI34: 12 | AJ34: 505 | AL34: 0 | AN34: 0 | AO34: 0
C35: HE | D35: 波点花边短袖 | E35: 2025317 | F35: 尺码：M 收件人: 周粥粥 手机号码: 15366323188 所在地区: 江苏省南通市启东市汇龙镇 详细地址: 科创嘉园23号楼1003室 | G35: YT7610834647249 | I35: 小红书 | J35: 65 | K35: 周粥粥 | L35: 46105 | N35: 46152 | P35: KOL | Q35: ZYL-baby1012 | R35: 档期内 | U35: 送拍 | V35: 单篇 | W35: 未发布 | AC35: 否 | AF35: 否 | AI35: 22 | AJ35: 115 | AL35: 0 | AN35: 0 | AO35: 0
C36: HE | D36: 波点中裙 | E36: 2025329 | F36: 尺码s 收件人: 周粥粥 手机号码: 15366323188 所在地区: 江苏省南通市启东市汇龙镇 详细地址: 科创嘉园23号楼1003室 | I36: 小红书 | J36: 0 | K36: 周粥粥 | L36: 46105 | N36: 46152 | P36: KOL | Q36: ZYL-baby1012 | R36: 档期内 | U36: 送拍 | V36: 单篇 | W36: 未发布 | AC36: 否 | AF36: 否 | AI36: 22 | AJ36: 52 | AL36: 0 | AN36: 0 | AO36: 0
C37: HE | D37: v领绑带上衣 | E37: NH008 | F37: 尺码：M 收件人: 周粥粥 手机号码: 15366323188 所在地区: 江苏省南通市启东市汇龙镇 详细地址: 科创嘉园23号楼1003室 | G37: 已登记 | I37: 小红书 | J37: 65 | K37: 周粥粥 | L37: 46105 | N37: 46152 | P37: KOL | Q37: ZYL-baby1012 | R37: 档期内 | U37: 送拍 | V37: 单篇 | W37: 未发布 | AC37: 否 | AF37: 否 | AI37: 22 | AJ37: 65 | AL37: 0 | AN37: 0 | AO37: 0
C38: HE | D38: 不规则波点半裙 | E38: NH009 | F38: 尺码s 收件人: 周粥粥 手机号码: 15366323188 所在地区: 江苏省南通市启东市汇龙镇 详细地址: 科创嘉园23号楼1003室 | G38: 已登记 | I38: 小红书 | J38: 0 | K38: 周粥粥 | L38: 46105 | N38: 46152 | P38: KOL | Q38: ZYL-baby1012 | R38: 档期内 | U38: 送拍 | V38: 单篇 | W38: 未发布 | AC38: 否 | AF38: 否 | AI38: 22 | AJ38: 0 | AL38: 0 | AN38: 0 | AO38: 0
C39: jing | D39: 无袖花苞长裙（黄） | E39: 2025945 | F39: 尺码：s 收件人: 周粥粥 手机号码: 15366323188 所在地区: 江苏省南通市启东市汇龙镇 详细地址: 科创嘉园23号楼1003室 | I39: 小红书 | J39: 65 | K39: 周粥粥 | L39: 46107 | N39: 46152 | P39: KOC | Q39: ZYL-baby1012 | R39: 档期内 | U39: 送拍 | V39: 单篇 | W39: 未发布 | AC39: 否 | AF39: 否 | AI39: 22 | AJ39: 125 | AL39: 0 | AN39: 0 | AO39: 0
C40: XN | D40: 波点花边长袖 | E40: 2025933 | I40: 小红书 | J40: 400 | K40: 周周不烦恼 | L40: 46080 | N40: 46113 | P40: KOC | Q40: zhousirur | R40: 已发布 | U40: 送拍 | V40: 单篇 | W40: 已发布 | X40: 46110 | Y40: http://xhslink.com/o/14pBJCUjuaK | AC40: 否 | AF40: 否 | AI40: 已发布 | AJ40: 450 | AL40: 0 | AM40: 0 | AN40: 0 | AO40: 0
C41: XN | D41: 波点中裙 | E41: 2025329 | I41: 小红书 | J41: 0 | K41: 周周不烦恼 | L41: 46080 | N41: 46113 | P41: KOC | Q41: zhousirur | R41: 已发布 | U41: 送拍 | V41: 单篇 | W41: 已发布 | X41: 46110 | Y41: http://xhslink.com/o/14pBJCUjuaK | AC41: 否 | AF41: 否 | AI41: 已发布 | AJ41: 52 | AN41: 0 | AO41: 0
C42: XN | D42: 繁花套装 | E42: 2026010 2026013 | I42: 小红书 | J42: 400 | K42: 周周不烦恼 | L42: 46080 | N42: 46132 | P42: KOC | Q42: zhousirur | R42: 重要催发 | U42: 送拍 | V42: 单篇 | W42: 未发布 | AC42: 否 | AF42: 否 | AI42: 2 | AJ42: 400 | AL42: 0 | AN42: 0 | AO42: 0
C43: jing | D43: 紫色连衣裙 | E43: 2026065 | F43: 尺码：m 收件人: 周周 手机号码: 17873587957 所在地区: 湖南省长沙市长沙县星沙街道 详细地址: 恒基凯旋门一期5 | G43: 已登记 | I43: 小红书 | J43: 400 | K43: 周周不烦恼 | L43: 46111 | N43: 46157 | P43: KOC | Q43: zhousirur | R43: 档期内 | U43: 送拍 | V43: 单篇 | W43: 未发布 | AC43: 否 | AF43: 否 | AI43: 27 | AJ43: 400 | AL43: 0 | AN43: 0 | AO43: 0
C44: 果片 | D44: 莫代尔防晒开衫（黑） | E44: 2026039外套 | F44: 尺码：s 收件人: 周周 手机号码: 17873587957 所在地区: 湖南省长沙市长沙县星沙街道 详细地址: 恒基凯旋门一期5 | I44: 小红书 | J44: 400 | K44: 周周不烦恼 | L44: 46112 | N44: 46157 | P44: KOL | Q44: zhousirur | R44: 档期内 | U44: 送拍 | V44: 单篇 | W44: 未发布 | AC44: 否 | AF44: 否 | AI44: 27 | AJ44: 430 | AL44: 0 | AN44: 0 | AO44: 0
C45: 果片 | D45: 百褶短裙（黑） | E45: NH011 | F45: 尺码：s 收件人: 周周 手机号码: 17873587957 所在地区: 湖南省长沙市长沙县星沙街道 详细地址: 恒基凯旋门一期5 | I45: 小红书 | J45: 0 | K45: 周周不烦恼 | N45: 46157 | P45: KOL | Q45: zhousirur | R45: 档期内 | U45: 送拍 | V45: 单篇 | W45: 未发布 | AC45: 否 | AF45: 否 | AI45: 27 | AJ45: 0 | AL45: 0 | AN45: 0 | AO45: 0
C46: 果片 | D46: 波点飘带（黑） | E46: NH010 | F46: 尺码：s 收件人: 周周 手机号码: 17873587957 所在地区: 湖南省长沙市长沙县星沙街道 详细地址: 恒基凯旋门一期5 | I46: 小红书 | J46: 0 | K46: 周周不烦恼 | L46: 46112 | N46: 46157 | P46: KOL | Q46: zhousirur | R46: 档期内 | U46: 送拍 | V46: 单篇 | W46: 未发布 | AC46: 否 | AF46: 否 | AI46: 27 | AJ46: 0 | AL46: 0 | AN46: 0 | AO46: 0
C47: 果片 | D47: 波点奶芙抹胸 | E47: 2026038内里 | F47: 尺码：s 收件人: 周周 手机号码: 17873587957 所在地区: 湖南省长沙市长沙县星沙街道 详细地址: 恒基凯旋门一期5 | I47: 小红书 | J47: 0 | K47: 周周不烦恼 | L47: 46112 | N47: 46157 | P47: KOL | Q47: zhousirur | R47: 档期内 | U47: 送拍 | V47: 单篇 | W47: 未发布 | AC47: 否 | AF47: 否 | AI47: 27 | AJ47: 35 | AL47: 0 | AN47: 0 | AO47: 0
C48: jing | D48: 假两件波点短袖 | E48: 2026003 | F48: 尺码：s 地址：收件人: 周 手机号码: 13715309596 所在地区: 广东省广州黄埔区文冲街道 详细地址: 黄埔万科中心T3栋 | G48: 已登记 | I48: 小红书 | J48: 0 | K48: 周周z | L48: 46113 | N48: 46157 | P48: 素人 | Q48: GD502741508 | R48: 档期内 | U48: 置换 | V48: 单篇 | W48: 未发布 | AC48: 否 | AF48: 否 | AI48: 27 | AJ48: 45 | AL48: 0 | AN48: 0 | AO48: 0
C49: jing | D49: 葡萄冰萃上衣 | E49: 2026056 | F49: 尺码：s 地址：收件人: 周 手机号码: 13715309596 所在地区: 广东省广州黄埔区文冲街道 详细地址: 黄埔万科中心T3栋 | G49: 已登记 | I49: 小红书 | J49: 0 | K49: 周周z | L49: 46113 | N49: 46157 | P49: 素人 | Q49: GD502741508 | R49: 档期内 | U49: 置换 | V49: 单篇 | W49: 未发布 | AC49: 否 | AF49: 否 | AI49: 27 | AJ49: 0 | AL49: 0 | AN49: 0 | AO49: 0
C50: jing | D50: 蕾丝吊带 | E50: NH012 | F50: 尺码：s 地址：收件人: 周 手机号码: 13715309596 所在地区: 广东省广州黄埔区文冲街道 详细地址: 黄埔万科中心T3栋 | G50: 已登记 | I50: 小红书 | J50: 0 | K50: 周周z | L50: 46113 | N50: 46157 | P50: 素人 | Q50: GD502741508 | R50: 档期内 | U50: 置换 | V50: 单篇 | W50: 未发布 | AC50: 否 | AF50: 否 | AI50: 27 | AJ50: 0 | AL50: 0 | AN50: 0 | AO50: 0
C51: 馒头 | D51: 初恋小白裙 | E51: 2026007 | F51: s码 厦门市集美区岩内墩上东里178-21号1907 周小娜 18506920052 | G51: YT7612051004528 | I51: 小红书 | J51: 100 | K51: 周小娜 | L51: 46111 | N51: 46157 | P51: 素人 | Q51: Z407798951 | R51: 档期内 | U51: 送拍 | V51: 单篇 | W51: 未发布 | AC51: 否 | AF51: 否 | AI51: 27 | AJ51: 165 | AL51: 0 | AN51: 0 | AO51: 0
C52: 阿咩 | D52: 抽绳波点吊带 | E52: 2026053 | F52: 尺码：M 安徽省亳州市利辛县强力学府b区9栋 等雨婷 19556522316 | I52: 小红书 | J52: 180 | K52: 周小六 | L52: 46101 | N52: 46152 | P52: KOC | Q52: syt20053 | R52: 档期内 | U52: 送拍 | V52: 单篇 | W52: 未发布 | AC52: 否 | AF52: 否 | AI52: 22 | AJ52: 180 | AL52: 0 | AN52: 0 | AO52: 0
C53: 阿咩 | D53: 莫代尔防晒开衫（黑） | E53: 2026039外套 | F53: 尺码：M 安徽省亳州市利辛县强力学府b区9栋 等雨婷 19556522316 | I53: 小红书 | J53: 0 | K53: 周小六 | L53: 46101 | N53: 46152 | P53: KOC | Q53: syt20053 | R53: 档期内 | U53: 送拍 | V53: 单篇 | W53: 未发布 | AC53: 否 | AF53: 否 | AI53: 22 | AJ53: 30 | AL53: 0 | AN53: 0 | AO53: 0
C54: HE | D54: 藏青色小香风 | E54: 2023010 | I54: 小红书 | J54: 120 | K54: 周杰伦大表妹 | L54: 46056 | N54: 46096 | P54: 素人 | Q54: Jay7918y | R54: 已发布 | U54: 送拍 | V54: 单篇 | W54: 已发布 | X54: 46094 | Y54: https://www.xiaohongshu.com/discovery/item/69b408d6000000001a02a34b?source=webshare&xhsshare=pc_web&xsec_token=ABiuaWOmBQnWH3GnIb455-fvmwYvBuNsNiOYKU1bdfBmw=&xsec_source=pc_share | Z54: 31 | AA54: 14 | AB54: 10 | AC54: 否 | AF54: 否 | AI54: 已发布 | AJ54: 205 | AL54: 31 | AM54: 31 | AN54: 0.4516129 | AO54: 6.6129032
C55: HE | D55: 条纹衬衫 | E55: 2023008 | I55: 小红书 | J55: 0 | K55: 周杰伦大表妹 | L55: 46056 | N55: 46096 | P55: 素人 | Q55: Jay7918y | R55: 已发布 | U55: 送拍 | V55: 单篇 | W55: 已发布 | X55: 46094 | Y55: https://www.xiaohongshu.com/discovery/item/69b408d6000000001a02a34b?source=webshare&xhsshare=pc_web&xsec_token=ABiuaWOmBQnWH3GnIb455-fvmwYvBuNsNiOYKU1bdfBmw=&xsec_source=pc_share | Z55: 31 | AA55: 14 | AB55: 10 | AC55: 否 | AF55: 否 | AI55: 已发布 | AJ55: 42 | AN55: 0.4516129 | AO55: 0
C56: 一号 | D56: 卡其风衣 | E56: 2025321 | I56: 小红书 | J56: 150 | K56: 周大小姐 | L56: 46011 | N56: 46053 | P56: KOC | Q56: zd719875337 | R56: 已发布 | U56: 送拍 | V56: 单篇 | W56: 已发布 | X56: 46041 | Y56: https://www.xiaohongshu.com/explore/696dcd7f000000002202234d?xsec_token=ABziGlt3WLs05-X_mGrVbICnxs2y5N15CIiUOxEa4qbrM=&xsec_source=pc_user | Z56: 94 | AA56: 35 | AB56: 6 | AC56: 否 | AF56: 否 | AI56: 已发布 | AJ56: 250 | AL56: 94 | AM56: 94 | AN56: 0.37234043 | AO56: 2.6595745
C57: 阿咩 | D57: 莫代尔防晒开衫（黑） | E57: 2026039外套 | F57: 尺码：S 四川省宜宾市翠屏区西华大学菜鸟驿站 熙熙 19960831982 | I57: 小红书 | J57: 100 | K57: 中午觉觉 | L57: 46114 | N57: 46157 | P57: KOC | Q57: Z_January14 | R57: 档期内 | U57: 送拍 | V57: 单篇 | W57: 未发布 | AC57: 否 | AF57: 否 | AI57: 27 | AJ57: 130 | AL57: 0 | AN57: 0 | AO57: 0
C58: 阿咩 | D58: 百褶短裙（黑） | E58: NH011 | F58: 尺码：S 四川省宜宾市翠屏区西华大学菜鸟驿站 熙熙 19960831982 | I58: 小红书 | J58: 0 | K58: 中午觉觉 | L58: 46114 | N58: 46157 | P58: KOC | Q58: Z_January14 | R58: 档期内 | U58: 送拍 | V58: 单篇 | W58: 未发布 | AC58: 否 | AF58: 否 | AI58: 27 | AJ58: 0 | AL58: 0 | AN58: 0 | AO58: 0
C59: 阿咩 | D59: 波点飘带（黑） | E59: NH010 | F59: 尺码：S 四川省宜宾市翠屏区西华大学菜鸟驿站 熙熙 19960831982 | I59: 小红书 | J59: 0 | K59: 中午觉觉 | L59: 46114 | N59: 46157 | P59: KOC | Q59: Z_January14 | R59: 档期内 | U59: 送拍 | V59: 单篇 | W59: 未发布 | AC59: 否 | AF59: 否 | AI59: 27 | AJ59: 0 | AL59: 0 | AN59: 0 | AO59: 0
C60: 阿咩 | D60: 波点奶芙抹胸 | E60: 2026038内里 | F60: 尺码：S 四川省宜宾市翠屏区西华大学菜鸟驿站 熙熙 19960831982 | I60: 小红书 | J60: 0 | K60: 中午觉觉 | L60: 46114 | N60: 46157 | P60: KOC | Q60: Z_January14 | R60: 档期内 | U60: 送拍 | V60: 单篇 | W60: 未发布 | AC60: 否 | AF60: 否 | AI60: 27 | AJ60: 35 | AL60: 0 | AN60: 0 | AO60: 0
C61: 馒头 | D61: 粉色毛领大衣 | E61: 2025334 | I61: 小红书 | J61: 600 | K61: 枳枳啊喂 | L61: 45992 | N61: 46052 | P61: KOC | Q61: zhizhia420 | R61: 已发布 | U61: 送拍 | V61: 合集 | W61: 已发布 | X61: 46027 | Y61: https://www.xiaohongshu.com/explore/695ba524000000000a02cc4d?xsec_token=ABge0uw3JyDIDkSTFZJvlpwl8M51l1Fu5bbRwHiA-RCK4=&xsec_source=pc_user | Z61: 1352 | AA61: 501 | AB61: 24 | AC61: 是 | AF61: 否 | AI61: 已发布 | AL61: 1352 | AM61: 1352 | AN61: 0.37056213 | AO61: 0
C62: 一号 | D62: 波点花边长袖 | E62: 2025933 | I62: 小红书 | J62: 500 | K62: 只有鱼 | L62: 46009 | N62: 46052 | P62: KOC | Q62: Zzy_3641 | R62: 已发布 | U62: 送拍 | V62: 合集 | W62: 已发布 | X62: 46050 | Y62: https://www.xiaohongshu.com/explore/6979cb18000000000a028749?xsec_token=ABXBRH6shm9DZGytpZ1DbnEkKO8UMy_mmyh6Tm1REYNKY=&xsec_source=pc_user | Z62: 6002 | AA62: 2507 | AB62: 86 | AC62: 是 | AF62: 否 | AI62: 已发布 | AJ62: 550 | AL62: 6002 | AM62: 6002 | AN62: 0.4176941 | AO62: 0.091636121
B63: 重复 | C63: 一号 | D63: 波点中裙 | E63: 2025329 | I63: 小红书 | J63: 0 | K63: 只有鱼 | L63: 46009 | N63: 46052 | P63: KOC | Q63: Zzy_3641 | R63: 已发布 | U63: 送拍 | V63: 单篇 | W63: 已发布 | X63: 46050 | Y63: https://www.xiaohongshu.com/explore/6979cb18000000000a028749?xsec_token=ABXBRH6shm9DZGytpZ1DbnEkKO8UMy_mmyh6Tm1REYNKY=&xsec_source=pc_user | Z63: 6002 | AA63: 2507 | AB63: 86 | AC63: 是 | AF63: 否 | AI63: 已发布 | AJ63: 52 | AN63: 0.4176941 | AO63: 0
B64: 重复 | C64: jing | D64: 毛衣马甲 | I64: 小红书 | J64: 650 | K64: 只有鱼 | L64: 46031 | N64: 46081 | P64: KOC | Q64: Zzy_3641 | R64: 已取消 | U64: 送拍 | V64: 合集 | W64: 已取消 | AC64: 否 | AF64: 否 | AI64: 已取消 | AL64: 0 | AN64: 0 | AO64: 0
B65: 重复 | C65: jing | D65: 木耳边打底 | I65: 小红书 | J65: 0 | K65: 只有鱼 | L65: 46031 | N65: 46081 | P65: KOC | Q65: Zzy_3641 | R65: 已取消 | U65: 送拍 | V65: 合集 | W65: 已取消 | AC65: 否 | AF65: 否 | AI65: 已取消 | AL65: 0 | AN65: 0 | AO65: 0
C66: jing | D66: 无袖花苞长裙（黄） | E66: 2025945 | F66: 尺码：s 福建省福州市闽侯县上街镇博士后b区 张颖13365389673 | G66: YT7606899504940 | I66: 小红书 | J66: 650 | K66: 只有鱼 | L66: 46086 | N66: 46157 | P66: KOC | Q66: Zzy_3641 | R66: 档期内 | U66: 送拍 | V66: 合集 | W66: 未发布 | AC66: 否 | AF66: 否 | AI66: 27 | AJ66: 710 | AL66: 0 | AN66: 0 | AO66: 0
A67: 双平台 | B67: 重复 | C67: 一号 | D67: 荷叶边沙滩裙 | E67: 2025322 | F67: 尺码：s 福建省福州市闽侯县上街镇博士后b区 张颖 13365389673 | G67: YT7609448139574 | I67: 小红书 | J67: 600 | K67: 只有鱼 | L67: 46098 | N67: 46142 | P67: KOC | Q67: Zzy_3641 | R67: 档期内 | U67: 送拍 | V67: 单篇 | W67: 未发布 | AC67: 否 | AF67: 否 | AI67: 12 | AJ67: 690 | AL67: 0 | AN67: 0 | AO67: 0
B68: 重复 | C68: 一号 | D68: 荷叶边沙滩上衣 | E68: 2025322 | F68: 尺码：s 福建省福州市闽侯县上街镇博士后b区 张颖 13365389673 | I68: 小红书 | J68: 0 | K68: 只有鱼 | L68: 46098 | N68: 46142 | P68: KOC | Q68: Zzy_3641 | R68: 档期内 | U68: 送拍 | V68: 单篇 | W68: 未发布 | AC68: 否 | AF68: 否 | AI68: 12 | AJ68: 90 | AL68: 0 | AN68: 0 | AO68: 0
C69: HE | D69: 波点花边短袖 | E69: 2025317 | F69: 尺码：s 福建省福州市闽侯县上街镇博士后b区 张颖 13365389673 | G69: YT7610722416333 | I69: 小红书 | J69: 700 | K69: 只有鱼 | L69: 46100 | N69: 46152 | P69: KOC | Q69: Zzy_3641 | R69: 档期内 | S69: 召回中 | U69: 寄拍 | V69: 单篇 | W69: 未发布 | AC69: 否 | AF69: 否 | AI69: 22 | AJ69: 750 | AL69: 0 | AN69: 0 | AO69: 0
B70: 重复 | C70: HE | D70: 波点中裙 | E70: 2025329 | F70: 尺码：s 福建省福州市闽侯县上街镇博士后b区 张颖 13365389673 | I70: 小红书 | J70: 0 | K70: 只有鱼 | L70: 46100 | N70: 46152 | P70: KOC | Q70: Zzy_3641 | R70: 档期内 | S70: 召回中 | U70: 寄拍 | V70: 单篇 | W70: 未发布 | AC70: 否 | AF70: 否 | AI70: 22 | AJ70: 52 | AL70: 0 | AN70: 0 | AO70: 0
C71: 阿咩 | D71: 波点奶芙抹胸 | E71: 2026038内里 | F71: 尺码：S 刘思琪 15656864098 安徽省阜阳市阜南县 汪寺村连庄50号阜阳兴刚种养殖专业合作社汪寺小学 | G71: 已登记 | I71: 小红书 | J71: 50 | K71: 只想躺沙发 | L71: 46108 | N71: 46152 | P71: KOC | Q71: Lik07120 | R71: 档期内 | S71: 召回中 | U71: 寄拍 | V71: 单篇 | W71: 未发布 | AC71: 否 | AF71: 否 | AI71: 22 | AJ71: 85 | AL71: 0 | AN71: 0 | AO71: 0
C72: 阿咩 | D72: 莫代尔防晒开衫（黑） | E72: 2026039外套 | F72: 尺码：S 刘思琪 15656864098 安徽省阜阳市阜南县 汪寺村连庄50号阜阳兴刚种养殖专业合作社汪寺小学 | G72: 已登记 | I72: 小红书 | J72: 0 | K72: 只想躺沙发 | L72: 46108 | N72: 46152 | P72: KOC | Q72: Lik07120 | R72: 档期内 | S72: 召回中 | U72: 寄拍 | V72: 单篇 | W72: 未发布 | AC72: 否 | AF72: 否 | AI72: 22 | AJ72: 30 | AL72: 0 | AN72: 0 | AO72: 0
C73: 阿咩 | D73: 百褶短裙（黑） | E73: NH011 | F73: 尺码：S 刘思琪 15656864098 安徽省阜阳市阜南县 汪寺村连庄50号阜阳兴刚种养殖专业合作社汪寺小学 | G73: 已登记 | I73: 小红书 | J73: 0 | K73: 只想躺沙发 | L73: 46108 | N73: 46152 | P73: KOC | Q73: Lik07120 | R73: 档期内 | S73: 召回中 | U73: 寄拍 | V73: 单篇 | W73: 未发布 | AC73: 否 | AF73: 否 | AI73: 22 | AJ73: 0 | AL73: 0 | AN73: 0 | AO73: 0
C74: 阿咩 | D74: 波点飘带（黑） | E74: NH010 | F74: 尺码：S 刘思琪 15656864098 安徽省阜阳市阜南县 汪寺村连庄50号阜阳兴刚种养殖专业合作社汪寺小学 | G74: 已登记 | I74: 小红书 | J74: 0 | K74: 只想躺沙发 | L74: 46108 | N74: 46152 | P74: KOC | Q74: Lik07120 | R74: 档期内 | S74: 召回中 | U74: 寄拍 | V74: 单篇 | W74: 未发布 | AC74: 否 | AF74: 否 | AI74: 22 | AJ74: 0 | AL74: 0 | AN74: 0 | AO74: 0
C75: 一号 | D75: 粉棕一字肩 | I75: 小红书 | J75: 300 | K75: 只想睡觉 | L75: 46026 | N75: 46068 | P75: KOC | Q75: zxy10008y | R75: 已取消 | U75: 送拍 | V75: 单篇 | W75: 已取消 | AC75: 否 | AF75: 否 | AI75: 已取消 | AL75: 0 | AN75: 0 | AO75: 0
C76: 一号 | D76: 镶钻一字肩 | E76: MY012 | I76: 小红书 | J76: 300 | K76: 只想睡觉 | L76: 46026 | N76: 46068 | P76: KOC | Q76: zxy10008y | R76: 已取消 | U76: 送拍 | V76: 单篇 | W76: 已取消 | AC76: 否 | AF76: 否 | AI76: 已取消 | AJ76: 300 | AL76: 0 | AN76: 0 | AO76: 0
C77: 馒头 | D77: 波点花边长袖 | E77: 2025933 | I77: 小红书 | J77: 350 | K77: 只会比耶 | L77: 46052 | N77: 46111 | P77: KOC | R77: 已发布 | U77: 送拍 | V77: 单篇 | W77: 已发布 | X77: 46107 | Y77: https://www.xiaohongshu.com/explore/69c49a16000000002200da3c?app_platform=ios&app_version=9.22.1&share_from_user_hidden=true&xsec_source=app_share&type=video&xsec_token=CByvxo1ys2B7op6_8Nj_E8eFo_xfoZOEIamj1O7uEHyLg=&author_share=1&xhsshare=CopyLink&shareRedId=N0k3MTtLPDs2NzUyOTgwNjdEOTpGOD5A&apptime=1774506150&share_id=890251fa74454f7289d4800c565d7236&wechatWid=f7c29764c15365e43d0a80e5f8790bf2&wechatOrigin=menu | Z77: 46 | AA77: 13 | AB77: 5 | AC77: 否 | AF77: 否 | AI77: 已发布 | AJ77: 400 | AL77: 46 | AM77: 46 | AN77: 0.2826087 | AO77: 8.6956522
C78: 馒头 | D78: 波点中裙 | E78: 2025329 | I78: 小红书 | J78: 0 | K78: 只会比耶 | L78: 46052 | N78: 46111 | P78: KOC | R78: 已发布 | U78: 送拍 | V78: 单篇 | W78: 已发布 | X78: 46107 | Y78: https://www.xiaohongshu.com/explore/69c49a16000000002200da3c?app_platform=ios&app_version=9.22.1&share_from_user_hidden=true&xsec_source=app_share&type=video&xsec_token=CByvxo1ys2B7op6_8Nj_E8eFo_xfoZOEIamj1O7uEHyLg=&author_share=1&xhsshare=CopyLink&shareRedId=N0k3MTtLPDs2NzUyOTgwNjdEOTpGOD5A&apptime=1774506150&share_id=890251fa74454f7289d4800c565d7236&wechatWid=f7c29764c15365e43d0a80e5f8790bf2&wechatOrigin=menu | Z78: 46 | AA78: 13 | AB78: 5 | AC78: 否 | AF78: 否 | AI78: 已发布 | AJ78: 52 | AN78: 0.2826087 | AO78: 0
C79: 馒头 | D79: 收腰礼裙 | I79: 小红书 | J79: 350 | K79: 只会比耶 | L79: 46052 | N79: 46111 | P79: KOC | R79: 已取消 | S79: 召回成功 | T79: 435099532531636 | U79: 送拍 | V79: 单篇 | W79: 已召回 | AC79: 否 | AF79: 否 | AI79: 超时 | AL79: 0 | AN79: 0 | AO79: 0
C80: jing | D80: 无袖花苞长裙（黄） | E80: 2025945 | I80: 抖音 | J80: 0 | K80: 止咳糖江女士 | L80: 46055 | N80: 46096 | P80: KOC | Q80: Wwu00312 | R80: 已发布 | U80: 送拍 | V80: 单篇 | W80: 已发布 | X80: 46097 | Y80: https://www.douyin.com/user/MS4wLjABAAAA0D89cbj85J-Dqb1GihpA9w2Z9uxh27ojeeiXaxRXoyM?from_tab_name=main&modal_id=7617836965061076970 | Z80: 1194 | AA80: 50 | AB80: 72 | AC80: 是 | AF80: 否 | AI80: 已发布 | AJ80: 60 | AL80: 1194 | AM80: 119.4 | AN80: 0.041876047 | AO80: 0.50251256
C81: HE | D81: 波点花边长袖 | E81: 2025933 | I81: 小红书 | J81: 60 | K81: 栀枳 | L81: 46051 | N81: 46096 | P81: 素人 | Q81: Wjtxqz25 | R81: 已发布 | U81: 送拍 | V81: 单篇 | W81: 已发布 | X81: 46093 | Y81: https://www.xiaohongshu.com/discovery/item/69b2df8200000000060099ab?source=webshare&xhsshare=pc_web&xsec_token=CBOLXaVUkSP4ZQb26JLLrTB08RSEkzj-YyCQXs9BhahFE=&xsec_source=pc_share | Z81: 20 | AA81: 5 | AB81: 1 | AC81: 否 | AF81: 否 | AI81: 已发布 | AJ81: 110 | AL81: 20 | AM81: 20 | AN81: 0.25 | AO81: 5.5
C82: HE | D82: 波点中裙 | E82: 2025329 | I82: 小红书 | J82: 0 | K82: 栀枳 | L82: 46051 | N82: 46096 | P82: 素人 | Q82: Wjtxqz25 | R82: 已发布 | U82: 送拍 | V82: 单篇 | W82: 已发布 | X82: 46093 | Y82: https://www.xiaohongshu.com/discovery/item/69b2df8200000000060099ab?source=webshare&xhsshare=pc_web&xsec_token=CBOLXaVUkSP4ZQb26JLLrTB08RSEkzj-YyCQXs9BhahFE=&xsec_source=pc_share | Z82: 20 | AA82: 5 | AB82: 1 | AC82: 否 | AF82: 否 | AI82: 已发布 | AJ82: 52 | AN82: 0.25 | AO82: 0
C83: jing | D83: 蕾丝防晒衬衫（蓝） | E83: 2025308 | I83: 抖音 | J83: 0 | K83: 知知知更 | L83: 46051 | N83: 46096 | P83: 素人 | Q83: Haruaimama0214 | R83: 已发布 | U83: 送拍 | V83: 单篇 | W83: 已发布 | X83: 46095 | Y83: https://www.douyin.com/jingxuan/search/%E7%9F%A5%E7%9F%A5%E7%9F%A5%E6%9B%B4?aid=f9a62638-b345-4ebe-97dc-538d0c4f1fd4&modal_id=7617049160084854437&type=general | Z83: 74 | AA83: 13 | AB83: 5 | AC83: 否 | AF83: 否 | AI83: 已发布 | AJ83: 55 | AL83: 74 | AM83: 7.4 | AN83: 0.17567568 | AO83: 7.4324324
C84: jing | D84: 黑白格连衣裙 | E84: 2026006 | F84: 尺码：L 收件人: 陈 手机号码: 13158251138 所在地区: 贵州省黔东南苗族侗族自治州凯里市西门街道 详细地址: 碧桂园·星悦湾5栋 | G84: 已登记 | I84: 小红书 | J84: 400 | K84: 知知学穿搭酱 | L84: 46086 | N84: 46132 | P84: KOL | Q84: zhizhichuanda | R84: 重要催发 | U84: 送拍 | V84: 单篇 | W84: 未发布 | AC84: 否 | AF84: 否 | AI84: 2 | AJ84: 490 | AL84: 0 | AN84: 0 | AO84: 0
C85: jing | D85: 波点花边长袖 | E85: 2025933 | F85: 尺码：L 收件人: 陈 手机号码: 13158251138 所在地区: 贵州省黔东南苗族侗族自治州凯里市西门街道 详细地址: 碧桂园·星悦湾5栋 | G85: YT7613770158439 | I85: 小红书 | J85: 400 | K85: 知知学穿搭酱 | L85: 46086 | N85: 46122 | P85: KOL | Q85: zhizhichuanda | R85: 已取消 | U85: 送拍 | V85: 单篇 | W85: 已取消 | AC85: 否 | AF85: 否 | AI85: 已取消 | AJ85: 450 | AL85: 0 | AN85: 0 | AO85: 0
C86: jing | D86: 波点中裙 | E86: 2025329 | F86: 尺码：L 收件人: 陈 手机号码: 13158251138 所在地区: 贵州省黔东南苗族侗族自治州凯里市西门街道 详细地址: 碧桂园·星悦湾5栋 | G86: YT7613770158439 | I86: 小红书 | J86: 0 | K86: 知知学穿搭酱 | L86: 46086 | N86: 46122 | P86: KOL | Q86: zhizhichuanda | R86: 已取消 | U86: 送拍 | V86: 单篇 | W86: 已取消 | AC86: 否 | AF86: 否 | AI86: 已取消 | AJ86: 52 | AL86: 0 | AN86: 0 | AO86: 0
C87: jing | D87: 繁花半裙 | E87: 2026013 | F87: 尺码：L 收件人: 陈 手机号码: 13158251138 所在地区: 贵州省黔东南苗族侗族自治州凯里市西门街道 详细地址: 碧桂园·星悦湾5栋 | G87: YT7615411973258 | I87: 小红书 | J87: 400 | K87: 知知学穿搭酱 | L87: 46126 | N87: 46157 | P87: KOC | Q87: zhizhichuanda | R87: 档期内 | U87: 送拍 | V87: 单篇 | W87: 未发布 | AC87: 否 | AF87: 否 | AI87: 27 | AJ87: 460 | AL87: 0 | AN87: 0 | AO87: 0
C88: jing | D88: 繁花短袖 | E88: 2026010 | F88: 尺码：L 收件人: 陈 手机号码: 13158251138 所在地区: 贵州省黔东南苗族侗族自治州凯里市西门街道 详细地址: 碧桂园·星悦湾5栋 | G88: YT7615411973258 | I88: 小红书 | J88: 0 | K88: 知知学穿搭酱 | L88: 46126 | N88: 46157 | P88: KOC | Q88: zhizhichuanda | R88: 档期内 | U88: 送拍 | V88: 单篇 | W88: 未发布 | AC88: 否 | AF88: 否 | AI88: 27 | AJ88: 30 | AL88: 0 | AN88: 0 | AO88: 0
A89: 双平台 | B89: 重复 | C89: 阿咩 | D89: 波点花边长袖 | E89: 2025933 | I89: 小红书 | J89: 400 | K89: 知世者的神 | L89: 46017 | N89: 46068 | P89: KOC | Q89: Butte2flyL1tter_1 | R89: 已发布 | U89: 送拍 | V89: 单篇 | W89: 已发布 | X89: 46086 | Y89: https://www.xiaohongshu.com/explore/698ec8390000000009038716?app_platform=ios&app_version=9.19.4&share_from_user_hidden=true&xsec_source=app_share&type=video&xsec_token=CBuDQgsvybydzZehrlMhEJIe1Y5S0FsnGH1TaxU39p1LM=&author_share=1&xhsshare=WeixinSession&shareRedId=ODlIRjw1N0I2NzUyOTgwNjZJOTg2ODY6&apptime=1771257219&share_id=06ebaacaac2a41c3893b009292fa9eca&wechatWid=197de0b9528d9f3a75eac472a6e2009c&wechatOrigin=menu | AC89: 否 | AF89: 否 | AI89: 已发布 | AJ89: 450 | AL89: 0 | AM89: 0 | AN89: 0 | AO89: 0
A90: 双平台 | B90: 重复 | C90: 阿咩 | D90: 波点花边长袖 | E90: 2025933 | I90: 抖音 | J90: 0 | K90: 知世者的神 | L90: 46017 | N90: 46068 | P90: KOC | Q90: Butte2flyL1tter_1 | R90: 已发布 | U90: 送拍 | V90: 单篇 | W90: 已发布 | X90: 46086 | Y90: https://weixin110.qq.com/cgi-bin/mmspamsupport-bin/newredirectconfirmcgi?click=6e88d59daf0b4efc14c40bbdd4d13c8f&bankey=1ad204af26c6b4d4f23b88add46f995b&midpagecode=e2faa0ee03e19e6efecf869b7f9ca0522c68d4854df6fbfa04376e4e5a76fb68051eaf8948fea39790a1cd7df4a64a26&bancode=f1a0e95e1f127ef431e6eb22a48348dfb74553bb6e8bb8bfcbeb5d99325c4cca961f9d48851306721bc9de7384f91d5cc6f02710262e90b0b3e6e3b54e5fee0d92c2ccf4d505aaf8026178073905dfbe70456d1a8bdd19e80b015db67fce87028b9dae7fcc0ce55aeab060af2ab540dc55c23b2b9ae8180e6348f169ab4361c66493c4c0ede9fed2058c006b31ffd43cfac1868471e7327e12b367701111b750482461e7b7cf014d6cd896927f8a0118dc07522a4241108d4191db898bcdd0c7f907180284ff01eb63272dbd398c29429433946c26908e196e5dcd4e1676d1a35a7e544d819ea4dbd24975a17ee5ca6ba220b3474891a0c575c13324f1be69d5eb56acb034960f1b23054440b94f4f58fb27963122711e2e787b070f09717b64a23c2ccfca88d81bce7227e94db7b76a3739de8849752b2954c9efdc860fd1a60578f03d463cff4e230a574d329f328dd4b3e4529a4fef36304d9a68ff2c11d7ed0ace15f3bde537b4d30e1645d5c6895c47430c2bbf16459813d43afc18661d3c072241082d7fb1d95b70f90dcab260d4f003b7aed4981714842b1625bb985ef0774c88399f1a281d3a5f716f0d51f6127d340db417a0d4f3571f6ddb0757a37dccdba7d6a91b4af34452b25115432a9761efd64aba91af62987969c030f1810935e4162c90e55ea82ea748c52781e2051801f921c3c168abdd1e988b47d58070aa140fec0abd684a2ead9011ffc08c5e55f8dc16e2fb4ebccbfa79de8f59a7ce1375dfd777bbcf0f118978b11c5a48be94ced826eb250878dbd739521eb7f5ba3c5dcef7341bd4258fcdcfd9d8ae0a2c729c6b91e1ada100225e26fd9eac5bce9f6b4edad8315c26e2b36225a8b2243a816d70cdcddc9f2aabceac5c2de89dc41f061b6586352afd83fbc7e9946ca2f92749dda3850718f2bb4e8a9291ee77a5c4d096625caa0e879caef9b826b433a37d17b77e839738ff362bfb5e2dc6736649cf69b1514349a86ba8113d5521b188698c0e659abd8486d61075e63f89c39893be96567f10a8cc95158f345ce706f1338a109c179911b1ea22441dfece700c8f890728f27281a00067530aacd2b29a90b9b7d4d61b3c584565c292d76bebbf955852df2d9add0f2107455bd3847d16ae454edcd4b450c23754f3c6ba5a8905fa67cc04ad5e1810e22759b98decad | AC90: 否 | AF90: 否 | AI90: 已发布 | AJ90: 50 | AL90: 0 | AM90: 0 | AN90: 0 | AO90: 0
A91: 双平台 | B91: 重复 | C91: 阿咩 | D91: 波点中裙 | E91: 2025329 | I91: 小红书 | J91: 0 | K91: 知世者的神 | L91: 46017 | N91: 46068 | P91: KOC | Q91: Butte2flyL1tter_1 | R91: 已发布 | U91: 送拍 | V91: 单篇 | W91: 已发布 | X91: 46086 | Y91: https://www.xiaohongshu.com/explore/698ec8390000000009038716?app_platform=ios&app_version=9.19.4&share_from_user_hidden=true&xsec_source=app_share&type=video&xsec_token=CBuDQgsvybydzZehrlMhEJIe1Y5S0FsnGH1TaxU39p1LM=&author_share=1&xhsshare=WeixinSession&shareRedId=ODlIRjw1N0I2NzUyOTgwNjZJOTg2ODY6&apptime=1771257219&share_id=06ebaacaac2a41c3893b009292fa9eca&wechatWid=197de0b9528d9f3a75eac472a6e2009c&wechatOrigin=menu | AC91: 否 | AF91: 否 | AI91: 已发布 | AJ91: 52 | AN91: 0 | AO91: 0
A92: 双平台 | B92: 重复 | C92: 阿咩 | D92: 波点中裙 | E92: 2025329 | I92: 抖音 | J92: 0 | K92: 知世者的神 | L92: 46017 | N92: 46068 | P92: KOC | Q92: Butte2flyL1tter_1 | R92: 已发布 | U92: 送拍 | V92: 单篇 | W92: 已发布 | X92: 46086 | Y92: https://weixin110.qq.com/cgi-bin/mmspamsupport-bin/newredirectconfirmcgi?click=6e88d59daf0b4efc14c40bbdd4d13c8f&bankey=1ad204af26c6b4d4f23b88add46f995b&midpagecode=e2faa0ee03e19e6efecf869b7f9ca0522c68d4854df6fbfa04376e4e5a76fb68051eaf8948fea39790a1cd7df4a64a26&bancode=f1a0e95e1f127ef431e6eb22a48348dfb74553bb6e8bb8bfcbeb5d99325c4cca961f9d48851306721bc9de7384f91d5cc6f02710262e90b0b3e6e3b54e5fee0d92c2ccf4d505aaf8026178073905dfbe70456d1a8bdd19e80b015db67fce87028b9dae7fcc0ce55aeab060af2ab540dc55c23b2b9ae8180e6348f169ab4361c66493c4c0ede9fed2058c006b31ffd43cfac1868471e7327e12b367701111b750482461e7b7cf014d6cd896927f8a0118dc07522a4241108d4191db898bcdd0c7f907180284ff01eb63272dbd398c29429433946c26908e196e5dcd4e1676d1a35a7e544d819ea4dbd24975a17ee5ca6ba220b3474891a0c575c13324f1be69d5eb56acb034960f1b23054440b94f4f58fb27963122711e2e787b070f09717b64a23c2ccfca88d81bce7227e94db7b76a3739de8849752b2954c9efdc860fd1a60578f03d463cff4e230a574d329f328dd4b3e4529a4fef36304d9a68ff2c11d7ed0ace15f3bde537b4d30e1645d5c6895c47430c2bbf16459813d43afc18661d3c072241082d7fb1d95b70f90dcab260d4f003b7aed4981714842b1625bb985ef0774c88399f1a281d3a5f716f0d51f6127d340db417a0d4f3571f6ddb0757a37dccdba7d6a91b4af34452b25115432a9761efd64aba91af62987969c030f1810935e4162c90e55ea82ea748c52781e2051801f921c3c168abdd1e988b47d58070aa140fec0abd684a2ead9011ffc08c5e55f8dc16e2fb4ebccbfa79de8f59a7ce1375dfd777bbcf0f118978b11c5a48be94ced826eb250878dbd739521eb7f5ba3c5dcef7341bd4258fcdcfd9d8ae0a2c729c6b91e1ada100225e26fd9eac5bce9f6b4edad8315c26e2b36225a8b2243a816d70cdcddc9f2aabceac5c2de89dc41f061b6586352afd83fbc7e9946ca2f92749dda3850718f2bb4e8a9291ee77a5c4d096625caa0e879caef9b826b433a37d17b77e839738ff362bfb5e2dc6736649cf69b1514349a86ba8113d5521b188698c0e659abd8486d61075e63f89c39893be96567f10a8cc95158f345ce706f1338a109c179911b1ea22441dfece700c8f890728f27281a00067530aacd2b29a90b9b7d4d61b3c584565c292d76bebbf955852df2d9add0f2107455bd3847d16ae454edcd4b450c23754f3c6ba5a8905fa67cc04ad5e1810e22759b98decad | AC92: 否 | AF92: 否 | AI92: 已发布 | AJ92: 52 | AN92: 0 | AO92: 0
C93: HE | D93: v领绑带上衣 | E93: NH008 | F93: 尺码：S 春日野 19033812013 安徽省芜湖市弋江区 大工山路与仓津路交汇处东南侧伟星国樾1栋3单元1101 | G93: 已登记 | I93: 小红书 | J93: 200 | K93: 知世者的神 | L93: 46101 | N93: 46152 | P93: KOL | Q93: Butte2flyL1tter_1 | R93: 档期内 | U93: 送拍 | V93: 单篇 | W93: 未发布 | AC93: 否 | AF93: 否 | AI93: 22 | AJ93: 200 | AL93: 0 | AN93: 0 | AO93: 0
C94: HE | D94: 不规则波点半裙 | E94: NH009 | F94: 尺码：S 春日野 19033812013 安徽省芜湖市弋江区 大工山路与仓津路交汇处东南侧伟星国樾1栋3单元1101 | G94: 已登记 | I94: 小红书 | J94: 0 | K94: 知世者的神 | L94: 46101 | N94: 46152 | P94: KOL | Q94: Butte2flyL1tter_1 | R94: 档期内 | U94: 送拍 | V94: 单篇 | W94: 未发布 | AC94: 否 | AF94: 否 | AI94: 22 | AJ94: 0 | AL94: 0 | AN94: 0 | AO94: 0
C95: jing | D95: 蕾丝防晒衬衫（蓝） | E95: 2025308 | I95: 小红书 | J95: 500 | K95: 知更 | L95: 46051 | N95: 46096 | P95: KOL | Q95: Haruaimama0214 | R95: 已发布 | U95: 送拍 | V95: 单篇 | W95: 已发布 | X95: 46095 | Y95: https://www.xiaohongshu.com/explore/69b532490000000023004289?xsec_token=ABFsghZyg5Oi2BuP4i0hJNVWPoYL8AuTWSLxWtQ0SR49g=&xsec_source=pc_user | Z95: 514 | AA95: 191 | AB95: 25 | AC95: 否 | AF95: 否 | AI95: 已发布 | AJ95: 555 | AL95: 514 | AM95: 514 | AN95: 0.37159533 | AO95: 1.0797665
B96: 重复 | C96: 一号 | D96: 毛衣马甲 | I96: 小红书 | J96: 250 | K96: 吱吱 | L96: 46038 | N96: 46081 | P96: KOC | Q96: _zizizz | R96: 已取消 | U96: 送拍 | V96: 单篇 | W96: 已取消 | AC96: 否 | AF96: 否 | AI96: 已取消 | AL96: 0 | AN96: 0 | AO96: 0
B97: 重复 | C97: 一号 | D97: 木耳边打底 | I97: 小红书 | J97: 0 | K97: 吱吱 | L97: 46038 | N97: 46081 | P97: KOC | Q97: _zizizz | R97: 已取消 | U97: 送拍 | V97: 单篇 | W97: 已取消 | AC97: 否 | AF97: 否 | AI97: 已取消 | AL97: 0 | AN97: 0 | AO97: 0
C98: 馒头 | D98: 波点花边长袖 | E98: 2025933 | I98: 小红书 | J98: 230 | K98: 吱吱 | L98: 46056 | N98: 46106 | P98: KOC | Q98: _zizizz | R98: 已发布 | U98: 送拍 | V98: 单篇 | W98: 已发布 | X98: 46090 | Y98: https://www.xiaohongshu.com/explore/69ae3c8d0000000015039e5e?app_platform=ios&app_version=9.19.5&share_from_user_hidden=true&xsec_source=app_share&type=video&xsec_token=CBrwxtWJxPmrTg9RfHu1kFN-rocZbEia3thDt8sNA_tvs=&author_share=1&xhsshare=CopyLink&shareRedId=N0s2OTQ5PEA2NzUyOTgwNjY0OTc2PDdP&apptime=1773027378&share_id=0abb773250614ef298246cd577d6a668&wechatWid=f7c29764c15365e43d0a80e5f8790bf2&wechatOrigin=menu | Z98: 313 | AA98: 124 | AB98: 12 | AC98: 否 | AF98: 否 | AI98: 已发布 | AJ98: 280 | AL98: 313 | AM98: 313 | AN98: 0.39616613 | AO98: 0.89456869
C99: 馒头 | D99: 波点中裙 | E99: 2025329 | I99: 小红书 | J99: 0 | K99: 吱吱 | L99: 46056 | N99: 46106 | P99: KOC | Q99: _zizizz | R99: 已发布 | U99: 送拍 | V99: 单篇 | W99: 已发布 | X99: 46090 | Y99: https://www.xiaohongshu.com/explore/69ae3c8d0000000015039e5e?app_platform=ios&app_version=9.19.5&share_from_user_hidden=true&xsec_source=app_share&type=video&xsec_token=CBrwxtWJxPmrTg9RfHu1kFN-rocZbEia3thDt8sNA_tvs=&author_share=1&xhsshare=CopyLink&shareRedId=N0s2OTQ5PEA2NzUyOTgwNjY0OTc2PDdP&apptime=1773027378&share_id=0abb773250614ef298246cd577d6a668&wechatWid=f7c29764c15365e43d0a80e5f8790bf2&wechatOrigin=menu | Z99: 313 | AA99: 124 | AB99: 12 | AC99: 否 | AF99: 否 | AI99: 已发布 | AJ99: 52 | AN99: 0.39616613 | AO99: 0
C100: 一号 | D100: 大翻领皮草（卡其） | E100: 2025997 | I100: 小红书 | J100: 0 | K100: 芝士张 | L100: 45997 | N100: 46052 | P100: KOC | Q100: zdzy8889 | R100: 已发布 | U100: 置换 | V100: 单篇 | W100: 已发布 | X100: 46010 | Y100: https://www.xiaohongshu.com/explore/6944c0ed000000001e034bf3?xsec_token=ABV4VcErubfY__WklX4Mznjr6fWOkM3DdgI-tmW81w4NM=&xsec_source=pc_user | Z100: 102 | AA100: 20 | AB100: 7 | AC100: 否 | AF100: 否 | AI100: 已发布 | AJ100: 100 | AL100: 102 | AM100: 102 | AN100: 0.19607843 | AO100: 0.98039216
...

Sheet BI看板
A1: 三月（默认当月，支持筛选）
A2: 负责PR | B2: 约篇件数 | C2: 档期内 | D2: 催发 | E2: 重要催发 | F2: 超时 | G2: 已发布 | H2: 已填写点赞量数量 | I2: 信息完整度 | J2: 已取消 | K2: 应召回 | L2: 召回成功 | M2: 召回完成率 | N2: 超时率 | O2: 月度完成率 | P2: 3月爆文数 (≥500赞) | Q2: 爆文率 | R2: 点赞数 | S2: 成本（含衣服） | T2: CPL（元 / 赞）
A3: 阿咩 | B3: 228 | C3: 132 | D3: 0 | E3: 25 | F3: 36 | G3: 31 | H3: 24 | I3: 0.77419355 | J3: 4 | K3: 34 | L3: 3 | M3: 0.088235294 | N3: 0.15789474 | O3: 0.15350877 | P3: 4 | Q3: 0.12903226 | R3: 4359.9 | S3: 7924 | T3: 1.8174729
A4: jing | B4: 375 | C4: 166 | D4: 0 | E4: 41 | F4: 9 | G4: 138 | H4: 94 | I4: 0.68115942 | J4: 20 | K4: 7 | L4: 10 | M4: 1.4285714 | N4: 0.024 | O4: 0.448 | P4: 14 | Q4: 0.10144928 | R4: 35985.1 | S4: 31409 | T4: 0.87283348
A5: 一号 | B5: 301 | C5: 137 | D5: 0 | E5: 54 | F5: 3 | G5: 85 | H5: 64 | I5: 0.75294118 | J5: 22 | K5: 0 | L5: 2 | M5: #DIV/0! | N5: 0.0099667774 | O5: 0.36212625 | P5: 15 | Q5: 0.17647059 | R5: #VALUE! | S5: 22194 | T5: #VALUE!
A6: 馒头 | B6: 258 | C6: 144 | D6: 2 | E6: 23 | F6: 2 | G6: 71 | H6: 34 | I6: 0.47887324 | J6: 16 | K6: 32 | L6: 14 | M6: 0.4375 | N6: 0.007751938 | O6: 0.39147287 | P6: 23 | Q6: 0.32394366 | R6: 19163.9 | S6: 24718 | T6: 1.289821
A7: HE | B7: 297 | C7: 224 | D7: 0 | E7: 15 | F7: 1 | G7: 46 | H7: 38 | I7: 0.82608696 | J7: 11 | K7: 42 | L7: 14 | M7: 0.33333333 | N7: 0.0033670034 | O7: 0.23905724 | P7: 8 | Q7: 0.17391304 | R7: 7501.8 | S7: 11219 | T7: 1.4955077
A8: heee | B8: 214 | C8: 0 | D8: 0 | E8: 9 | F8: 4 | G8: 34 | H8: 31 | I8: 0.91176471 | J8: 10 | K8: 29 | L8: 3 | M8: 0.10344828 | N8: 0.018691589 | O8: 0.21962617 | P8: 4 | Q8: 0.11764706 | R8: #N/A | S8: 9238 | T8: #N/A
A9: 六六 | B9: 94 | C9: 17 | D9: 2 | E9: 14 | F9: 24 | G9: 34 | H9: 0 | I9: 0 | J9: 3 | K9: 3 | L9: 2 | M9: 0.66666667 | N9: 0.25531915 | O9: 0.41489362 | P9: 0 | Q9: 0 | R9: 0 | S9: 9459 | T9: 0
A10: 果片 | B10: 207 | C10: 160 | D10: 0 | E10: 5 | F10: 5 | G10: 33 | H10: 29 | I10: 0.87878788 | J10: 4 | K10: 13 | L10: 3 | M10: 0.23076923 | N10: 0.024154589 | O10: 0.19323671 | P10: 7 | Q10: 0.21212121 | R10: 10017.4 | S10: 10351 | T10: 1.0333021
A11: XN | B11: 77 | C11: 63 | D11: 0 | E11: 3 | F11: 4 | G11: 7 | H11: 0 | I11: 0 | J11: 0 | K11: 2 | L11: 0 | M11: 0 | N11: 0.051948052 | O11: 0.090909091 | P11: 0 | Q11: 0 | R11: 0 | S11: 2119 | T11: 0
A14: 起始日期 | B14: 结束日期 | C14: 档期内应发布 | D14: 发布量 | E14: 超时篇数 | F14: 约篇金额 | G14: 发布金额 | H14: 档期内 | I14: 发布率 | J14: 超时率
A15: 46082 | B15: 46091 | C15: 40 | D15: 38 | E15: 2 | F15: 11270 | G15: 9995 | H15: 0 | I15: 0.95 | J15: 0.05
A16: 46092 | B16: 46101 | C16: 296 | D16: 288 | E16: 8 | F16: 67370 | G16: 65194 | H16: 0 | I16: 0.97297297 | J16: 0.027027027
A17: 46101 | B17: 46112 | C17: 273 | D17: 233 | E17: 40 | F17: 67366 | G17: 57663 | H17: 0 | I17: 0.85347985 | J17: 0.14652015
A20: 负责PR | B20: 约片数量
A21: 阿咩 | B21: 35
A22: jing | B22: 14
A23: 一号 | B23: 11
A24: 馒头 | B24: 16
A25: HE | B25: 0
A26: heee | B26: 5
A27: 六六 | B27: 0
A28: 果片 | B28: 0
A29: XN | B29: 0
H33: ·

Sheet 商品成本表
A1: 图片 | B1: 款式编码 | C1: 商品编码 | D1: 商品名称 | E1: 商品简称 | F1: 颜色及规格 | G1: 颜色 | H1: 规格 | I1: 基本售价 | J1: 成本价 | K1: 采购价 | L1: 市场|吊牌价 | M1: 品牌
B2: 2025945 | C2: 2025945-H-L | D2: LENNEA法式小个子设计感减龄黄色连衣裙子女夏季无袖背心花苞短裙 | E2: 无袖花苞长裙 | F2: 黄色;L | G2: 黄色 | H2: L | I2: 188 | J2: 60 | K2: 80 | L2: 255 | M2: LENNEALAB
B3: 2025945 | C3: 2025945-H-M | D3: LENNEA法式小个子设计感减龄黄色连衣裙子女夏季无袖背心花苞短裙 | E3: 无袖花苞长裙 | F3: 黄色;M | G3: 黄色 | H3: M | I3: 188 | J3: 60 | K3: 80 | L3: 255 | M3: LENNEALAB
B4: 2025945 | C4: 2025945-H-S | D4: LENNEA法式小个子设计感减龄黄色连衣裙子女夏季无袖背心花苞短裙 | E4: 无袖花苞长裙 | F4: 黄色;S | G4: 黄色 | H4: S | I4: 188 | J4: 60 | K4: 80 | L4: 255 | M4: LENNEALAB
B5: 2025945 | C5: 2025945-L-L | D5: LENNEA法式小个子设计感减龄黄色连衣裙子女夏季无袖背心花苞短裙 | E5: 无袖花苞长裙 | F5: 蓝色;L | G5: 蓝色 | H5: L | I5: 188 | J5: 60 | K5: 80 | L5: 255 | M5: LENNEALAB
B6: 2025945 | C6: 2025945-L-M | D6: LENNEA法式小个子设计感减龄黄色连衣裙子女夏季无袖背心花苞短裙 | E6: 无袖花苞长裙 | F6: 蓝色;M | G6: 蓝色 | H6: M | I6: 188 | J6: 60 | K6: 80 | L6: 255 | M6: LENNEALAB
B7: 2025945 | C7: 2025945-L-S | D7: LENNEA法式小个子设计感减龄黄色连衣裙子女夏季无袖背心花苞短裙 | E7: 无袖花苞长裙 | F7: 蓝色;S | G7: 蓝色 | H7: S | I7: 188 | J7: 60 | K7: 80 | L7: 255 | M7: LENNEALAB
B8: 2025933 | C8: 2025933-H-L | D8: LENNEAXXXXXXX波点花边长袖 | E8: 波点花边长袖 | F8: 黑色;L | G8: 黑色 | H8: L | I8: 166 | J8: 55 | K8: 70 | L8: 199 | M8: LENNEALAB | N8: 套装要可以关联 生成一个新的款号 然后名字变成波点套装 TZ-2025933-2025317
B9: 2025933 | C9: 2025933-H-M | D9: LENNEAXXXXXXX波点花边长袖 | E9: 波点花边长袖 | F9: 黑色;M | G9: 黑色 | H9: M | I9: 166 | J9: 55 | K9: 70 | L9: 199 | M9: LENNEALAB
B10: 2025933 | C10: 2025933-H-S | D10: LENNEAXXXXXXX波点花边长袖 | E10: 波点花边长袖 | F10: 黑色;S | G10: 黑色 | H10: S | I10: 166 | J10: 55 | K10: 70 | L10: 199 | M10: LENNEALAB
B11: 2025317 | C11: 2025933-B-L | D11: LENNEAXXXXXXX波点中裙 | E11: 波点中裙 | F11: 白色;L | G11: 白色 | H11: L | I11: 155 | J11: 50 | K11: 60 | L11: 185 | M11: LENNEALAB
B12: 2025317 | C12: 2025933-B-M | D12: LENNEAXXXXXXX波点中裙 | E12: 波点中裙 | F12: 白色;M | G12: 白色 | H12: M | I12: 155 | J12: 50 | K12: 60 | L12: 185 | M12: LENNEALAB
B13: 2025317 | C13: 2025933-B-S | D13: LENNEAXXXXXXX波点中裙 | E13: 波点中裙 | F13: 白色;S | G13: 白色 | H13: S | I13: 155 | J13: 50 | K13: 60 | L13: 185 | M13: LENNEALAB

Sheet 博主库
A1: 联系人 | B1: 小红书昵称 | C1: 小红书ID | D1: 邮箱(联系上的可不填) | E1: 微信号 | F1: 报价 | G1: 粉丝量 | H1: 3篇阅读量 | I1: 3篇点赞数 | J1: 3篇收藏数 | K1: 3篇评论数 | L1: 7篇阅读量 | M1: 7篇点赞数 | N1: 7篇收藏数 | O1: 7篇评论数 | P1: 14篇阅读量 | Q1: 14篇点赞数 | R1: 14篇收藏数 | S1: 14篇评论数 | T1: 阅读点赞比（3+7+14的点赞阅读比） | U1: 收藏赞比（同阅读） | V1: 近期数据涨的博主 | W1: 是否假号 | X1: 活跃粉丝数 | Y1: 阅读粉丝数 | Z1: 粉丝画像 | AA1: 粉丝占比 | AB1: 主要年龄 | AC1: 粉丝赞藏比 | AD1: 笔记数 | AE1: 爆文率 | AF1: 3天平均阅读 | AG1: 7天平均阅读 | AH1: 14天平均阅读（14篇阅读量/14） | AI1: 3天平均点赞 | AJ1: 7天平均点赞 | AK1: 14天平均点赞 | AL1: 3天阅读涨跌 | AM1: 7天阅读涨跌 | AN1: 3天点赞涨跌 | AO1: 7天点赞涨跌
A2: jing | B2: 155的瑶瑶阿 | C2: 590366188 | D2: ly516442426@qq.com | G2: 17.90w | H2: 3418 | I2: 221 | J2: 64 | K2: 13 | L2: 4774 | M2: 291 | N2: 82 | O2: 19 | P2: 6632 | Q2: 410 | R2: 118 | S2: 22 | T2: =IF(ISBLANK(Q2),M2/L2,Q2/P2) -> 0.061821472 | U2: =IF(ISBLANK(R2),IF(ISBLANK(N2),J2/I2,N2/M2),R2/Q2) -> 0.28780488 | V2: =IF(AH2=0,"自查",IF(AND(AF2>AH2,AG2>AH2),"涨","波动")) -> 涨 | W2: =IF(T2<=0.1,"否","是") -> 否 | X2: --|-- | Y2: 0.411 | Z2: 女性 | AA2: 0.979 | AB2: 25-34岁|48.4% | AC2: 0.0007025463 | AD2: 113 | AE2: 0.2212 | AF2: =H2/3 -> 1139.3333 | AG2: =L2/7 -> 682 | AH2: =P2/14 -> 473.71429 | AI2: =I2/3 -> 73.666667 | AJ2: =M2/7 -> 41.571429 | AK2: =Q2/14 -> 29.285714 | AL2: =(AF2-AH2)/AH2 -> 1.4051066 | AM2: =(AG2-AH2)/AH2 -> 0.43968637 | AN2: =(AI2-AK2)/AK2 -> 1.5154472 | AO2: =(AJ2-AK2)/AK2 -> 0.4195122
A3: 果片 | B3: 丰腴幼软 | C3: 110027090 | D3: abeedoo@163.com | G3: 16.53w | H3: 11064 | I3: 709 | J3: 246 | K3: 28 | L3: 9757 | M3: 638 | N3: 209 | O3: 30 | P3: 21093 | Q3: 1321 | R3: 480 | S3: 39 | T3: =IF(ISBLANK(Q3),M3/L3,Q3/P3) -> 0.062627412 | U3: =IF(ISBLANK(R3),IF(ISBLANK(N3),J3/I3,N3/M3),R3/Q3) -> 0.36336109 | V3: =IF(AH3=0,"自查",IF(AND(AF3>AH3,AG3>AH3),"涨","波动")) -> 波动 | W3: =IF(T3<=0.1,"否","是") -> 否 | X3: --|-- | Y3: 0.31 | Z3: 女性 | AA3: 0.968 | AB3: 25-34岁|53.2% | AC3: 0.00069675926 | AD3: 20 | AE3: 0.45 | AF3: =H3/3 -> 3688 | AG3: =L3/7 -> 1393.8571 | AH3: =P3/14 -> 1506.6429 | AI3: =I3/3 -> 236.33333 | AJ3: =M3/7 -> 91.142857 | AK3: =Q3/14 -> 94.357143 | AL3: =(AF3-AH3)/AH3 -> 1.4478263 | AM3: =(AG3-AH3)/AH3 -> -0.074858958 | AN3: =(AI3-AK3)/AK3 -> 1.5046682 | AO3: =(AJ3-AK3)/AK3 -> -0.034065102
A4: 果片 | B4: -coin88 | C4: 105625109 | D4: coin88@foxmail.com | G4: 8.12w | H4: 4930 | I4: 287 | J4: 87 | K4: 27 | L4: 4742 | M4: 297 | N4: 85 | O4: 19 | P4: 6207 | Q4: 406 | R4: 111 | S4: 19 | T4: =IF(ISBLANK(Q4),M4/L4,Q4/P4) -> 0.065410021 | U4: =IF(ISBLANK(R4),IF(ISBLANK(N4),J4/I4,N4/M4),R4/Q4) -> 0.27339901 | V4: =IF(AH4=0,"自查",IF(AND(AF4>AH4,AG4>AH4),"涨","波动")) -> 涨 | W4: =IF(T4<=0.1,"否","是") -> 否 | X4: --|-- | Y4: 0.338 | Z4: 女性 | AA4: 0.917 | AB4: 18-24岁|53.8% | AC4: 0.00070023148 | AD4: 42 | AE4: 0.2381 | AF4: =H4/3 -> 1643.3333 | AG4: =L4/7 -> 677.42857 | AH4: =P4/14 -> 443.35714 | AI4: =I4/3 -> 95.666667 | AJ4: =M4/7 -> 42.428571 | AK4: =Q4/14 -> 29 | AL4: =(AF4-AH4)/AH4 -> 2.7065679 | AM4: =(AG4-AH4)/AH4 -> 0.52795231 | AN4: =(AI4-AK4)/AK4 -> 2.2988506 | AO4: =(AJ4-AK4)/AK4 -> 0.46305419
A5: 果片 | B5: 沙琪奶芙 | C5: 6787854426 | D5: 1693199450@qq.com | E5: HaHa120 | G5: 3.88w | H5: 299 | I5: 19 | J5: 6 | K5: 2 | L5: 2643 | M5: 179 | N5: 59 | O5: 5 | P5: 6578 | Q5: 421 | R5: 153 | S5: 11 | T5: =IF(ISBLANK(Q5),M5/L5,Q5/P5) -> 0.064001216 | U5: =IF(ISBLANK(R5),IF(ISBLANK(N5),J5/I5,N5/M5),R5/Q5) -> 0.36342043 | V5: =IF(AH5=0,"自查",IF(AND(AF5>AH5,AG5>AH5),"涨","波动")) -> 波动 | W5: =IF(T5<=0.1,"否","是") -> 否 | X5: --|-- | Y5: 0.407 | Z5: 女性 | AA5: 0.971 | AB5: 18-24岁|55.9% | AC5: 0.00070023148 | AD5: 23 | AE5: 0.2174 | AF5: =H5/3 -> 99.666667 | AG5: =L5/7 -> 377.57143 | AH5: =P5/14 -> 469.85714 | AI5: =I5/3 -> 6.3333333 | AJ5: =M5/7 -> 25.571429 | AK5: =Q5/14 -> 30.071429 | AL5: =(AF5-AH5)/AH5 -> -0.78787879 | AM5: =(AG5-AH5)/AH5 -> -0.19641228 | AN5: =(AI5-AK5)/AK5 -> -0.78939034 | AO5: =(AJ5-AK5)/AK5 -> -0.14964371
A6: XN | B6: D子别买了 | C6: 9430285146 | D6: 137338755@qq.com | G6: 2388 | H6: 9039 | I6: 687 | J6: 187 | K6: 31 | L6: 10694 | M6: 715 | N6: 182 | O6: 37 | P6: 15007 | Q6: 911 | R6: 209 | S6: 49 | T6: =IF(ISBLANK(Q6),M6/L6,Q6/P6) -> 0.060705004 | U6: =IF(ISBLANK(R6),IF(ISBLANK(N6),J6/I6,N6/M6),R6/Q6) -> 0.22941822 | V6: =IF(AH6=0,"自查",IF(AND(AF6>AH6,AG6>AH6),"涨","波动")) -> 涨 | W6: =IF(T6<=0.1,"否","是") -> 否 | X6: 2,346|98.20% | Y6: 0.808 | Z6: 女性 | AA6: 0.577 | AB6: 18-24岁|46.8% | AC6: 0.00079282407 | AD6: 16 | AE6: 0.4375 | AF6: =H6/3 -> 3013 | AG6: =L6/7 -> 1527.7143 | AH6: =P6/14 -> 1071.9286 | AI6: =I6/3 -> 229 | AJ6: =M6/7 -> 102.14286 | AK6: =Q6/14 -> 65.071429 | AL6: =(AF6-AH6)/AH6 -> 1.8108216 | AM6: =(AG6-AH6)/AH6 -> 0.42520157 | AN6: =(AI6-AK6)/AK6 -> 2.5192097 | AO6: =(AJ6-AK6)/AK6 -> 0.56970362
A7: XN | B7: 淡淡的绿 | C7: 512693887 | D7: palegreenbody@yeah.net | G7: 2.14w | H7: 5154 | I7: 401 | J7: 109 | K7: 10 | L7: 5534 | M7: 392 | N7: 111 | O7: 13 | P7: 7153 | Q7: 517 | R7: 147 | S7: 14 | T7: =IF(ISBLANK(Q7),M7/L7,Q7/P7) -> 0.072277366 | U7: =IF(ISBLANK(R7),IF(ISBLANK(N7),J7/I7,N7/M7),R7/Q7) -> 0.28433269 | V7: =IF(AH7=0,"自查",IF(AND(AF7>AH7,AG7>AH7),"涨","波动")) -> 涨 | W7: =IF(T7<=0.1,"否","是") -> 否 | X7: --|-- | Y7: 0.504 | Z7: 女性 | AA7: 0.974 | AB7: 18-24岁|64.6% | AC7: 0.0007037037 | AD7: 22 | AE7: 0.1364 | AF7: =H7/3 -> 1718 | AG7: =L7/7 -> 790.57143 | AH7: =P7/14 -> 510.92857 | AI7: =I7/3 -> 133.66667 | AJ7: =M7/7 -> 56 | AK7: =Q7/14 -> 36.928571 | AL7: =(AF7-AH7)/AH7 -> 2.3625052 | AM7: =(AG7-AH7)/AH7 -> 0.5473228 | AN7: =(AI7-AK7)/AK7 -> 2.6196003 | AO7: =(AJ7-AK7)/AK7 -> 0.51644101
A8: jing | B8: HTG | C8: 152402304 | D8: 1404975999@qq.com | G8: 15.36w | H8: 9482 | I8: 613 | J8: 177 | K8: 36 | L8: 26989 | M8: 1635 | N8: 666 | O8: 51 | P8: 29353 | Q8: 1816 | R8: 719 | S8: 54 | T8: =IF(ISBLANK(Q8),M8/L8,Q8/P8) -> 0.061867611 | U8: =IF(ISBLANK(R8),IF(ISBLANK(N8),J8/I8,N8/M8),R8/Q8) -> 0.39592511 | V8: =IF(AH8=0,"自查",IF(AND(AF8>AH8,AG8>AH8),"涨","波动")) -> 涨 | W8: =IF(T8<=0.1,"否","是") -> 否 | X8: --|-- | Y8: 0.357 | Z8: 女性 | AA8: 0.981 | AB8: 18-24岁|67.2% | AC8: 0.00069907407 | AD8: 36 | AE8: 0.25 | AF8: =H8/3 -> 3160.6667 | AG8: =L8/7 -> 3855.5714 | AH8: =P8/14 -> 2096.6429 | AI8: =I8/3 -> 204.33333 | AJ8: =M8/7 -> 233.57143 | AK8: =Q8/14 -> 129.71429 | AL8: =(AF8-AH8)/AH8 -> 0.5074893 | AM8: =(AG8-AH8)/AH8 -> 0.83892617 | AN8: =(AI8-AK8)/AK8 -> 0.57525698 | AO8: =(AJ8-AK8)/AK8 -> 0.80066079
A9: 果片 | B9: 果仁儿曦 | C9: 534235838 | D9: 745980776@qq.com | E9: wn11197689730 | G9: 14.57w | H9: 3324 | I9: 205 | J9: 77 | K9: 10 | L9: 3269 | M9: 199 | N9: 71 | O9: 13 | P9: 4837 | Q9: 291 | R9: 98 | S9: 19 | T9: =IF(ISBLANK(Q9),M9/L9,Q9/P9) -> 0.060161257 | U9: =IF(ISBLANK(R9),IF(ISBLANK(N9),J9/I9,N9/M9),R9/Q9) -> 0.33676976 | V9: =IF(AH9=0,"自查",IF(AND(AF9>AH9,AG9>AH9),"涨","波动")) -> 涨 | W9: =IF(T9<=0.1,"否","是") -> 否 | X9: 6.57w|45.09% | Y9: 0 | Z9: 女性 | AA9: 0.963 | AB9: 18-24岁|63.0% | AC9: 0.00069560185 | AD9: 23 | AE9: 0 | AF9: =H9/3 -> 1108 | AG9: =L9/7 -> 467 | AH9: =P9/14 -> 345.5 | AI9: =I9/3 -> 68.333333 | AJ9: =M9/7 -> 28.428571 | AK9: =Q9/14 -> 20.785714 | AL9: =(AF9-AH9)/AH9 -> 2.2069465 | AM9: =(AG9-AH9)/AH9 -> 0.35166425 | AN9: =(AI9-AK9)/AK9 -> 2.2875143 | AO9: =(AJ9-AK9)/AK9 -> 0.36769759
A10: XN | B10: 邪恶的00 | C10: 636938894 | D10: cutedoggy@yeah.net | G10: 19.76w | H10: 1963 | I10: 138 | J10: 24 | K10: 10 | L10: 3203 | M10: 235 | N10: 39 | O10: 14 | P10: 3380 | Q10: 251 | R10: 39 | S10: 13 | T10: =IF(ISBLANK(Q10),M10/L10,Q10/P10) -> 0.074260355 | U10: =IF(ISBLANK(R10),IF(ISBLANK(N10),J10/I10,N10/M10),R10/Q10) -> 0.15537849 | V10: =IF(AH10=0,"自查",IF(AND(AF10>AH10,AG10>AH10),"涨","波动")) -> 涨 | W10: =IF(T10<=0.1,"否","是") -> 否 | X10: --|-- | Y10: 0.17 | Z10: 女性 | AA10: 0.831 | AB10: 18-24岁|52.1% | AC10: 0.00069560185 | AD10: 35 | AE10: 0.0286 | AF10: =H10/3 -> 654.33333 | AG10: =L10/7 -> 457.57143 | AH10: =P10/14 -> 241.42857 | AI10: =I10/3 -> 46 | AJ10: =M10/7 -> 33.571429 | AK10: =Q10/14 -> 17.928571 | AL10: =(AF10-AH10)/AH10 -> 1.7102564 | AM10: =(AG10-AH10)/AH10 -> 0.89526627 | AN10: =(AI10-AK10)/AK10 -> 1.5657371 | AO10: =(AJ10-AK10)/AK10 -> 0.87250996
A11: jing | B11: 睡觉了 | C11: 425270944 | D11: 2251253964@qq.com | E11: Z7-23037 | G11: 7.50w | H11: 5618 | I11: 360 | J11: 91 | K11: 18 | L11: 5725 | M11: 361 | N11: 96 | O11: 16 | P11: 14234 | Q11: 1055 | R11: 293 | S11: 25 | T11: =IF(ISBLANK(Q11),M11/L11,Q11/P11) -> 0.074118308 | U11: =IF(ISBLANK(R11),IF(ISBLANK(N11),J11/I11,N11/M11),R11/Q11) -> 0.27772512 | V11: =IF(AH11=0,"自查",IF(AND(AF11>AH11,AG11>AH11),"涨","波动")) -> 波动 | W11: =IF(T11<=0.1,"否","是") -> 否 | X11: --|-- | Y11: 0 | Z11: 女性 | AA11: 0.915 | AB11: 18-24岁|52.0% | AC11: 0.00069907407 | AD11: 20 | AE11: 0.45 | AF11: =H11/3 -> 1872.6667 | AG11: =L11/7 -> 817.85714 | AH11: =P11/14 -> 1016.7143 | AI11: =I11/3 -> 120 | AJ11: =M11/7 -> 51.571429 | AK11: =Q11/14 -> 75.357143 | AL11: =(AF11-AH11)/AH11 -> 0.84188094 | AM11: =(AG11-AH11)/AH11 -> -0.19558803 | AN11: =(AI11-AK11)/AK11 -> 0.59241706 | AO11: =(AJ11-AK11)/AK11 -> -0.31563981
A12: jing | B12: 好甜 | C12: 42703864716 | D12: 844150173@qq.com | G12: 11.63w | H12: 3352 | I12: 216 | J12: 54 | K12: 8 | L12: 12030 | M12: 758 | N12: 269 | O12: 17 | P12: 18306 | Q12: 1135 | R12: 416 | S12: 24 | T12: =IF(ISBLANK(Q12),M12/L12,Q12/P12) -> 0.06200153 | U12: =IF(ISBLANK(R12),IF(ISBLANK(N12),J12/I12,N12/M12),R12/Q12) -> 0.36651982 | V12: =IF(AH12=0,"自查",IF(AND(AF12>AH12,AG12>AH12),"涨","波动")) -> 波动 | W12: =IF(T12<=0.1,"否","是") -> 否 | X12: --|-- | Y12: 0.296 | Z12: 女性 | AA12: 0.984 | AB12: 18-24岁|71.3% | AC12: 0.00070138889 | AD12: 30 | AE12: 0.4333 | AF12: =H12/3 -> 1117.3333 | AG12: =L12/7 -> 1718.5714 | AH12: =P12/14 -> 1307.5714 | AI12: =I12/3 -> 72 | AJ12: =M12/7 -> 108.28571 | AK12: =Q12/14 -> 81.071429 | AL12: =(AF12-AH12)/AH12 -> -0.14548964 | AM12: =(AG12-AH12)/AH12 -> 0.31432317 | AN12: =(AI12-AK12)/AK12 -> -0.11189427 | AO12: =(AJ12-AK12)/AK12 -> 0.33568282
A13: jing | B13: 小朋友 | C13: xiaobudib | D13: 1126534121@qq.com | G13: 5.06w | H13: 7858 | I13: 500 | J13: 166 | K13: 16 | L13: 9541 | M13: 604 | N13: 188 | O13: 14 | P13: 14914 | Q13: 945 | R13: 324 | S13: 17 | T13: =IF(ISBLANK(Q13),M13/L13,Q13/P13) -> 0.063363283 | U13: =IF(ISBLANK(R13),IF(ISBLANK(N13),J13/I13,N13/M13),R13/Q13) -> 0.34285714 | V13: =IF(AH13=0,"自查",IF(AND(AF13>AH13,AG13>AH13),"涨","波动")) -> 涨 | W13: =IF(T13<=0.1,"否","是") -> 否 | X13: --|-- | Y13: 0.111 | Z13: 女性 | AA13: 0.966 | AB13: 18-24岁|64.3% | AC13: 0.00070138889 | AD13: 21 | AE13: 0.2857 | AF13: =H13/3 -> 2619.3333 | AG13: =L13/7 -> 1363 | AH13: =P13/14 -> 1065.2857 | AI13: =I13/3 -> 166.66667 | AJ13: =M13/7 -> 86.285714 | AK13: =Q13/14 -> 67.5 | AL13: =(AF13-AH13)/AH13 -> 1.4588083 | AM13: =(AG13-AH13)/AH13 -> 0.27946896 | AN13: =(AI13-AK13)/AK13 -> 1.4691358 | AO13: =(AJ13-AK13)/AK13 -> 0.27830688
A14: 果片 | B14: 发财小段 | C14: dsl2001 | D14: 2949912425@qq.com | G14: 6100 | H14: 23792 | I14: 1586 | J14: 496 | K14: 31 | L14: 26159 | M14: 1899 | N14: 433 | O14: 33 | T14: =IF(ISBLANK(Q14),M14/L14,Q14/P14) -> 0.072594518 | U14: =IF(ISBLANK(R14),IF(ISBLANK(N14),J14/I14,N14/M14),R14/Q14) -> 0.22801474 | V14: =IF(AH14=0,"自查",IF(AND(AF14>AH14,AG14>AH14),"涨","波动")) -> 自查 | W14: =IF(T14<=0.1,"否","是") -> 否 | X14: --|-- | Y14: 0.273 | Z14: 女性 | AA14: 0.948 | AB14: 18-24岁|57.3% | AC14: 0.00072569444 | AD14: 8 | AE14: 0.25 | AF14: =H14/3 -> 7930.6667 | AG14: =L14/7 -> 3737 | AH14: =P14/14 -> 0 | AI14: =I14/3 -> 528.66667 | AJ14: =M14/7 -> 271.28571 | AK14: =Q14/14 -> 0 | AL14: =(AF14-AH14)/AH14 -> #DIV/0! | AM14: =(AG14-AH14)/AH14 -> #DIV/0! | AN14: =(AI14-AK14)/AK14 -> #DIV/0! | AO14: =(AJ14-AK14)/AK14 -> #DIV/0!
A15: jing | B15: 就是姜子 | C15: 6240978830 | D15: 981010979@qq.com | G15: 1199 | H15: 12558 | I15: 792 | J15: 315 | K15: 18 | L15: 27179 | M15: 2477 | N15: 962 | O15: 28 | T15: =IF(ISBLANK(Q15),M15/L15,Q15/P15) -> 0.091136539 | U15: =IF(ISBLANK(R15),IF(ISBLANK(N15),J15/I15,N15/M15),R15/Q15) -> 0.38837303 | V15: =IF(AH15=0,"自查",IF(AND(AF15>AH15,AG15>AH15),"涨","波动")) -> 自查 | W15: =IF(T15<=0.1,"否","是") -> 否 | X15: 1,199|100% | Y15: 0.964 | Z15: 女性 | AA15: 0.971 | AB15: 18-24岁|62.5% | AC15: 0.00092592593 | AD15: 13 | AE15: 0.3077 | AF15: =H15/3 -> 4186 | AG15: =L15/7 -> 3882.7143 | AH15: =P15/14 -> 0 | AI15: =I15/3 -> 264 | AJ15: =M15/7 -> 353.85714 | AK15: =Q15/14 -> 0 | AL15: =(AF15-AH15)/AH15 -> #DIV/0! | AM15: =(AG15-AH15)/AH15 -> #DIV/0! | AN15: =(AI15-AK15)/AK15 -> #DIV/0! | AO15: =(AJ15-AK15)/AK15 -> #DIV/0!
A16: jing | B16: hetao_ | C16: 4171498179 | D16: 1352783397@qq.com | G16: 1.14w | H16: 3100 | I16: 93 | J16: 20 | K16: 6 | L16: 2690 | M16: 99 | N16: 22 | O16: 7 | P16: 3721 | Q16: 217 | R16: 43 | S16: 10 | T16: =IF(ISBLANK(Q16),M16/L16,Q16/P16) -> 0.058317657 | U16: =IF(ISBLANK(R16),IF(ISBLANK(N16),J16/I16,N16/M16),R16/Q16) -> 0.19815668 | V16: =IF(AH16=0,"自查",IF(AND(AF16>AH16,AG16>AH16),"涨","波动")) -> 涨 | W16: =IF(T16<=0.1,"否","是") -> 否 | X16: 1.09w|95.30% | Y16: 0.605 | Z16: 女性 | AA16: 0.97 | AB16: 18-24岁|53.4% | AC16: 0.0007037037 | AD16: 22 | AE16: 0.0909 | AF16: =H16/3 -> 1033.3333 | AG16: =L16/7 -> 384.28571 | AH16: =P16/14 -> 265.78571 | AI16: =I16/3 -> 31 | AJ16: =M16/7 -> 14.142857 | AK16: =Q16/14 -> 15.5 | AL16: =(AF16-AH16)/AH16 -> 2.8878438 | AM16: =(AG16-AH16)/AH16 -> 0.44584789 | AN16: =(AI16-AK16)/AK16 -> 1 | AO16: =(AJ16-AK16)/AK16 -> -0.087557604
A17: jing | B17: anti函涵 | C17: 1652106912 | D17: 1347736080@qq.com | G17: 3.95w | H17: 1570 | I17: 109 | J17: 22 | K17: 6 | L17: 5961 | M17: 433 | N17: 106 | O17: 11 | P17: 5453 | Q17: 384 | R17: 93 | S17: 15 | T17: =IF(ISBLANK(Q17),M17/L17,Q17/P17) -> 0.070419952 | U17: =IF(ISBLANK(R17),IF(ISBLANK(N17),J17/I17,N17/M17),R17/Q17) -> 0.2421875 | V17: =IF(AH17=0,"自查",IF(AND(AF17>AH17,AG17>AH17),"涨","波动")) -> 涨 | W17: =IF(T17<=0.1,"否","是") -> 否 | X17: 3.53w|89.40% | Y17: 0.3 | Z17: 女性 | AA17: 0.968 | AB17: 18-24岁|60.3% | AC17: 0.0007025463 | AD17: 43 | AE17: 0.093 | AF17: =H17/3 -> 523.33333 | AG17: =L17/7 -> 851.57143 | AH17: =P17/14 -> 389.5 | AI17: =I17/3 -> 36.333333 | AJ17: =M17/7 -> 61.857143 | AK17: =Q17/14 -> 27.428571 | AL17: =(AF17-AH17)/AH17 -> 0.34360291 | AM17: =(AG17-AH17)/AH17 -> 1.1863195 | AN17: =(AI17-AK17)/AK17 -> 0.32465278 | AO17: =(AJ17-AK17)/AK17 -> 1.2552083
A18: XN | B18: Xx. | C18: Starcookies | D18: xinxin01_19@qq.com | G18: 1.03w | H18: 2847 | I18: 246 | J18: 14 | K18: 5 | L18: 2155 | M18: 181 | N18: 13 | O18: 5 | P18: 5202 | Q18: 388 | R18: 63 | S18: 7 | T18: =IF(ISBLANK(Q18),M18/L18,Q18/P18) -> 0.074586697 | U18: =IF(ISBLANK(R18),IF(ISBLANK(N18),J18/I18,N18/M18),R18/Q18) -> 0.16237113 | V18: =IF(AH18=0,"自查",IF(AND(AF18>AH18,AG18>AH18),"涨","波动")) -> 波动 | W18: =IF(T18<=0.1,"否","是") -> 否 | X18: 9,172|89.10% | Y18: 0.433 | Z18: 女性 | AA18: 0.976 | AB18: 18-24岁|60.7% | AC18: 0.00071180556 | AD18: 38 | AE18: 0.0526 | AF18: =H18/3 -> 949 | AG18: =L18/7 -> 307.85714 | AH18: =P18/14 -> 371.57143 | AI18: =I18/3 -> 82 | AJ18: =M18/7 -> 25.857143 | AK18: =Q18/14 -> 27.714286 | AL18: =(AF18-AH18)/AH18 -> 1.5540177 | AM18: =(AG18-AH18)/AH18 -> -0.17147251 | AN18: =(AI18-AK18)/AK18 -> 1.9587629 | AO18: =(AJ18-AK18)/AK18 -> -0.067010309
A19: XN | B19: 久久 | C19: 1643680124 | D19: cq_3336412769@sina.cn | G19: 7.34w | H19: 3055 | I19: 228 | J19: 44 | K19: 5 | L19: 3331 | M19: 262 | N19: 43 | O19: 5 | P19: 8256 | Q19: 665 | R19: 159 | S19: 9 | T19: =IF(ISBLANK(Q19),M19/L19,Q19/P19) -> 0.080547481 | U19: =IF(ISBLANK(R19),IF(ISBLANK(N19),J19/I19,N19/M19),R19/Q19) -> 0.23909774 | V19: =IF(AH19=0,"自查",IF(AND(AF19>AH19,AG19>AH19),"涨","波动")) -> 波动 | W19: =IF(T19<=0.1,"否","是") -> 否 | X19: --|-- | Y19: 0.242 | Z19: 女性 | AA19: 0.897 | AB19: 18-24岁|68.9% | AC19: 0.00069791667 | AD19: 16 | AE19: 0.25 | AF19: =H19/3 -> 1018.3333 | AG19: =L19/7 -> 475.85714 | AH19: =P19/14 -> 589.71429 | AI19: =I19/3 -> 76 | AJ19: =M19/7 -> 37.428571 | AK19: =Q19/14 -> 47.5 | AL19: =(AF19-AH19)/AH19 -> 0.72682494 | AM19: =(AG19-AH19)/AH19 -> -0.19307171 | AN19: =(AI19-AK19)/AK19 -> 0.6 | AO19: =(AJ19-AK19)/AK19 -> -0.21203008
A20: XN | B20: 又又敏 | C20: 620031106 | D20: 1220269116@qq.com | G20: 5.74w | H20: 4457 | I20: 230 | J20: 52 | K20: 17 | L20: 4921 | M20: 266 | N20: 58 | O20: 25 | P20: 6486 | Q20: 389 | R20: 82 | S20: 30 | T20: =IF(ISBLANK(Q20),M20/L20,Q20/P20) -> 0.059975331 | U20: =IF(ISBLANK(R20),IF(ISBLANK(N20),J20/I20,N20/M20),R20/Q20) -> 0.21079692 | V20: =IF(AH20=0,"自查",IF(AND(AF20>AH20,AG20>AH20),"涨","波动")) -> 涨 | W20: =IF(T20<=0.1,"否","是") -> 否 | X20: --|-- | Y20: 0.229 | Z20: 女性 | AA20: 0.957 | AB20: 18-24岁|72.4% | AC20: 0.00069560185 | AD20: 19 | AE20: 0.0526 | AF20: =H20/3 -> 1485.6667 | AG20: =L20/7 -> 703 | AH20: =P20/14 -> 463.28571 | AI20: =I20/3 -> 76.666667 | AJ20: =M20/7 -> 38 | AK20: =Q20/14 -> 27.785714 | AL20: =(AF20-AH20)/AH20 -> 2.2068044 | AM20: =(AG20-AH20)/AH20 -> 0.51742214 | AN20: =(AI20-AK20)/AK20 -> 1.7592117 | AO20: =(AJ20-AK20)/AK20 -> 0.36760925
A21: XN | B21: 一只考拉 | C21: 2982137124 | D21: 2318262804@qq.com | G21: 8159 | H21: 14124 | I21: 1121 | J21: 433 | K21: 22 | T21: =IF(ISBLANK(Q21),IF(ISBLANK(M21),I21/H21,M21/L21),Q21/P21) -> 0.079368451 | U21: =IF(ISBLANK(R21),IF(ISBLANK(N21),J21/I21,N21/M21),R21/Q21) -> 0.38626227 | V21: =IF(AH21=0,"自查",IF(AND(AF21>AH21,AG21>AH21),"涨","波动")) -> 自查 | W21: =IF(T21<=0.1,"否","是") -> 否 | X21: 7,849|96.20% | Y21: 0.313 | Z21: 女性 | AA21: 0.983 | AB21: 18-24岁|70.3% | AC21: 0.00070138889 | AD21: 4 | AE21: 0.5 | AF21: =H21/3 -> 4708 | AG21: =L21/7 -> 0 | AH21: =P21/14 -> 0 | AI21: =I21/3 -> 373.66667 | AJ21: =M21/7 -> 0 | AK21: =Q21/14 -> 0 | AL21: =(AF21-AH21)/AH21 -> #DIV/0! | AM21: =(AG21-AH21)/AH21 -> #DIV/0! | AN21: =(AI21-AK21)/AK21 -> #DIV/0! | AO21: =(AJ21-AK21)/AK21 -> #DIV/0!
A22: XN | B22: quqookicu | C22: quqookicu | D22: quqooooook@163.com | G22: 18.79w | H22: 4910 | I22: 313 | J22: 96 | K22: 20 | L22: 6058 | M22: 399 | N22: 122 | O22: 16 | P22: 8873 | Q22: 581 | R22: 197 | S22: 18 | T22: =IF(ISBLANK(Q22),M22/L22,Q22/P22) -> 0.065479545 | U22: =IF(ISBLANK(R22),IF(ISBLANK(N22),J22/I22,N22/M22),R22/Q22) -> 0.33907057 | V22: =IF(AH22=0,"自查",IF(AND(AF22>AH22,AG22>AH22),"涨","波动")) -> 涨 | W22: =IF(T22<=0.1,"否","是") -> 否 | X22: --|-- | Y22: 0.173 | Z22: 女性 | AA22: 0.978 | AB22: 18-24岁|71.1% | AC22: 0.00069907407 | AD22: 31 | AE22: 0.2581 | AF22: =H22/3 -> 1636.6667 | AG22: =L22/7 -> 865.42857 | AH22: =P22/14 -> 633.78571 | AI22: =I22/3 -> 104.33333 | AJ22: =M22/7 -> 57 | AK22: =Q22/14 -> 41.5 | AL22: =(AF22-AH22)/AH22 -> 1.582366 | AM22: =(AG22-AH22)/AH22 -> 0.36549081 | AN22: =(AI22-AK22)/AK22 -> 1.5140562 | AO22: =(AJ22-AK22)/AK22 -> 0.37349398
A23: XN | B23: 之一 | C23: 971606825 | D23: aa_3336412769@sina.com | G23: 4.92w | H23: 12035 | I23: 856 | J23: 241 | K23: 8 | L23: 18315 | M23: 1312 | N23: 317 | O23: 16 | T23: =IF(ISBLANK(Q23),M23/L23,Q23/P23) -> 0.071635272 | U23: =IF(ISBLANK(R23),IF(ISBLANK(N23),J23/I23,N23/M23),R23/Q23) -> 0.24161585 | V23: =IF(AH23=0,"自查",IF(AND(AF23>AH23,AG23>AH23),"涨","波动")) -> 自查 | W23: =IF(T23<=0.1,"否","是") -> 否 | X23: --|-- | Y23: 0 | Z23: 女性 | AA23: 0.86 | AB23: 18-24岁|58.4% | AC23: 0.0007025463 | AD23: 13 | AE23: 0.4615 | AF23: =H23/3 -> 4011.6667 | AG23: =L23/7 -> 2616.4286 | AH23: =P23/14 -> 0 | AI23: =I23/3 -> 285.33333 | AJ23: =M23/7 -> 187.42857 | AK23: =Q23/14 -> 0 | AL23: =(AF23-AH23)/AH23 -> #DIV/0! | AM23: =(AG23-AH23)/AH23 -> #DIV/0! | AN23: =(AI23-AK23)/AK23 -> #DIV/0! | AO23: =(AJ23-AK23)/AK23 -> #DIV/0!
A24: 果片 | B24: 是PiP鸭 | C24: IPP25899 | D24: 2257074781@qq.com | G24: 11.22w | H24: 40000 | I24: 5221 | J24: 2312 | K24: 50 | L24: 23977 | M24: 2780 | N24: 1134 | O24: 33 | T24: =IF(ISBLANK(Q24),M24/L24,Q24/P24) -> 0.11594445 | U24: =IF(ISBLANK(R24),IF(ISBLANK(N24),J24/I24,N24/M24),R24/Q24) -> 0.40791367 | V24: =IF(AH24=0,"自查",IF(AND(AF24>AH24,AG24>AH24),"涨","波动")) -> 自查 | W24: =IF(T24<=0.1,"否","是") -> 是 | X24: --|-- | Y24: 0.147 | Z24: 女性 | AA24: 0.974 | AB24: 18-24岁|57.6% | AC24: 0.00070023148 | AD24: 12 | AE24: 0.5833 | AF24: =H24/3 -> 13333.333 | AG24: =L24/7 -> 3425.2857 | AH24: =P24/14 -> 0 | AI24: =I24/3 -> 1740.3333 | AJ24: =M24/7 -> 397.14286 | AK24: =Q24/14 -> 0 | AL24: =(AF24-AH24)/AH24 -> #DIV/0! | AM24: =(AG24-AH24)/AH24 -> #DIV/0! | AN24: =(AI24-AK24)/AK24 -> #DIV/0! | AO24: =(AJ24-AK24)/AK24 -> #DIV/0!
A25: 果片 | B25: 小猪胖胖 | C25: 959148789 | D25: pigpp123@qq.com | G25: 10.67w | H25: 11136 | I25: 761 | J25: 214 | K25: 35 | L25: 8589 | M25: 590 | N25: 148 | O25: 27 | P25: 13145 | Q25: 875 | R25: 245 | S25: 34 | T25: =IF(ISBLANK(Q25),M25/L25,Q25/P25) -> 0.066565234 | U25: =IF(ISBLANK(R25),IF(ISBLANK(N25),J25/I25,N25/M25),R25/Q25) -> 0.28 | V25: =IF(AH25=0,"自查",IF(AND(AF25>AH25,AG25>AH25),"涨","波动")) -> 涨 | W25: =IF(T25<=0.1,"否","是") -> 否 | X25: 8.77w|82.20% | Y25: 0.324 | Z25: 女性 | AA25: 0.908 | AB25: 18-24岁|55.8% | AC25: 0.00069907407 | AD25: 23 | AE25: 0.2609 | AF25: =H25/3 -> 3712 | AG25: =L25/7 -> 1227 | AH25: =P25/14 -> 938.92857 | AI25: =I25/3 -> 253.66667 | AJ25: =M25/7 -> 84.285714 | AK25: =Q25/14 -> 62.5 | AL25: =(AF25-AH25)/AH25 -> 2.9534424 | AM25: =(AG25-AH25)/AH25 -> 0.30680867 | AN25: =(AI25-AK25)/AK25 -> 3.0586667 | AO25: =(AJ25-AK25)/AK25 -> 0.34857143
A26: XN | B26: 佼佼牛奶 | C26: JiaoJiaoMilk | E26: JiaoJiaoMilk | G26: 7.60w | H26: 19454 | I26: 1256 | J26: 375 | K26: 65 | L26: 22380 | M26: 1424 | N26: 410 | O26: 79 | T26: =IF(ISBLANK(Q26),M26/L26,Q26/P26) -> 0.063628239 | U26: =IF(ISBLANK(R26),IF(ISBLANK(N26),J26/I26,N26/M26),R26/Q26) -> 0.28792135 | V26: =IF(AH26=0,"自查",IF(AND(AF26>AH26,AG26>AH26),"涨","波动")) -> 自查 | W26: =IF(T26<=0.1,"否","是") -> 否 | X26: 6.28w|82.60% | Y26: 0.098 | Z26: 女性 | AA26: 0.94 | AB26: 18-24岁|66.1% | AC26: 0.00069675926 | AD26: 8 | AE26: 0.5 | AF26: =H26/3 -> 6484.6667 | AG26: =L26/7 -> 3197.1429 | AH26: =P26/14 -> 0 | AI26: =I26/3 -> 418.66667 | AJ26: =M26/7 -> 203.42857 | AK26: =Q26/14 -> 0 | AL26: =(AF26-AH26)/AH26 -> #DIV/0! | AM26: =(AG26-AH26)/AH26 -> #DIV/0! | AN26: =(AI26-AK26)/AK26 -> #DIV/0! | AO26: =(AJ26-AK26)/AK26 -> #DIV/0!
A27: 果片 | B27: 先赚一百万 | C27: 265101203 | D27: 1076422075@qq.com | G27: 4.38w | H27: 629 | I27: 37 | J27: 12 | K27: 5 | L27: 958 | M27: 62 | N27: 16 | O27: 5 | P27: 4787 | Q27: 344 | R27: 96 | S27: 11 | T27: =IF(ISBLANK(Q27),M27/L27,Q27/P27) -> 0.071861291 | U27: =IF(ISBLANK(R27),IF(ISBLANK(N27),J27/I27,N27/M27),R27/Q27) -> 0.27906977 | V27: =IF(AH27=0,"自查",IF(AND(AF27>AH27,AG27>AH27),"涨","波动")) -> 波动 | W27: =IF(T27<=0.1,"否","是") -> 否 | X27: 3.70w|84.50% | Y27: 0.2 | Z27: 女性 | AA27: 0.849 | AB27: 18-24岁|49.4% | AC27: 0.00069791667 | AD27: 27 | AE27: 0.1481 | AF27: =H27/3 -> 209.66667 | AG27: =L27/7 -> 136.85714 | AH27: =P27/14 -> 341.92857 | AI27: =I27/3 -> 12.333333 | AJ27: =M27/7 -> 8.8571429 | AK27: =Q27/14 -> 24.571429 | AL27: =(AF27-AH27)/AH27 -> -0.3868115 | AM27: =(AG27-AH27)/AH27 -> -0.59974932 | AN27: =(AI27-AK27)/AK27 -> -0.49806202 | AO27: =(AJ27-AK27)/AK27 -> -0.63953488
A28: 果片 | B28: 曼妥思二世 | C28: 777948917 | D28: 870977177@qq.com | E28: yxloo33 | G28: 38.88w | H28: 2414 | I28: 133 | J28: 41 | K28: 19 | L28: 3219 | M28: 184 | N28: 60 | O28: 20 | P28: 3999 | Q28: 242 | R28: 77 | S28: 20 | T28: =IF(ISBLANK(Q28),M28/L28,Q28/P28) -> 0.060515129 | U28: =IF(ISBLANK(R28),IF(ISBLANK(N28),J28/I28,N28/M28),R28/Q28) -> 0.31818182 | V28: =IF(AH28=0,"自查",IF(AND(AF28>AH28,AG28>AH28),"涨","波动")) -> 涨 | W28: =IF(T28<=0.1,"否","是") -> 否 | X28: --|-- | Y28: 0.295 | Z28: 女性 | AA28: 0.987 | AB28: 18-24岁|54.9% | AC28: 0.00069444444 | AD28: 31 | AE28: 0 | AF28: =H28/3 -> 804.66667 | AG28: =L28/7 -> 459.85714 | AH28: =P28/14 -> 285.64286 | AI28: =I28/3 -> 44.333333 | AJ28: =M28/7 -> 26.285714 | AK28: =Q28/14 -> 17.285714 | AL28: =(AF28-AH28)/AH28 -> 1.8170376 | AM28: =(AG28-AH28)/AH28 -> 0.60990248 | AN28: =(AI28-AK28)/AK28 -> 1.5647383 | AO28: =(AJ28-AK28)/AK28 -> 0.52066116
A29: 果片 | B29: 吐司椰ye🍞 | C29: 6888556510 | E29: Cliosk_kk | G29: 1313 | H29: 5229 | I29: 414 | J29: 126 | K29: 7 | L29: 4210 | M29: 315 | N29: 99 | O29: 5 | P29: 2623 | Q29: 198 | R29: 64 | S29: 4 | T29: =IF(ISBLANK(Q29),M29/L29,Q29/P29) -> 0.075486085 | U29: =IF(ISBLANK(R29),IF(ISBLANK(N29),J29/I29,N29/M29),R29/Q29) -> 0.32323232 | V29: =IF(AH29=0,"自查",IF(AND(AF29>AH29,AG29>AH29),"涨","波动")) -> 涨 | W29: =IF(T29<=0.1,"否","是") -> 否 | X29: 1,273|96.90% | Y29: 0.799 | Z29: 女性 | AA29: 0.949 | AB29: 18-24岁|54.4% | AC29: 0.00109375 | AD29: 30 | AE29: 0.2667 | AF29: =H29/3 -> 1743 | AG29: =L29/7 -> 601.42857 | AH29: =P29/14 -> 187.35714 | AI29: =I29/3 -> 138 | AJ29: =M29/7 -> 45 | AK29: =Q29/14 -> 14.142857 | AL29: =(AF29-AH29)/AH29 -> 8.3030881 | AM29: =(AG29-AH29)/AH29 -> 2.2100648 | AN29: =(AI29-AK29)/AK29 -> 8.7575758 | AO29: =(AJ29-AK29)/AK29 -> 2.1818182
A30: 果片 | B30: 帕恰小鱼 | C30: 26536693514 | E30: PPYYQX | T30: =IF(ISBLANK(Q30),M30/L30,Q30/P30) -> #DIV/0! | U30: =IF(ISBLANK(R30),IF(ISBLANK(N30),J30/I30,N30/M30),R30/Q30) -> #DIV/0! | V30: =IF(AH30=0,"自查",IF(AND(AF30>AH30,AG30>AH30),"涨","波动")) -> 自查 | W30: =IF(T30<=0.1,"否","是") -> #DIV/0! | AF30: =H30/3 -> 0 | AG30: =L30/7 -> 0 | AH30: =P30/14 -> 0 | AI30: =I30/3 -> 0 | AJ30: =M30/7 -> 0 | AK30: =Q30/14 -> 0 | AL30: =(AF30-AH30)/AH30 -> #DIV/0! | AM30: =(AG30-AH30)/AH30 -> #DIV/0! | AN30: =(AI30-AK30)/AK30 -> #DIV/0! | AO30: =(AJ30-AK30)/AK30 -> #DIV/0!
A31: 果片 | B31: 爱吃蛋糕 | C31: zjf892855902 | D31: xz123470@qq.com | E31: Twang709 | G31: 2984 | H31: 25082 | I31: 2822 | J31: 1040 | K31: 34 | L31: 11934 | M31: 1271 | N31: 468 | O31: 20 | P31: 6905 | Q31: 691 | R31: 248 | S31: 14 | T31: =IF(ISBLANK(Q31),M31/L31,Q31/P31) -> 0.10007241 | U31: =IF(ISBLANK(R31),IF(ISBLANK(N31),J31/I31,N31/M31),R31/Q31) -> 0.35890014 | V31: =IF(AH31=0,"自查",IF(AND(AF31>AH31,AG31>AH31),"涨","波动")) -> 涨 | W31: =IF(T31<=0.1,"否","是") -> 是 | X31: 2,149|72.00% | Y31: 0.288 | Z31: 女性 | AA31: 0.974 | AB31: 18-24岁|59.6% | AC31: 0.00074652778 | AD31: 15 | AE31: 0.0667 | AF31: =H31/3 -> 8360.6667 | AG31: =L31/7 -> 1704.8571 | AH31: =P31/14 -> 493.21429 | AI31: =I31/3 -> 940.66667 | AJ31: =M31/7 -> 181.57143 | AK31: =Q31/14 -> 49.357143 | AL31: =(AF31-AH31)/AH31 -> 15.951388 | AM31: =(AG31-AH31)/AH31 -> 2.4566256 | AN31: =(AI31-AK31)/AK31 -> 18.05837 | AO31: =(AJ31-AK31)/AK31 -> 2.6787265
A32: XN | B32: 懒懒_ | C32: you_you0203 | D32: liuweijianqueen@163.com | G32: 2.15w | H32: 2777 | I32: 189 | J32: 34 | K32: 16 | L32: 3959 | M32: 283 | N32: 41 | O32: 20 | P32: 4634 | Q32: 340 | R32: 47 | S32: 22 | T32: =IF(ISBLANK(Q32),M32/L32,Q32/P32) -> 0.073370738 | U32: =IF(ISBLANK(R32),IF(ISBLANK(N32),J32/I32,N32/M32),R32/Q32) -> 0.13823529 | V32: =IF(AH32=0,"自查",IF(AND(AF32>AH32,AG32>AH32),"涨","波动")) -> 涨 | W32: =IF(T32<=0.1,"否","是") -> 否 | X32: 1.92w|89.30% | Y32: 0.167 | Z32: 女性 | AA32: 0.839 | AB32: 18-24岁|48.6% | AC32: 0.00070023148 | AD32: 25 | AE32: 0 | AF32: =H32/3 -> 925.66667 | AG32: =L32/7 -> 565.57143 | AH32: =P32/14 -> 331 | AI32: =I32/3 -> 63 | AJ32: =M32/7 -> 40.428571 | AK32: =Q32/14 -> 24.285714 | AL32: =(AF32-AH32)/AH32 -> 1.796576 | AM32: =(AG32-AH32)/AH32 -> 0.70867501 | AN32: =(AI32-AK32)/AK32 -> 1.5941176 | AO32: =(AJ32-AK32)/AK32 -> 0.66470588
A33: 阿咩 | B33: 王雨桐 | C33: 602619625 | D33: swhzzx2025@163.com | G33: 1.10w | H33: 1488 | I33: 116 | J33: 7 | K33: 5 | L33: 37430 | M33: 3235 | N33: 156 | O33: 34 | T33: =IF(ISBLANK(Q33),M33/L33,Q33/P33) -> 0.086427999 | U33: =IF(ISBLANK(R33),IF(ISBLANK(N33),J33/I33,N33/M33),R33/Q33) -> 0.048222566 | V33: =IF(AH33=0,"自查",IF(AND(AF33>AH33,AG33>AH33),"涨","波动")) -> 自查 | W33: =IF(T33<=0.1,"否","是") -> 否 | X33: 1.10w|99.40% | Y33: 0.935 | Z33: 女性 | AA33: 0.731 | AB33: 18-24岁|62.6% | AC33: 0.00071990741 | AD33: 8 | AE33: 0.25 | AF33: =H33/3 -> 496 | AG33: =L33/7 -> 5347.1429 | AH33: =P33/14 -> 0 | AI33: =I33/3 -> 38.666667 | AJ33: =M33/7 -> 462.14286 | AK33: =Q33/14 -> 0 | AL33: =(AF33-AH33)/AH33 -> #DIV/0! | AM33: =(AG33-AH33)/AH33 -> #DIV/0! | AN33: =(AI33-AK33)/AK33 -> #DIV/0! | AO33: =(AJ33-AK33)/AK33 -> #DIV/0!
A34: 阿咩 | B34: 一芝 | C34: 747362953 | D34: 651093200@qq.com | G34: 2.91w | H34: 3373 | I34: 236 | J34: 37 | K34: 5 | L34: 5986 | M34: 388 | N34: 82 | O34: 6 | P34: 10415 | Q34: 697 | R34: 150 | S34: 13 | T34: =IF(ISBLANK(Q34),M34/L34,Q34/P34) -> 0.066922708 | U34: =IF(ISBLANK(R34),IF(ISBLANK(N34),J34/I34,N34/M34),R34/Q34) -> 0.21520803 | V34: =IF(AH34=0,"自查",IF(AND(AF34>AH34,AG34>AH34),"涨","波动")) -> 涨 | W34: =IF(T34<=0.1,"否","是") -> 否 | X34: --|-- | Y34: 0.142 | Z34: 男性 | AA34: 0.519 | AB34: 25-34岁|49.3% | AC34: 0.0007025463 | AD34: 22 | AE34: 0.1818 | AF34: =H34/3 -> 1124.3333 | AG34: =L34/7 -> 855.14286 | AH34: =P34/14 -> 743.92857 | AI34: =I34/3 -> 78.666667 | AJ34: =M34/7 -> 55.428571 | AK34: =Q34/14 -> 49.785714 | AL34: =(AF34-AH34)/AH34 -> 0.51134582 | AM34: =(AG34-AH34)/AH34 -> 0.14949592 | AN34: =(AI34-AK34)/AK34 -> 0.58010521 | AO34: =(AJ34-AK34)/AK34 -> 0.1133429
A35: 阿咩 | B35: zrfeiaaaaa | C35: 6540171005 | D35: zrfei966@qq.com | G35: 1.09w | H35: 984 | I35: 55 | J35: 10 | K35: 9 | L35: 1731 | M35: 123 | N35: 28 | O35: 8 | P35: 2256 | Q35: 190 | R35: 36 | S35: 7 | T35: =IF(ISBLANK(Q35),M35/L35,Q35/P35) -> 0.084219858 | U35: =IF(ISBLANK(R35),IF(ISBLANK(N35),J35/I35,N35/M35),R35/Q35) -> 0.18947368 | V35: =IF(AH35=0,"自查",IF(AND(AF35>AH35,AG35>AH35),"涨","波动")) -> 涨 | W35: =IF(T35<=0.1,"否","是") -> 否 | X35: --|-- | Y35: 0.196 | Z35: 男性 | AA35: 0.765 | AB35: 25-34岁|43.8% | AC35: 0.00070138889 | AD35: 21 | AE35: 0.0476 | AF35: =H35/3 -> 328 | AG35: =L35/7 -> 247.28571 | AH35: =P35/14 -> 161.14286 | AI35: =I35/3 -> 18.333333 | AJ35: =M35/7 -> 17.571429 | AK35: =Q35/14 -> 13.571429 | AL35: =(AF35-AH35)/AH35 -> 1.035461 | AM35: =(AG35-AH35)/AH35 -> 0.53457447 | AN35: =(AI35-AK35)/AK35 -> 0.35087719 | AO35: =(AJ35-AK35)/AK35 -> 0.29473684
A36: 阿咩 | B36: 波点稳 | C36: iambodian | D36: 492717850@qq.com | G36: 1.55w | H36: 15334 | I36: 1831 | J36: 210 | K36: 14 | L36: 7831 | M36: 1007 | N36: 118 | O36: 9 | P36: 4974 | Q36: 731 | R36: 85 | S36: 8 | T36: =IF(ISBLANK(Q36),M36/L36,Q36/P36) -> 0.14696421 | U36: =IF(ISBLANK(R36),IF(ISBLANK(N36),J36/I36,N36/M36),R36/Q36) -> 0.11627907 | V36: =IF(AH36=0,"自查",IF(AND(AF36>AH36,AG36>AH36),"涨","波动")) -> 涨 | W36: =IF(T36<=0.1,"否","是") -> 是 | X36: 1.20w|77.70% | Y36: 0.169 | Z36: 女性 | AA36: 0.847 | AB36: 18-24岁|52.7% | AC36: 0.00070486111 | AD36: 17 | AE36: 0.2941 | AF36: =H36/3 -> 5111.3333 | AG36: =L36/7 -> 1118.7143 | AH36: =P36/14 -> 355.28571 | AI36: =I36/3 -> 610.33333 | AJ36: =M36/7 -> 143.85714 | AK36: =Q36/14 -> 52.214286 | AL36: =(AF36-AH36)/AH36 -> 13.386543 | AM36: =(AG36-AH36)/AH36 -> 2.1487736 | AN36: =(AI36-AK36)/AK36 -> 10.68901 | AO36: =(AJ36-AK36)/AK36 -> 1.75513
A37: 阿咩 | B37: 小杜一米五三 | C37: 123005764 | D37: 694647101@qq.com | G37: 1.66w | H37: 638 | I37: 50 | J37: 19 | K37: 5 | L37: 1106 | M37: 63 | N37: 21 | O37: 8 | T37: =IF(ISBLANK(Q37),M37/L37,Q37/P37) -> 0.056962025 | U37: =IF(ISBLANK(R37),IF(ISBLANK(N37),J37/I37,N37/M37),R37/Q37) -> 0.33333333 | V37: =IF(AH37=0,"自查",IF(AND(AF37>AH37,AG37>AH37),"涨","波动")) -> 自查 | W37: =IF(T37<=0.1,"否","是") -> 否 | X37: 1.57w|94.40% | Y37: 0.211 | Z37: 女性 | AA37: 0.981 | AB37: 18-24岁|60.7% | AC37: 0.00069560185 | AD37: 12 | AE37: 0 | AF37: =H37/3 -> 212.66667 | AG37: =L37/7 -> 158 | AH37: =P37/14 -> 0 | AI37: =I37/3 -> 16.666667 | AJ37: =M37/7 -> 9 | AK37: =Q37/14 -> 0 | AL37: =(AF37-AH37)/AH37 -> #DIV/0! | AM37: =(AG37-AH37)/AH37 -> #DIV/0! | AN37: =(AI37-AK37)/AK37 -> #DIV/0! | AO37: =(AJ37-AK37)/AK37 -> #DIV/0!
A38: 阿咩 | B38: UU | C38: 973075668 | D38: wswsm@8155.com | G38: 8516 | H38: 2578 | I38: 222 | J38: 43 | K38: 12 | L38: 2840 | M38: 249 | N38: 47 | O38: 13 | P38: 3132 | Q38: 313 | R38: 60 | S38: 12 | T38: =IF(ISBLANK(Q38),M38/L38,Q38/P38) -> 0.099936143 | U38: =IF(ISBLANK(R38),IF(ISBLANK(N38),J38/I38,N38/M38),R38/Q38) -> 0.19169329 | V38: =IF(AH38=0,"自查",IF(AND(AF38>AH38,AG38>AH38),"涨","波动")) -> 涨 | W38: =IF(T38<=0.1,"否","是") -> 否 | X38: --|-- | Y38: 0.377 | Z38: 女性 | AA38: 0.772 | AB38: 25-34岁|48.9% | AC38: 0.00070138889 | AD38: 14 | AE38: 0 | AF38: =H38/3 -> 859.33333 | AG38: =L38/7 -> 405.71429 | AH38: =P38/14 -> 223.71429 | AI38: =I38/3 -> 74 | AJ38: =M38/7 -> 35.571429 | AK38: =Q38/14 -> 22.357143 | AL38: =(AF38-AH38)/AH38 -> 2.841209 | AM38: =(AG38-AH38)/AH38 -> 0.81353768 | AN38: =(AI38-AK38)/AK38 -> 2.3099042 | AO38: =(AJ38-AK38)/AK38 -> 0.59105431
A39: 阿咩 | B39: 盎司 | C39: 1567249960 | D39: 3920615728@qq.com | G39: 2.95w | H39: 9023 | I39: 1134 | J39: 159 | K39: 27 | T39: =IF(ISBLANK(Q39),M39/L39,Q39/P39) -> #DIV/0! | U39: =IF(ISBLANK(R39),IF(ISBLANK(N39),J39/I39,N39/M39),R39/Q39) -> 0.14021164 | V39: =IF(AH39=0,"自查",IF(AND(AF39>AH39,AG39>AH39),"涨","波动")) -> 自查 | W39: =IF(T39<=0.1,"否","是") -> #DIV/0! | X39: 2.69w|91.30% | Y39: 0.182 | Z39: 男性 | AA39: 0.532 | AB39: 25-34岁|43.5% | AC39: 0.00069675926 | AD39: 5 | AE39: 0.4 | AF39: =H39/3 -> 3007.6667 | AG39: =L39/7 -> 0 | AH39: =P39/14 -> 0 | AI39: =I39/3 -> 378 | AJ39: =M39/7 -> 0 | AK39: =Q39/14 -> 0 | AL39: =(AF39-AH39)/AH39 -> #DIV/0! | AM39: =(AG39-AH39)/AH39 -> #DIV/0! | AN39: =(AI39-AK39)/AK39 -> #DIV/0! | AO39: =(AJ39-AK39)/AK39 -> #DIV/0!
A40: 阿咩 | B40: rima曲扎 | C40: 94198647225 | G40: 6597 | H40: 1090 | I40: 76 | J40: 16 | K40: 1 | L40: 12753 | M40: 835 | N40: 358 | O40: 9 | T40: =IF(ISBLANK(Q40),M40/L40,Q40/P40) -> 0.06547479 | U40: =IF(ISBLANK(R40),IF(ISBLANK(N40),J40/I40,N40/M40),R40/Q40) -> 0.42874251 | V40: =IF(AH40=0,"自查",IF(AND(AF40>AH40,AG40>AH40),"涨","波动")) -> 自查 | W40: =IF(T40<=0.1,"否","是") -> 否 | X40: 6,591|99.90% | Y40: 0.959 | Z40: 女性 | AA40: 0.866 | AB40: 25-34岁|50.1% | AC40: 0.00070833333 | AD40: 7 | AE40: 0.2857 | AF40: =H40/3 -> 363.33333 | AG40: =L40/7 -> 1821.8571 | AH40: =P40/14 -> 0 | AI40: =I40/3 -> 25.333333 | AJ40: =M40/7 -> 119.28571 | AK40: =Q40/14 -> 0 | AL40: =(AF40-AH40)/AH40 -> #DIV/0! | AM40: =(AG40-AH40)/AH40 -> #DIV/0! | AN40: =(AI40-AK40)/AK40 -> #DIV/0! | AO40: =(AJ40-AK40)/AK40 -> #DIV/0!
A41: 阿咩 | B41: zrfeiaaaaa | C41: 6540171005 | D41: zrfei966@qq.com | G41: 1.09w | H41: 984 | I41: 55 | J41: 10 | K41: 9 | L41: 1731 | M41: 123 | N41: 28 | O41: 8 | T41: =IF(ISBLANK(Q41),M41/L41,Q41/P41) -> 0.071057192 | U41: =IF(ISBLANK(R41),IF(ISBLANK(N41),J41/I41,N41/M41),R41/Q41) -> 0.22764228 | V41: =IF(AH41=0,"自查",IF(AND(AF41>AH41,AG41>AH41),"涨","波动")) -> 自查 | W41: =IF(T41<=0.1,"否","是") -> 否 | X41: --|-- | Y41: 0.196 | Z41: 男性 | AA41: 0.765 | AB41: 25-34岁|43.8% | AC41: 0.00070138889 | AD41: 21 | AE41: 0.0476 | AF41: =H41/3 -> 328 | AG41: =L41/7 -> 247.28571 | AH41: =P41/14 -> 0 | AI41: =I41/3 -> 18.333333 | AJ41: =M41/7 -> 17.571429 | AK41: =Q41/14 -> 0 | AL41: =(AF41-AH41)/AH41 -> #DIV/0! | AM41: =(AG41-AH41)/AH41 -> #DIV/0! | AN41: =(AI41-AK41)/AK41 -> #DIV/0! | AO41: =(AJ41-AK41)/AK41 -> #DIV/0!
A42: 阿咩 | B42: Selennna | C42: itselenaxx | D42: itselenaxx@qq.com | G42: 2.68w | H42: 2718 | I42: 189 | J42: 20 | K42: 16 | L42: 13140 | M42: 1062 | N42: 103 | O42: 26 | T42: =IF(ISBLANK(Q42),M42/L42,Q42/P42) -> 0.080821918 | U42: =IF(ISBLANK(R42),IF(ISBLANK(N42),J42/I42,N42/M42),R42/Q42) -> 0.096986817 | V42: =IF(AH42=0,"自查",IF(AND(AF42>AH42,AG42>AH42),"涨","波动")) -> 自查 | W42: =IF(T42<=0.1,"否","是") -> 否 | X42: --|-- | Y42: 0.199 | Z42: 女性 | AA42: 0.813 | AB42: 18-24岁|64.9% | AC42: 0.00069791667 | AD42: 7 | AE42: 0.2857 | AF42: =H42/3 -> 906 | AG42: =L42/7 -> 1877.1429 | AH42: =P42/14 -> 0 | AI42: =I42/3 -> 63 | AJ42: =M42/7 -> 151.71429 | AK42: =Q42/14 -> 0 | AL42: =(AF42-AH42)/AH42 -> #DIV/0! | AM42: =(AG42-AH42)/AH42 -> #DIV/0! | AN42: =(AI42-AK42)/AK42 -> #DIV/0! | AO42: =(AJ42-AK42)/AK42 -> #DIV/0!
A43: 阿咩 | B43: 黑边角色 | C43: 6666668S | E43: Blushhaunt | G43: 2.32w | H43: 1385 | I43: 61 | J43: 5 | K43: 4 | L43: 6196 | M43: 581 | N43: 60 | O43: 8 | P43: 5596 | Q43: 484 | R43: 62 | S43: 8 | T43: =IF(ISBLANK(Q43),M43/L43,Q43/P43) -> 0.08649035 | U43: =IF(ISBLANK(R43),IF(ISBLANK(N43),J43/I43,N43/M43),R43/Q43) -> 0.12809917 | V43: =IF(AH43=0,"自查",IF(AND(AF43>AH43,AG43>AH43),"涨","波动")) -> 涨 | W43: =IF(T43<=0.1,"否","是") -> 否 | X43: --|-- | Y43: 0.228 | Z43: 女性 | AA43: 0.745 | AB43: 18-24岁|54.3% | AC43: 0.00069791667 | AD43: 16 | AE43: 0.1875 | AF43: =H43/3 -> 461.66667 | AG43: =L43/7 -> 885.14286 | AH43: =P43/14 -> 399.71429 | AI43: =I43/3 -> 20.333333 | AJ43: =M43/7 -> 83 | AK43: =Q43/14 -> 34.571429 | AL43: =(AF43-AH43)/AH43 -> 0.15499166 | AM43: =(AG43-AH43)/AH43 -> 1.2144389 | AN43: =(AI43-AK43)/AK43 -> -0.41184573 | AO43: =(AJ43-AK43)/AK43 -> 1.4008264
A44: 阿咩 | B44: Zora | C44: 303180124 | D44: 2788678902@qq.com | G44: 9073 | H44: 1153 | I44: 139 | J44: 16 | K44: 11 | L44: 1809 | M44: 194 | N44: 28 | O44: 8 | P44: 1797 | Q44: 161 | R44: 24 | S44: 8 | T44: =IF(ISBLANK(Q44),M44/L44,Q44/P44) -> 0.089593767 | U44: =IF(ISBLANK(R44),IF(ISBLANK(N44),J44/I44,N44/M44),R44/Q44) -> 0.14906832 | V44: =IF(AH44=0,"自查",IF(AND(AF44>AH44,AG44>AH44),"涨","波动")) -> 涨 | W44: =IF(T44<=0.1,"否","是") -> 否 | X44: 8,257|91.00% | Y44: 0.44 | Z44: 女性 | AA44: 0.65 | AB44: 18-24岁|53.3% | AC44: 0.00070138889 | AD44: 20 | AE44: 0 | AF44: =H44/3 -> 384.33333 | AG44: =L44/7 -> 258.42857 | AH44: =P44/14 -> 128.35714 | AI44: =I44/3 -> 46.333333 | AJ44: =M44/7 -> 27.714286 | AK44: =Q44/14 -> 11.5 | AL44: =(AF44-AH44)/AH44 -> 1.9942497 | AM44: =(AG44-AH44)/AH44 -> 1.0133556 | AN44: =(AI44-AK44)/AK44 -> 3.0289855 | AO44: =(AJ44-AK44)/AK44 -> 1.4099379
A45: 阿咩 | B45: anmongsil | C45: anmongsil_ | D45: anmon9sil@icloud.com | G45: 1.55w | H45: 3127 | I45: 264 | J45: 18 | K45: 5 | L45: 2480 | M45: 210 | N45: 12 | O45: 6 | T45: =IF(ISBLANK(Q45),M45/L45,Q45/P45) -> 0.084677419 | U45: =IF(ISBLANK(R45),IF(ISBLANK(N45),J45/I45,N45/M45),R45/Q45) -> 0.057142857 | V45: =IF(AH45=0,"自查",IF(AND(AF45>AH45,AG45>AH45),"涨","波动")) -> 自查 | W45: =IF(T45<=0.1,"否","是") -> 否 | X45: 320|2.06% | Y45: 0 | Z45: 女性 | AA45: 0.84 | AB45: 18-24岁|64.8% | AC45: 0.00070023148 | AD45: 11 | AE45: 0.0909 | AF45: =H45/3 -> 1042.3333 | AG45: =L45/7 -> 354.28571 | AH45: =P45/14 -> 0 | AI45: =I45/3 -> 88 | AJ45: =M45/7 -> 30 | AK45: =Q45/14 -> 0 | AL45: =(AF45-AH45)/AH45 -> #DIV/0! | AM45: =(AG45-AH45)/AH45 -> #DIV/0! | AN45: =(AI45-AK45)/AK45 -> #DIV/0! | AO45: =(AJ45-AK45)/AK45 -> #DIV/0!
A46: 阿咩 | B46: 橙子好好吃 | C46: fann1226 | D46: 1983725759@qq.com | G46: 2.48w | H46: 4486 | I46: 331 | J46: 27 | K46: 23 | L46: 5412 | M46: 434 | N46: 25 | O46: 23 | T46: =IF(ISBLANK(Q46),M46/L46,Q46/P46) -> 0.080192166 | U46: =IF(ISBLANK(R46),IF(ISBLANK(N46),J46/I46,N46/M46),R46/Q46) -> 0.057603687 | V46: =IF(AH46=0,"自查",IF(AND(AF46>AH46,AG46>AH46),"涨","波动")) -> 自查 | W46: =IF(T46<=0.1,"否","是") -> 否 | X46: --|-- | Y46: 0.36 | Z46: 女性 | AA46: 0.865 | AB46: 18-24岁|68.4% | AC46: 0.00069907407 | AD46: 13 | AE46: 0.0769 | AF46: =H46/3 -> 1495.3333 | AG46: =L46/7 -> 773.14286 | AH46: =P46/14 -> 0 | AI46: =I46/3 -> 110.33333 | AJ46: =M46/7 -> 62 | AK46: =Q46/14 -> 0 | AL46: =(AF46-AH46)/AH46 -> #DIV/0! | AM46: =(AG46-AH46)/AH46 -> #DIV/0! | AN46: =(AI46-AK46)/AK46 -> #DIV/0! | AO46: =(AJ46-AK46)/AK46 -> #DIV/0!
A47: 阿咩 | B47: 雅雯赵 | C47: 753104821 | D47: 402019713@qq.com | G47: 2.69w | H47: 2063 | I47: 110 | J47: 21 | K47: 19 | L47: 1862 | M47: 100 | N47: 17 | O47: 18 | T47: =IF(ISBLANK(Q47),M47/L47,Q47/P47) -> 0.053705693 | U47: =IF(ISBLANK(R47),IF(ISBLANK(N47),J47/I47,N47/M47),R47/Q47) -> 0.17 | V47: =IF(AH47=0,"自查",IF(AND(AF47>AH47,AG47>AH47),"涨","波动")) -> 自查 | W47: =IF(T47<=0.1,"否","是") -> 否 | X47: --|-- | Y47: 0 | Z47: 女性 | AA47: 0.94 | AB47: 25-34岁|63.7% | AC47: 0.00069560185 | AD47: 12 | AE47: 0 | AF47: =H47/3 -> 687.66667 | AG47: =L47/7 -> 266 | AH47: =P47/14 -> 0 | AI47: =I47/3 -> 36.666667 | AJ47: =M47/7 -> 14.285714 | AK47: =Q47/14 -> 0 | AL47: =(AF47-AH47)/AH47 -> #DIV/0! | AM47: =(AG47-AH47)/AH47 -> #DIV/0! | AN47: =(AI47-AK47)/AK47 -> #DIV/0! | AO47: =(AJ47-AK47)/AK47 -> #DIV/0!
A48: 阿咩 | B48: kiwi | C48: 1086718143 | D48: 756754278@qq.com | G48: 8.12w | H48: 14688 | I48: 1107 | J48: 146 | K48: 22 | L48: 17864 | M48: 1270 | N48: 213 | O48: 23 | P48: 14898 | Q48: 1351 | R48: 228 | S48: 26 | T48: =IF(ISBLANK(Q48),M48/L48,Q48/P48) -> 0.090683313 | U48: =IF(ISBLANK(R48),IF(ISBLANK(N48),J48/I48,N48/M48),R48/Q48) -> 0.16876388 | V48: =IF(AH48=0,"自查",IF(AND(AF48>AH48,AG48>AH48),"涨","波动")) -> 涨 | W48: =IF(T48<=0.1,"否","是") -> 否 | X48: 6.91w|85.10% | Y48: 0.336 | Z48: 女性 | AA48: 0.774 | AB48: 18-24岁|44.5% | AC48: 0.00069791667 | AD48: 15 | AE48: 0.4 | AF48: =H48/3 -> 4896 | AG48: =L48/7 -> 2552 | AH48: =P48/14 -> 1064.1429 | AI48: =I48/3 -> 369 | AJ48: =M48/7 -> 181.42857 | AK48: =Q48/14 -> 96.5 | AL48: =(AF48-AH48)/AH48 -> 3.600886 | AM48: =(AG48-AH48)/AH48 -> 1.3981743 | AN48: =(AI48-AK48)/AK48 -> 2.8238342 | AO48: =(AJ48-AK48)/AK48 -> 0.88008882
A49: 果片 | B49: Losely3 | C49: 7158380957 | E49: Losely3 | G49: 104 | H49: 6778 | I49: 423 | J49: 117 | K49: 15 | L49: 3721 | M49: 230 | N49: 61 | O49: 12 | T49: =IF(ISBLANK(Q49),M49/L49,Q49/P49) -> 0.061811341 | U49: =IF(ISBLANK(R49),IF(ISBLANK(N49),J49/I49,N49/M49),R49/Q49) -> 0.26521739 | V49: =IF(AH49=0,"自查",IF(AND(AF49>AH49,AG49>AH49),"涨","波动")) -> 自查 | W49: =IF(T49<=0.1,"否","是") -> 否 | X49: --|-- | Y49: -- | Z49: |-- | AA49: --|-- | AB49: 0 | AC49: 0.0009212963 | AD49: 7 | AE49: 0.1429 | AF49: =H49/3 -> 2259.3333 | AG49: =L49/7 -> 531.57143 | AH49: =P49/14 -> 0 | AI49: =I49/3 -> 141 | AJ49: =M49/7 -> 32.857143 | AK49: =Q49/14 -> 0 | AL49: =(AF49-AH49)/AH49 -> #DIV/0! | AM49: =(AG49-AH49)/AH49 -> #DIV/0! | AN49: =(AI49-AK49)/AK49 -> #DIV/0! | AO49: =(AJ49-AK49)/AK49 -> #DIV/0!
A50: 果片 | B50: 呼叫林林 | C50: 2074834862 | E50: xaqemm | G50: 6400 | H50: 2368 | I50: 135 | J50: 48 | K50: 15 | L50: 1909 | M50: 173 | N50: 63 | O50: 14 | P50: 4244 | Q50: 516 | R50: 185 | S50: 19 | T50: =IF(ISBLANK(Q50),M50/L50,Q50/P50) -> 0.12158341 | U50: =IF(ISBLANK(R50),IF(ISBLANK(N50),J50/I50,N50/M50),R50/Q50) -> 0.35852713 | V50: =IF(AH50=0,"自查",IF(AND(AF50>AH50,AG50>AH50),"涨","波动")) -> 波动 | W50: =IF(T50<=0.1,"否","是") -> 是 | X50: 6,010|93.90% | Y50: 0.707 | Z50: 女性 | AA50: 0.931 | AB50: 18-24岁|58.6% | AC50: 0.00095138889 | AD50: 66 | AE50: 0.3939 | AF50: =H50/3 -> 789.33333 | AG50: =L50/7 -> 272.71429 | AH50: =P50/14 -> 303.14286 | AI50: =I50/3 -> 45 | AJ50: =M50/7 -> 24.714286 | AK50: =Q50/14 -> 36.857143 | AL50: =(AF50-AH50)/AH50 -> 1.6038329 | AM50: =(AG50-AH50)/AH50 -> -0.100377 | AN50: =(AI50-AK50)/AK50 -> 0.22093023 | AO50: =(AJ50-AK50)/AK50 -> -0.32945736
A51: 果片 | B51: 月月不亮🌙 | C51: 9635265582 | D51: 2326291306@qq.com | G51: 3.02w | H51: 1026 | I51: 65 | J51: 26 | K51: 2 | L51: 1845 | M51: 117 | N51: 51 | O51: 4 | P51: 3296 | Q51: 203 | R51: 91 | S51: 6 | T51: =IF(ISBLANK(Q51),M51/L51,Q51/P51) -> 0.061589806 | U51: =IF(ISBLANK(R51),IF(ISBLANK(N51),J51/I51,N51/M51),R51/Q51) -> 0.44827586 | V51: =IF(AH51=0,"自查",IF(AND(AF51>AH51,AG51>AH51),"涨","波动")) -> 涨 | W51: =IF(T51<=0.1,"否","是") -> 否 | X51: --|-- | Y51: 0.325 | Z51: 女性 | AA51: 0.853 | AB51: 25-34岁|46.3% | AC51: 0.00070138889 | AD51: 42 | AE51: 0.0476 | AF51: =H51/3 -> 342 | AG51: =L51/7 -> 263.57143 | AH51: =P51/14 -> 235.42857 | AI51: =I51/3 -> 21.666667 | AJ51: =M51/7 -> 16.714286 | AK51: =Q51/14 -> 14.5 | AL51: =(AF51-AH51)/AH51 -> 0.4526699 | AM51: =(AG51-AH51)/AH51 -> 0.11953883 | AN51: =(AI51-AK51)/AK51 -> 0.49425287 | AO51: =(AJ51-AK51)/AK51 -> 0.15270936
A52: 果片 | B52: 小猫碎冰冰～ | C52: o3omary3 | D52: 3116577108@qq.com | G52: 2.31w | H52: 1854 | I52: 142 | J52: 22 | K52: 7 | L52: 2588 | M52: 207 | N52: 28 | O52: 8 | P52: 3861 | Q52: 308 | R52: 45 | S52: 9 | T52: =IF(ISBLANK(Q52),M52/L52,Q52/P52) -> 0.07977208 | U52: =IF(ISBLANK(R52),IF(ISBLANK(N52),J52/I52,N52/M52),R52/Q52) -> 0.1461039 | V52: =IF(AH52=0,"自查",IF(AND(AF52>AH52,AG52>AH52),"涨","波动")) -> 涨 | W52: =IF(T52<=0.1,"否","是") -> 否 | X52: 1.87w|80.90% | Y52: 0.263 | Z52: 男性 | AA52: 0.88 | AB52: 25-34岁|78.9% | AC52: 0.00069907407 | AD52: 24 | AE52: 0 | AF52: =H52/3 -> 618 | AG52: =L52/7 -> 369.71429 | AH52: =P52/14 -> 275.78571 | AI52: =I52/3 -> 47.333333 | AJ52: =M52/7 -> 29.571429 | AK52: =Q52/14 -> 22 | AL52: =(AF52-AH52)/AH52 -> 1.2408702 | AM52: =(AG52-AH52)/AH52 -> 0.34058534 | AN52: =(AI52-AK52)/AK52 -> 1.1515152 | AO52: =(AJ52-AK52)/AK52 -> 0.34415584
A53: 果片 | B53: 今天没有吃早餐 | C53: wxt123123 | D53: tongdadasiv@qq.com | G53: 3.31w | H53: 4997 | I53: 410 | J53: 67 | K53: 5 | L53: 3160 | M53: 255 | N53: 43 | O53: 5 | P53: 3071 | Q53: 267 | R53: 42 | S53: 6 | T53: =IF(ISBLANK(Q53),M53/L53,Q53/P53) -> 0.086942364 | U53: =IF(ISBLANK(R53),IF(ISBLANK(N53),J53/I53,N53/M53),R53/Q53) -> 0.15730337 | V53: =IF(AH53=0,"自查",IF(AND(AF53>AH53,AG53>AH53),"涨","波动")) -> 涨 | W53: =IF(T53<=0.1,"否","是") -> 否 | X53: 2.13w|64.30% | Y53: 0.111 | Z53: 女性 | AA53: 0.631 | AB53: 18-24岁|57.9% | AC53: 0.00069675926 | AD53: 18 | AE53: 0.1111 | AF53: =H53/3 -> 1665.6667 | AG53: =L53/7 -> 451.42857 | AH53: =P53/14 -> 219.35714 | AI53: =I53/3 -> 136.66667 | AJ53: =M53/7 -> 36.428571 | AK53: =Q53/14 -> 19.071429 | AL53: =(AF53-AH53)/AH53 -> 6.5934006 | AM53: =(AG53-AH53)/AH53 -> 1.0579616 | AN53: =(AI53-AK53)/AK53 -> 6.1660424 | AO53: =(AJ53-AK53)/AK53 -> 0.91011236
A54: 馒头 | B54: 蜡 | C54: y1127_617 | D54: 2399923059@qq.com | G54: 12.59w | H54: 1889 | I54: 102 | J54: 31 | K54: 15 | L54: 3762 | M54: 231 | N54: 68 | O54: 19 | P54: 6187 | Q54: 389 | R54: 117 | S54: 23 | T54: =IF(ISBLANK(Q54),M54/L54,Q54/P54) -> 0.062873768 | U54: =IF(ISBLANK(R54),IF(ISBLANK(N54),J54/I54,N54/M54),R54/Q54) -> 0.30077121 | V54: =IF(AH54=0,"自查",IF(AND(AF54>AH54,AG54>AH54),"涨","波动")) -> 涨 | W54: =IF(T54<=0.1,"否","是") -> 否 | X54: --|-- | Y54: 0.158 | Z54: 女性 | AA54: 0.892 | AB54: 18-24岁|70.3% | AC54: 0 | AD54: 0 | AE54: 0 | AF54: =H54/3 -> 629.66667 | AG54: =L54/7 -> 537.42857 | AH54: =P54/14 -> 441.92857 | AI54: =I54/3 -> 34 | AJ54: =M54/7 -> 33 | AK54: =Q54/14 -> 27.785714 | AL54: =(AF54-AH54)/AH54 -> 0.42481547 | AM54: =(AG54-AH54)/AH54 -> 0.21609827 | AN54: =(AI54-AK54)/AK54 -> 0.22365039 | AO54: =(AJ54-AK54)/AK54 -> 0.18766067
A55: 阿咩 | B55: 小橙别吃了 | C55: 1108214757 | D55: 2125936615@qq.com | G55: 1.55w | H55: 498 | I55: 73 | J55: 10 | K55: 4 | L55: 1527 | M55: 203 | N55: 32 | O55: 4 | P55: 5372 | Q55: 836 | R55: 122 | S55: 9 | T55: =IF(ISBLANK(Q55),M55/L55,Q55/P55) -> 0.15562174 | U55: =IF(ISBLANK(R55),IF(ISBLANK(N55),J55/I55,N55/M55),R55/Q55) -> 0.14593301 | V55: =IF(AH55=0,"自查",IF(AND(AF55>AH55,AG55>AH55),"涨","波动")) -> 波动 | W55: =IF(T55<=0.1,"否","是") -> 是 | X55: --|-- | Y55: 0.187 | Z55: 女性 | AA55: 0.773 | AB55: 18-24岁|66.0% | AC55: 0.00070486111 | AD55: 14 | AE55: 0.2143 | AF55: =H55/3 -> 166 | AG55: =L55/7 -> 218.14286 | AH55: =P55/14 -> 383.71429 | AI55: =I55/3 -> 24.333333 | AJ55: =M55/7 -> 29 | AK55: =Q55/14 -> 59.714286 | AL55: =(AF55-AH55)/AH55 -> -0.56738645 | AM55: =(AG55-AH55)/AH55 -> -0.43149665 | AN55: =(AI55-AK55)/AK55 -> -0.59250399 | AO55: =(AJ55-AK55)/AK55 -> -0.51435407
A56: 阿咩 | B56: 亲亲 | C56: zhenzhen21 | E56: Oiiinzien | G56: 716 | H56: 4179 | I56: 345 | J56: 35 | K56: 7 | L56: 3156 | M56: 256 | N56: 28 | O56: 8 | T56: =IF(ISBLANK(Q56),M56/L56,Q56/P56) -> 0.081115336 | U56: =IF(ISBLANK(R56),IF(ISBLANK(N56),J56/I56,N56/M56),R56/Q56) -> 0.109375 | V56: =IF(AH56=0,"自查",IF(AND(AF56>AH56,AG56>AH56),"涨","波动")) -> 自查 | W56: =IF(T56<=0.1,"否","是") -> 否 | X56: --|-- | Y56: -- | Z56: |-- | AA56: --|-- | AB56: 0 | AC56: 0.00073148148 | AD56: 10 | AE56: 0 | AF56: =H56/3 -> 1393 | AG56: =L56/7 -> 450.85714 | AH56: =P56/14 -> 0 | AI56: =I56/3 -> 115 | AJ56: =M56/7 -> 36.571429 | AK56: =Q56/14 -> 0 | AL56: =(AF56-AH56)/AH56 -> #DIV/0! | AM56: =(AG56-AH56)/AH56 -> #DIV/0! | AN56: =(AI56-AK56)/AK56 -> #DIV/0! | AO56: =(AJ56-AK56)/AK56 -> #DIV/0!
A57: 阿咩 | B57: 值小妹 | C57: cerasus02 | D57: 978413875@qq.com | G57: 1.02w | H57: 671 | I57: 56 | J57: 7 | K57: 1 | T57: =IF(ISBLANK(Q57),M57/L57,Q57/P57) -> #DIV/0! | U57: =IF(ISBLANK(R57),IF(ISBLANK(N57),J57/I57,N57/M57),R57/Q57) -> 0.125 | V57: =IF(AH57=0,"自查",IF(AND(AF57>AH57,AG57>AH57),"涨","波动")) -> 自查 | W57: =IF(T57<=0.1,"否","是") -> #DIV/0! | X57: 4,059|39.66% | Y57: 0 | Z57: 男性 | AA57: 0.608 | AB57: 18-24岁|42.1% | AC57: 0 | AD57: 0 | AE57: 0 | AF57: =H57/3 -> 223.66667 | AG57: =L57/7 -> 0 | AH57: =P57/14 -> 0 | AI57: =I57/3 -> 18.666667 | AJ57: =M57/7 -> 0 | AK57: =Q57/14 -> 0 | AL57: =(AF57-AH57)/AH57 -> #DIV/0! | AM57: =(AG57-AH57)/AH57 -> #DIV/0! | AN57: =(AI57-AK57)/AK57 -> #DIV/0! | AO57: =(AJ57-AK57)/AK57 -> #DIV/0!
A58: 阿咩 | B58: 宅宅 | C58: JenC3QWQ | D58: 1135041305@qq.com | G58: 1.13w | H58: 5944 | I58: 663 | J58: 81 | K58: 26 | L58: 3544 | M58: 424 | N58: 52 | O58: 22 | P58: 3908 | Q58: 364 | R58: 46 | S58: 22 | T58: =IF(ISBLANK(Q58),M58/L58,Q58/P58) -> 0.093142272 | U58: =IF(ISBLANK(R58),IF(ISBLANK(N58),J58/I58,N58/M58),R58/Q58) -> 0.12637363 | V58: =IF(AH58=0,"自查",IF(AND(AF58>AH58,AG58>AH58),"涨","波动")) -> 涨 | W58: =IF(T58<=0.1,"否","是") -> 否 | X58: --|-- | Y58: 0.313 | Z58: 女性 | AA58: 0.868 | AB58: 18-24岁|62.7% | AC58: 0.00070138889 | AD58: 16 | AE58: 0.0625 | AF58: =H58/3 -> 1981.3333 | AG58: =L58/7 -> 506.28571 | AH58: =P58/14 -> 279.14286 | AI58: =I58/3 -> 221 | AJ58: =M58/7 -> 60.571429 | AK58: =Q58/14 -> 26 | AL58: =(AF58-AH58)/AH58 -> 6.0979188 | AM58: =(AG58-AH58)/AH58 -> 0.81371546 | AN58: =(AI58-AK58)/AK58 -> 7.5 | AO58: =(AJ58-AK58)/AK58 -> 1.3296703
A59: 阿咩 | B59: w | C59: 5095532582 | D59: 807553596@qq.com | G59: 4.30w | H59: 3738 | I59: 209 | J59: 57 | K59: 24 | L59: 8137 | M59: 481 | N59: 160 | O59: 29 | P59: 8149 | Q59: 507 | R59: 155 | S59: 26 | T59: =IF(ISBLANK(Q59),M59/L59,Q59/P59) -> 0.062216223 | U59: =IF(ISBLANK(R59),IF(ISBLANK(N59),J59/I59,N59/M59),R59/Q59) -> 0.30571992 | V59: =IF(AH59=0,"自查",IF(AND(AF59>AH59,AG59>AH59),"涨","波动")) -> 涨 | W59: =IF(T59<=0.1,"否","是") -> 否 | X59: 4.15w|96.40% | Y59: 0.548 | Z59: 女性 | AA59: 1 | AB59: 18-24岁|60.0% | AC59: 0.0007037037 | AD59: 30 | AE59: 0.2333 | AF59: =H59/3 -> 1246 | AG59: =L59/7 -> 1162.4286 | AH59: =P59/14 -> 582.07143 | AI59: =I59/3 -> 69.666667 | AJ59: =M59/7 -> 68.714286 | AK59: =Q59/14 -> 36.214286 | AL59: =(AF59-AH59)/AH59 -> 1.1406308 | AM59: =(AG59-AH59)/AH59 -> 0.99705485 | AN59: =(AI59-AK59)/AK59 -> 0.92373439 | AO59: =(AJ59-AK59)/AK59 -> 0.8974359
A60: 阿咩 | B60: hxcf_ | C60: 565176001 | D60: 2507913267@gq.com | G60: 3910 | H60: 1147 | I60: 80 | J60: 16 | K60: 10 | L60: 14715 | M60: 1741 | N60: 225 | O60: 28 | T60: =IF(ISBLANK(Q60),M60/L60,Q60/P60) -> 0.11831464 | U60: =IF(ISBLANK(R60),IF(ISBLANK(N60),J60/I60,N60/M60),R60/Q60) -> 0.12923607 | V60: =IF(AH60=0,"自查",IF(AND(AF60>AH60,AG60>AH60),"涨","波动")) -> 自查 | W60: =IF(T60<=0.1,"否","是") -> 是 | X60: 3,621|92.60% | Y60: 0.469 | Z60: 女性 | AA60: 0.786 | AB60: 18-24岁|59.6% | AC60: 0.00073611111 | AD60: 8 | AE60: 0.25 | AF60: =H60/3 -> 382.33333 | AG60: =L60/7 -> 2102.1429 | AH60: =P60/14 -> 0 | AI60: =I60/3 -> 26.666667 | AJ60: =M60/7 -> 248.71429 | AK60: =Q60/14 -> 0 | AL60: =(AF60-AH60)/AH60 -> #DIV/0! | AM60: =(AG60-AH60)/AH60 -> #DIV/0! | AN60: =(AI60-AK60)/AK60 -> #DIV/0! | AO60: =(AJ60-AK60)/AK60 -> #DIV/0!
A61: 阿咩 | B61: Rico | C61: lilacqgg | D61: iamg1an@163.com | T61: =IF(ISBLANK(Q61),M61/L61,Q61/P61) -> #DIV/0! | U61: =IF(ISBLANK(R61),IF(ISBLANK(N61),J61/I61,N61/M61),R61/Q61) -> #DIV/0! | V61: =IF(AH61=0,"自查",IF(AND(AF61>AH61,AG61>AH61),"涨","波动")) -> 自查 | W61: =IF(T61<=0.1,"否","是") -> #DIV/0! | AF61: =H61/3 -> 0 | AG61: =L61/7 -> 0 | AH61: =P61/14 -> 0 | AI61: =I61/3 -> 0 | AJ61: =M61/7 -> 0 | AK61: =Q61/14 -> 0 | AL61: =(AF61-AH61)/AH61 -> #DIV/0! | AM61: =(AG61-AH61)/AH61 -> #DIV/0! | AN61: =(AI61-AK61)/AK61 -> #DIV/0! | AO61: =(AJ61-AK61)/AK61 -> #DIV/0!
A62: 阿咩 | B62: 铈柿 | C62: 636162140 | D62: 1002563788@qq.com | G62: 1.78w | H62: 1112 | I62: 87 | J62: 14 | K62: 4 | L62: 2270 | M62: 190 | N62: 41 | O62: 8 | P62: 2305 | Q62: 169 | R62: 38 | S62: 8 | T62: =IF(ISBLANK(Q62),M62/L62,Q62/P62) -> 0.073318872 | U62: =IF(ISBLANK(R62),IF(ISBLANK(N62),J62/I62,N62/M62),R62/Q62) -> 0.22485207 | V62: =IF(AH62=0,"自查",IF(AND(AF62>AH62,AG62>AH62),"涨","波动")) -> 涨 | W62: =IF(T62<=0.1,"否","是") -> 否 | X62: --|-- | Y62: 0.171 | Z62: 女性 | AA62: 0.576 | AB62: 18-24岁|48.0% | AC62: 0.00072569444 | AD62: 19 | AE62: 0 | AF62: =H62/3 -> 370.66667 | AG62: =L62/7 -> 324.28571 | AH62: =P62/14 -> 164.64286 | AI62: =I62/3 -> 29 | AJ62: =M62/7 -> 27.142857 | AK62: =Q62/14 -> 12.071429 | AL62: =(AF62-AH62)/AH62 -> 1.2513377 | AM62: =(AG62-AH62)/AH62 -> 0.96963124 | AN62: =(AI62-AK62)/AK62 -> 1.4023669 | AO62: =(AJ62-AK62)/AK62 -> 1.2485207
A63: 阿咩 | B63: yuni | C63: 1061353336 | D63: feimi30@163.com | G63: 1.29w | H63: 8726 | I63: 894 | J63: 186 | K63: 9 | T63: =IF(ISBLANK(Q63),M63/L63,Q63/P63) -> #DIV/0! | U63: =IF(ISBLANK(R63),IF(ISBLANK(N63),J63/I63,N63/M63),R63/Q63) -> 0.20805369 | V63: =IF(AH63=0,"自查",IF(AND(AF63>AH63,AG63>AH63),"涨","波动")) -> 自查 | W63: =IF(T63<=0.1,"否","是") -> #DIV/0! | X63: 1.15w|89.10% | Y63: 0.405 | Z63: 男性 | AA63: 0.624 | AB63: 18-24岁|39.4% | AC63: 0.00069791667 | AD63: 4 | AE63: 0.25 | AF63: =H63/3 -> 2908.6667 | AG63: =L63/7 -> 0 | AH63: =P63/14 -> 0 | AI63: =I63/3 -> 298 | AJ63: =M63/7 -> 0 | AK63: =Q63/14 -> 0 | AL63: =(AF63-AH63)/AH63 -> #DIV/0! | AM63: =(AG63-AH63)/AH63 -> #DIV/0! | AN63: =(AI63-AK63)/AK63 -> #DIV/0! | AO63: =(AJ63-AK63)/AK63 -> #DIV/0!
A64: d | B64: 吃什么好呢 | C64: 8966656333 | D64: 762106332@qq.com | G64: 5423 | H64: 3908 | I64: 502 | J64: 79 | K64: 8 | L64: 2257 | M64: 276 | N64: 43 | O64: 7 | T64: =IF(ISBLANK(Q64),M64/L64,Q64/P64) -> 0.12228622 | U64: =IF(ISBLANK(R64),IF(ISBLANK(N64),J64/I64,N64/M64),R64/Q64) -> 0.1557971 | V64: =IF(AH64=0,"自查",IF(AND(AF64>AH64,AG64>AH64),"涨","波动")) -> 自查 | W64: =IF(T64<=0.1,"否","是") -> 是 | X64: 4,914|90.60% | Y64: 0.167 | Z64: 男性 | AA64: 0.766 | AB64: 25-34岁|44.9% | AC64: 0.00069907407 | AD64: 7 | AE64: 0.1429 | AF64: =H64/3 -> 1302.6667 | AG64: =L64/7 -> 322.42857 | AH64: =P64/14 -> 0 | AI64: =I64/3 -> 167.33333 | AJ64: =M64/7 -> 39.428571 | AK64: =Q64/14 -> 0 | AL64: =(AF64-AH64)/AH64 -> #DIV/0! | AM64: =(AG64-AH64)/AH64 -> #DIV/0! | AN64: =(AI64-AK64)/AK64 -> #DIV/0! | AO64: =(AJ64-AK64)/AK64 -> #DIV/0!
A65: 阿咩 | B65: 燎禾 | C65: Liaohe826 | D65: 15099716@qq.com | G65: 5423 | H65: 3908 | I65: 502 | J65: 79 | K65: 8 | L65: 2257 | M65: 276 | N65: 43 | O65: 7 | T65: =IF(ISBLANK(Q65),M65/L65,Q65/P65) -> 0.12228622 | U65: =IF(ISBLANK(R65),IF(ISBLANK(N65),J65/I65,N65/M65),R65/Q65) -> 0.1557971 | V65: =IF(AH65=0,"自查",IF(AND(AF65>AH65,AG65>AH65),"涨","波动")) -> 自查 | W65: =IF(T65<=0.1,"否","是") -> 是 | X65: 4,914|90.60% | Y65: 0.167 | Z65: 男性 | AA65: 0.766 | AB65: 25-34岁|44.9% | AC65: 0.00069907407 | AD65: 7 | AE65: 0.1429 | AF65: =H65/3 -> 1302.6667 | AG65: =L65/7 -> 322.42857 | AH65: =P65/14 -> 0 | AI65: =I65/3 -> 167.33333 | AJ65: =M65/7 -> 39.428571 | AK65: =Q65/14 -> 0 | AL65: =(AF65-AH65)/AH65 -> #DIV/0! | AM65: =(AG65-AH65)/AH65 -> #DIV/0! | AN65: =(AI65-AK65)/AK65 -> #DIV/0! | AO65: =(AJ65-AK65)/AK65 -> #DIV/0!
A66: 阿咩 | B66: 屎粑烟儿 | C66: 601657077 | D66: 1337934240@qq.com | G66: 5.60w | H66: 5600 | I66: 445 | J66: 55 | K66: 9 | L66: 9016 | M66: 666 | N66: 93 | O66: 11 | P66: 14368 | Q66: 1093 | R66: 156 | S66: 14 | T66: =IF(ISBLANK(Q66),M66/L66,Q66/P66) -> 0.076071826 | U66: =IF(ISBLANK(R66),IF(ISBLANK(N66),J66/I66,N66/M66),R66/Q66) -> 0.14272644 | V66: =IF(AH66=0,"自查",IF(AND(AF66>AH66,AG66>AH66),"涨","波动")) -> 涨 | W66: =IF(T66<=0.1,"否","是") -> 否 | X66: --|-- | Y66: 0.164 | Z66: 女性 | AA66: 0.916 | AB66: 18-24岁|68.2% | AC66: 0.00070138889 | AD66: 27 | AE66: 0.4074 | AF66: =H66/3 -> 1866.6667 | AG66: =L66/7 -> 1288 | AH66: =P66/14 -> 1026.2857 | AI66: =I66/3 -> 148.33333 | AJ66: =M66/7 -> 95.142857 | AK66: =Q66/14 -> 78.071429 | AL66: =(AF66-AH66)/AH66 -> 0.81885672 | AM66: =(AG66-AH66)/AH66 -> 0.25501114 | AN66: =(AI66-AK66)/AK66 -> 0.8999695 | AO66: =(AJ66-AK66)/AK66 -> 0.21866423
A67: 阿咩 | B67: 一罐蜜 | C67: 6735772801 | E67: yiguanmi01 | G67: 1.29w | H67: 21685 | I67: 1264 | J67: 356 | K67: 29 | T67: =IF(ISBLANK(Q67),M67/L67,Q67/P67) -> #DIV/0! | U67: =IF(ISBLANK(R67),IF(ISBLANK(N67),J67/I67,N67/M67),R67/Q67) -> 0.28164557 | V67: =IF(AH67=0,"自查",IF(AND(AF67>AH67,AG67>AH67),"涨","波动")) -> 自查 | W67: =IF(T67<=0.1,"否","是") -> #DIV/0! | X67: --|-- | Y67: 0.206 | Z67: 女性 | AA67: 0.957 | AB67: 18-24岁|64.0% | AC67: 0.00070138889 | AD67: 5 | AE67: 0.4 | AF67: =H67/3 -> 7228.3333 | AG67: =L67/7 -> 0 | AH67: =P67/14 -> 0 | AI67: =I67/3 -> 421.33333 | AJ67: =M67/7 -> 0 | AK67: =Q67/14 -> 0 | AL67: =(AF67-AH67)/AH67 -> #DIV/0! | AM67: =(AG67-AH67)/AH67 -> #DIV/0! | AN67: =(AI67-AK67)/AK67 -> #DIV/0! | AO67: =(AJ67-AK67)/AK67 -> #DIV/0!
A68: 阿咩 | B68: 那羊饲养员 | C68: 295796118 | D68: 1610076348@qq.com | G68: 4.91w | H68: 3574 | I68: 259 | J68: 25 | K68: 17 | L68: 4159 | M68: 302 | N68: 36 | O68: 16 | P68: 7203 | Q68: 557 | R68: 80 | S68: 18 | T68: =IF(ISBLANK(Q68),M68/L68,Q68/P68) -> 0.077328891 | U68: =IF(ISBLANK(R68),IF(ISBLANK(N68),J68/I68,N68/M68),R68/Q68) -> 0.14362657 | V68: =IF(AH68=0,"自查",IF(AND(AF68>AH68,AG68>AH68),"涨","波动")) -> 涨 | W68: =IF(T68<=0.1,"否","是") -> 否 | X68: 4.33w|88.20% | Y68: 0.381 | Z68: 女性 | AA68: 0.959 | AB68: 18-24岁|77.2% | AC68: 0.00070138889 | AD68: 24 | AE68: 0.2917 | AF68: =H68/3 -> 1191.3333 | AG68: =L68/7 -> 594.14286 | AH68: =P68/14 -> 514.5 | AI68: =I68/3 -> 86.333333 | AJ68: =M68/7 -> 43.142857 | AK68: =Q68/14 -> 39.785714 | AL68: =(AF68-AH68)/AH68 -> 1.3155167 | AM68: =(AG68-AH68)/AH68 -> 0.15479661 | AN68: =(AI68-AK68)/AK68 -> 1.1699581 | AO68: =(AJ68-AK68)/AK68 -> 0.08438061
A69: 阿咩 | B69: 豹纹芭比儿 | C69: tobeyourbarbie | G69: 9217 | H69: 2371 | I69: 109 | J69: 23 | K69: 33 | L69: 2595 | M69: 127 | N69: 25 | O69: 35 | P69: 2583 | Q69: 137 | R69: 27 | S69: 30 | T69: =IF(ISBLANK(Q69),M69/L69,Q69/P69) -> 0.053039102 | U69: =IF(ISBLANK(R69),IF(ISBLANK(N69),J69/I69,N69/M69),R69/Q69) -> 0.19708029 | V69: =IF(AH69=0,"自查",IF(AND(AF69>AH69,AG69>AH69),"涨","波动")) -> 涨 | W69: =IF(T69<=0.1,"否","是") -> 否 | X69: --|-- | Y69: 0.446 | Z69: 女性 | AA69: 0.955 | AB69: 18-24岁|63.3% | AC69: 0.00070138889 | AD69: 32 | AE69: 0 | AF69: =H69/3 -> 790.33333 | AG69: =L69/7 -> 370.71429 | AH69: =P69/14 -> 184.5 | AI69: =I69/3 -> 36.333333 | AJ69: =M69/7 -> 18.142857 | AK69: =Q69/14 -> 9.7857143 | AL69: =(AF69-AH69)/AH69 -> 3.2836495 | AM69: =(AG69-AH69)/AH69 -> 1.0092915 | AN69: =(AI69-AK69)/AK69 -> 2.7128954 | AO69: =(AJ69-AK69)/AK69 -> 0.8540146
A70: 阿咩 | B70: Chlxy | C70: 630061357 | D70: 1459874198@qq.com | G70: 1.88w | H70: 2601 | I70: 153 | J70: 36 | K70: 18 | L70: 3926 | M70: 274 | N70: 63 | O70: 22 | T70: =IF(ISBLANK(Q70),M70/L70,Q70/P70) -> 0.069791136 | U70: =IF(ISBLANK(R70),IF(ISBLANK(N70),J70/I70,N70/M70),R70/Q70) -> 0.22992701 | V70: =IF(AH70=0,"自查",IF(AND(AF70>AH70,AG70>AH70),"涨","波动")) -> 自查 | W70: =IF(T70<=0.1,"否","是") -> 否 | X70: --|-- | Y70: 0.182 | Z70: 女性 | AA70: 0.691 | AB70: 25-34岁|45.3% | AC70: 0.00069675926 | AD70: 12 | AE70: 0 | AF70: =H70/3 -> 867 | AG70: =L70/7 -> 560.85714 | AH70: =P70/14 -> 0 | AI70: =I70/3 -> 51 | AJ70: =M70/7 -> 39.142857 | AK70: =Q70/14 -> 0 | AL70: =(AF70-AH70)/AH70 -> #DIV/0! | AM70: =(AG70-AH70)/AH70 -> #DIV/0! | AN70: =(AI70-AK70)/AK70 -> #DIV/0! | AO70: =(AJ70-AK70)/AK70 -> #DIV/0!
A71: 阿咩 | B71: 阿头吃胖了 | C71: 503662358 | D71: atouaat@163.com | G71: 13.25w | H71: 53308 | I71: 4107 | J71: 696 | K71: 68 | T71: =IF(ISBLANK(Q71),M71/L71,Q71/P71) -> #DIV/0! | U71: =IF(ISBLANK(R71),IF(ISBLANK(N71),J71/I71,N71/M71),R71/Q71) -> 0.16946676 | V71: =IF(AH71=0,"自查",IF(AND(AF71>AH71,AG71>AH71),"涨","波动")) -> 自查 | W71: =IF(T71<=0.1,"否","是") -> #DIV/0! | X71: --|-- | Y71: 0.189 | Z71: 女性 | AA71: 0.958 | AB71: 18-24岁|69.4% | AC71: 0.00069675926 | AD71: 6 | AE71: 0.6667 | AF71: =H71/3 -> 17769.333 | AG71: =L71/7 -> 0 | AH71: =P71/14 -> 0 | AI71: =I71/3 -> 1369 | AJ71: =M71/7 -> 0 | AK71: =Q71/14 -> 0 | AL71: =(AF71-AH71)/AH71 -> #DIV/0! | AM71: =(AG71-AH71)/AH71 -> #DIV/0! | AN71: =(AI71-AK71)/AK71 -> #DIV/0! | AO71: =(AJ71-AK71)/AK71 -> #DIV/0!
A72: 阿咩 | B72: 是大美女耶 | C72: xu20040607 | T72: =IF(ISBLANK(Q72),M72/L72,Q72/P72) -> #DIV/0! | U72: =IF(ISBLANK(R72),IF(ISBLANK(N72),J72/I72,N72/M72),R72/Q72) -> #DIV/0! | V72: =IF(AH72=0,"自查",IF(AND(AF72>AH72,AG72>AH72),"涨","波动")) -> 自查 | W72: =IF(T72<=0.1,"否","是") -> #DIV/0! | AF72: =H72/3 -> 0 | AG72: =L72/7 -> 0 | AH72: =P72/14 -> 0 | AI72: =I72/3 -> 0 | AJ72: =M72/7 -> 0 | AK72: =Q72/14 -> 0 | AL72: =(AF72-AH72)/AH72 -> #DIV/0! | AM72: =(AG72-AH72)/AH72 -> #DIV/0! | AN72: =(AI72-AK72)/AK72 -> #DIV/0! | AO72: =(AJ72-AK72)/AK72 -> #DIV/0!
A73: 阿咩 | B73: KinSoymilk | C73: 186643304 | D73: 1287257853@qq.com | T73: =IF(ISBLANK(Q73),M73/L73,Q73/P73) -> #DIV/0! | U73: =IF(ISBLANK(R73),IF(ISBLANK(N73),J73/I73,N73/M73),R73/Q73) -> #DIV/0! | V73: =IF(AH73=0,"自查",IF(AND(AF73>AH73,AG73>AH73),"涨","波动")) -> 自查 | W73: =IF(T73<=0.1,"否","是") -> #DIV/0! | AF73: =H73/3 -> 0 | AG73: =L73/7 -> 0 | AH73: =P73/14 -> 0 | AI73: =I73/3 -> 0 | AJ73: =M73/7 -> 0 | AK73: =Q73/14 -> 0 | AL73: =(AF73-AH73)/AH73 -> #DIV/0! | AM73: =(AG73-AH73)/AH73 -> #DIV/0! | AN73: =(AI73-AK73)/AK73 -> #DIV/0! | AO73: =(AJ73-AK73)/AK73 -> #DIV/0!
A74: 阿咩 | B74: yangkaki | C74: 279596151 | D74: ykkkaki@qq.com | G74: 2812 | H74: 7968 | I74: 574 | J74: 36 | K74: 14 | T74: =IF(ISBLANK(Q74),M74/L74,Q74/P74) -> #DIV/0! | U74: =IF(ISBLANK(R74),IF(ISBLANK(N74),J74/I74,N74/M74),R74/Q74) -> 0.06271777 | V74: =IF(AH74=0,"自查",IF(AND(AF74>AH74,AG74>AH74),"涨","波动")) -> 自查 | W74: =IF(T74<=0.1,"否","是") -> #DIV/0! | X74: 2,531|90.00% | Y74: 0.376 | Z74: 女性 | AA74: 0.653 | AB74: 18-24岁|58.6% | AC74: 0.00070833333 | AD74: 6 | AE74: 0.1667 | AF74: =H74/3 -> 2656 | AG74: =L74/7 -> 0 | AH74: =P74/14 -> 0 | AI74: =I74/3 -> 191.33333 | AJ74: =M74/7 -> 0 | AK74: =Q74/14 -> 0 | AL74: =(AF74-AH74)/AH74 -> #DIV/0! | AM74: =(AG74-AH74)/AH74 -> #DIV/0! | AN74: =(AI74-AK74)/AK74 -> #DIV/0! | AO74: =(AJ74-AK74)/AK74 -> #DIV/0!
A75: 阿咩 | B75: 是yyy啊 | C75: 334024207 | D75: 1440288307@qq.com | G75: 6906 | H75: 13901 | I75: 1762 | J75: 142 | K75: 41 | T75: =IF(ISBLANK(Q75),M75/L75,Q75/P75) -> #DIV/0! | U75: =IF(ISBLANK(R75),IF(ISBLANK(N75),J75/I75,N75/M75),R75/Q75) -> 0.080590238 | V75: =IF(AH75=0,"自查",IF(AND(AF75>AH75,AG75>AH75),"涨","波动")) -> 自查 | W75: =IF(T75<=0.1,"否","是") -> #DIV/0! | X75: 5,857|84.80% | Y75: 0.144 | Z75: 女性 | AA75: 0.883 | AB75: 18-24岁|65.9% | AC75: 0.0007037037 | AD75: 3 | AE75: 0.3333 | AF75: =H75/3 -> 4633.6667 | AG75: =L75/7 -> 0 | AH75: =P75/14 -> 0 | AI75: =I75/3 -> 587.33333 | AJ75: =M75/7 -> 0 | AK75: =Q75/14 -> 0 | AL75: =(AF75-AH75)/AH75 -> #DIV/0! | AM75: =(AG75-AH75)/AH75 -> #DIV/0! | AN75: =(AI75-AK75)/AK75 -> #DIV/0! | AO75: =(AJ75-AK75)/AK75 -> #DIV/0!
A76: 阿咩 | B76: 半条枪 | C76: FanYL_ | D76: 2747670756@qq.com | G76: 1.67w | H76: 2898 | I76: 239 | J76: 17 | K76: 8 | L76: 2816 | M76: 220 | N76: 23 | O76: 9 | P76: 3047 | Q76: 230 | R76: 26 | S76: 10 | T76: =IF(ISBLANK(Q76),M76/L76,Q76/P76) -> 0.075484083 | U76: =IF(ISBLANK(R76),IF(ISBLANK(N76),J76/I76,N76/M76),R76/Q76) -> 0.11304348 | V76: =IF(AH76=0,"自查",IF(AND(AF76>AH76,AG76>AH76),"涨","波动")) -> 涨 | W76: =IF(T76<=0.1,"否","是") -> 否 | X76: 1.56w|93.40% | Y76: 0.507 | Z76: 女性 | AA76: 0.914 | AB76: 18-24岁|74.5% | AC76: 0.0007037037 | AD76: 43 | AE76: 0.0465 | AF76: =H76/3 -> 966 | AG76: =L76/7 -> 402.28571 | AH76: =P76/14 -> 217.64286 | AI76: =I76/3 -> 79.666667 | AJ76: =M76/7 -> 31.428571 | AK76: =Q76/14 -> 16.428571 | AL76: =(AF76-AH76)/AH76 -> 3.4384641 | AM76: =(AG76-AH76)/AH76 -> 0.84837545 | AN76: =(AI76-AK76)/AK76 -> 3.8492754 | AO76: =(AJ76-AK76)/AK76 -> 0.91304348
